Workbook
Name S1Name: Inputs!$A$11
Name S1Alloc: Inputs!$C$11
Name S1Ret: Inputs!$D$11
Name S1Yld: Inputs!$E$11
Name S1Type: Inputs!$F$11
Name S1NR: Inputs!$G$11
Name S1TF: Inputs!$H$11
Name S1RR: Inputs!$I$11
Name S2Name: Inputs!$A$12
Name S2Alloc: Inputs!$C$12
Name S2Ret: Inputs!$D$12
Name S2Yld: Inputs!$E$12
Name S2Type: Inputs!$F$12
Name S2NR: Inputs!$G$12
Name S2TF: Inputs!$H$12
Name S2RR: Inputs!$I$12
Name S3Name: Inputs!$A$13
Name S3Alloc: Inputs!$C$13
Name S3Ret: Inputs!$D$13
Name S3Yld: Inputs!$E$13
Name S3Type: Inputs!$F$13
Name S3NR: Inputs!$G$13
Name S3TF: Inputs!$H$13
Name S3RR: Inputs!$I$13
Name S4Name: Inputs!$A$14
Name S4Alloc: Inputs!$C$14
Name S4Ret: Inputs!$D$14
Name S4Yld: Inputs!$E$14
Name S4Type: Inputs!$F$14
Name S4NR: Inputs!$G$14
Name S4TF: Inputs!$H$14
Name S4RR: Inputs!$I$14
Name S5Name: Inputs!$A$15
Name S5Alloc: Inputs!$C$15
Name S5Ret: Inputs!$D$15
Name S5Yld: Inputs!$E$15
Name S5Type: Inputs!$F$15
Name S5NR: Inputs!$G$15
Name S5TF: Inputs!$H$15
Name S5RR: Inputs!$I$15
Name S6Name: Inputs!$A$16
Name S6Alloc: Inputs!$C$16
Name S6Ret: Inputs!$D$16
Name S6Yld: Inputs!$E$16
Name S6Type: Inputs!$F$16
Name S6NR: Inputs!$G$16
Name S6TF: Inputs!$H$16
Name S6RR: Inputs!$I$16
Name HorizonM: Inputs!$B$45
Name HorizonY: Inputs!$B$46
Name ContribMonthly: Inputs!$B$47
Name CStartEff: Inputs!$B$48
Name CEndEff: Inputs!$B$49
Name WdMonthlyBase: Inputs!$B$50
Name WdStartEff: Inputs!$B$51
Name WdEndEff: Inputs!$B$52
Name RankNR: Inputs!$B$53
Name RankTF: Inputs!$B$54
Name RankRR: Inputs!$B$55
Name DS1: Inputs!$B$56

Sheet Dashboard
B1: Portfolio, Withdrawal & Tax Planner — Dashboard
B2: Canada (Ontario) · monthly engine · tax year 2026 rules. Edit the yellow cells on the Inputs tab; everything here updates automatically.
B4: Selected year | C4: 8 | D4: ="of "&HorizonY&" years" | F4: Key inputs (change on the Inputs tab): | M4: =MIN(MAX(1,N(SelYear)),HorizonY)
F5: ="Withdrawal: "&TEXT(N(WdAmt),"$#,##0")&" "&WdFreq&" from month "&WdStartEff
F6: ="Horizon: "&HorizonY&" yrs · Return override: "&TEXT(N(RetOverride),"+0.0%;-0.0%;0%")
B8: PORTFOLIO BALANCE | F8: TOTAL WITHDRAWN | J8: TOTAL TAX PAID (standalone)
B9: =INDEX('Projection'!$AA$4:$AA$53,SelYearEff) | F9: =INDEX('Projection'!$AB$4:$AB$53,SelYearEff) | J9: =SUMIFS('Tax Estimate'!$S$4:$S$53,'Tax Estimate'!$A$4:$A$53,"<="&SelYearEff)
B11: ="at end of year "&SelYearEff | F11: ="to date · "&TEXT(INDEX('Projection'!$Y$4:$Y$53,SelYearEff),"$#,##0")&" in year "&SelYearEff | J11: ="to date · stacked view adds "&TEXT(SUMIFS('Tax Estimate'!$AD$4:$AD$53,'Tax Estimate'!$A$4:$A$53,"<="&SelYearEff),"$#,##0")&" on top of other income"
B14: DIVIDENDS RECEIVED | F14: NET AFTER-TAX RETURN (annualized) | J14: PORTFOLIO LONGEVITY
B15: =SUMIFS('Projection'!$X$4:$X$53,'Projection'!$A$4:$A$53,"<="&SelYearEff) | F15: =IFERROR(POWER((INDEX('Projection'!$AA$4:$AA$53,SelYearEff)+INDEX('Projection'!$AB$4:$AB$53,SelYearEff)-SUMIFS('Tax Estimate'!$S$4:$S$53,'Tax Estimate'!$A$4:$A$53,"<="&SelYearEff))/(N(StartValue)+SUMIFS('Projection'!$V$4:$V$53,'Projection'!$A$4:$A$53,"<="&SelYearEff)),1/SelYearEff)-1,0) | J15: =IFERROR("Depletes in year "&(INT((MATCH(1,'Engine (Monthly)'!$DB$4:$DB$603,0)-1)/12)+1)&" ⚠","Lasts the full horizon ✅")
B17: ="all accounts, to end of year "&SelYearEff | F17: ="growth + dividends − tax, on money invested, to year "&SelYearEff | J17: ="the single most important wellbeing number"
B20: Sensitivity — expected return ±1%
C21: Return −1% | D21: Base plan | E21: Return +1%
B22: Ending balance | C22: =INDEX('Engine (-1%)'!$CX$3:$CX$603,HorizonM+1) | D22: =INDEX('Engine (Monthly)'!$CX$3:$CX$603,HorizonM+1) | E22: =INDEX('Engine (+1%)'!$CX$3:$CX$603,HorizonM+1)
B23: Depletes | C23: =IFERROR("Year "&(INT((MATCH(1,'Engine (-1%)'!$DB$4:$DB$603,0)-1)/12)+1)&" ⚠","Never (lasts)") | D23: =IFERROR("Year "&(INT((MATCH(1,'Engine (Monthly)'!$DB$4:$DB$603,0)-1)/12)+1)&" ⚠","Never (lasts)") | E23: =IFERROR("Year "&(INT((MATCH(1,'Engine (+1%)'!$DB$4:$DB$603,0)-1)/12)+1)&" ⚠","Never (lasts)")

Sheet Inputs
A1: Inputs — fill the yellow cells only
A2: Everything else in this workbook recalculates automatically. Grey cells are computed — do not edit.
A3: 1 · Portfolio setup
A4: Current total portfolio value (CAD) | B4: 500000 | D4: Market value of all accounts today.
A5: Projection horizon | B5: 20 | C5: Years | D5: Number + unit. Engine runs monthly (max 50 years).
A6: Annual inflation assumption | B6: 0.02 | D6: Used for withdrawal indexing and the real-dollar view.
A7: Expected-return override (± all sub-sections) | B7: 0 | D7: Adds to every sub-section's return. Leave 0% normally; scenario table uses ±1% around this.
A9: 2 · Sub-portfolio allocation (up to 6)
A10: Name | B10: Risk | C10: Alloc % | D10: Return %/yr (ex-div) | E10: Dividend yield %/yr | F10: Dividend type | G10: % Non-Reg | H10: % TFSA | I10: % RRSP/RRIF | J10: Row check
A11: Canadian Dividend Stocks | B11: Medium | C11: 0.3 | D11: 0.04 | E11: 0.04 | F11: Eligible | G11: 0.6 | H11: 0.2 | I11: 0.2 | J11: =IF(N($C11)=0,"",IF(ABS(N($G11)+N($H11)+N($I11)-1)<0.0001,"✓","⚠ accounts must total 100%"))
A12: US / Global Growth Equities | B12: High | C12: 0.3 | D12: 0.07 | E12: 0.012 | F12: Foreign / interest | G12: 0.4 | H12: 0.3 | I12: 0.3 | J12: =IF(N($C12)=0,"",IF(ABS(N($G12)+N($H12)+N($I12)-1)<0.0001,"✓","⚠ accounts must total 100%"))
A13: Bonds & GICs | B13: Low | C13: 0.25 | D13: 0.015 | E13: 0.035 | F13: Foreign / interest | G13: 0.2 | H13: 0.2 | I13: 0.6 | J13: =IF(N($C13)=0,"",IF(ABS(N($G13)+N($H13)+N($I13)-1)<0.0001,"✓","⚠ accounts must total 100%"))
A14: Canadian REITs | B14: Medium | C14: 0.15 | D14: 0.03 | E14: 0.045 | F14: Non-eligible | G14: 0.3 | H14: 0.4 | I14: 0.3 | J14: =IF(N($C14)=0,"",IF(ABS(N($G14)+N($H14)+N($I14)-1)<0.0001,"✓","⚠ accounts must total 100%"))
C15: 0 | D15: 0 | E15: 0 | F15: Eligible | G15: 0 | H15: 0 | I15: 0 | J15: =IF(N($C15)=0,"",IF(ABS(N($G15)+N($H15)+N($I15)-1)<0.0001,"✓","⚠ accounts must total 100%"))
C16: 0 | D16: 0 | E16: 0 | F16: Eligible | G16: 0 | H16: 0 | I16: 0 | J16: =IF(N($C16)=0,"",IF(ABS(N($G16)+N($H16)+N($I16)-1)<0.0001,"✓","⚠ accounts must total 100%"))
A17: Allocation check: | C17: =SUM(C11:C16) | E17: =IF(ABS(SUM($C$11:$C$16)-1)<0.0001,"✓ Allocations total 100%","⚠ Allocations must total 100% — currently "&TEXT(SUM($C$11:$C$16),"0.0%"))
A19: 3 · Contributions
A20: Contribution amount (CAD) | B20: 500 | D20: Per period (see frequency).
A21: Frequency | B21: Bi-weekly | D21: Weekly ×52/12, bi-weekly ×26/12 → monthly equivalent.
A22: Start month (1 = first month) | B22: 1
A23: End month (blank = end of horizon) | B23: 60 | D23: Many planners stop contributing when withdrawals start.
A24: Annual contribution escalation | B24: 0.03 | D24: Contribution grows this much every 12 months.
A25: Contribution destination | B25: Follow allocation % | D25: Or route 100% to one named sub-section.
A27: 4 · Withdrawals
A28: Withdrawal amount (CAD) | B28: 2000 | D28: Per period (see frequency).
A29: Frequency | B29: Monthly | D29: Bi-weekly ×26/12; Annual = withdrawn once every 12th month.
A30: Start month | B30: 61 | D30: e.g. 61 = start of year 6.
A31: End month (blank = end of horizon)
A32: Index withdrawals to inflation? | B32: Yes | D32: Steps up once per year by the inflation assumption.
A33: Funding order — 1st account drawn | B33: Non-Registered | D33: That month's dividends/cash in the account are used first,
A34: Funding order — 2nd account drawn | B34: TFSA | D34: then assets are sold pro-rata across its sub-sections.
A35: Funding order — 3rd account drawn | B35: RRSP/RRIF | D35: Each account must appear exactly once.
A36: Order check: | B36: =IF(AND(COUNTIF($B$33:$B$35,"Non-Registered")=1,COUNTIF($B$33:$B$35,"TFSA")=1,COUNTIF($B$33:$B$35,"RRSP/RRIF")=1),"✓ OK","⚠ each account exactly once")
A38: 5 · Tax settings
A39: Province | B39: Ontario | D39: Fixed for now; tax tables on the Assumptions tab are structured so other provinces can be added.
A40: Other annual taxable income (CAD) | B40: 60000 | D40: Used only for the "stacked" tax view.
A41: ACB today, as % of non-registered value | B41: 0.7 | D41: Adjusted cost base — gains are taxed on sale proceeds minus cost base.
A42: Reinvest dividends when not withdrawing? | B42: Yes | D42: If No, unused dividends accumulate as cash (0% return) in the account.
A44: Calculated values (do not edit) | L44: Destination options
A45: Horizon (months) | B45: =MIN(600,MAX(1,IF($C$5="Years",N($B$5)*12,N($B$5)))) | L45: Follow allocation %
A46: Horizon (years, rounded up) | B46: =ROUNDUP(HorizonM/12,0) | L46: =IF(S1Name="","",S1Name)
A47: Contribution / month | B47: =N($B$20)*IF($B$21="Weekly",52/12,IF($B$21="Bi-weekly",26/12,1)) | L47: =IF(S2Name="","",S2Name)
A48: Contribution start (effective) | B48: =IF(N($B$22)<1,1,$B$22) | L48: =IF(S3Name="","",S3Name)
A49: Contribution end (effective) | B49: =IF(N($B$23)<1,HorizonM,MIN($B$23,HorizonM)) | L49: =IF(S4Name="","",S4Name)
A50: Withdrawal / month (non-annual) | B50: =N($B$28)*IF($B$29="Bi-weekly",26/12,1) | L50: =IF(S5Name="","",S5Name)
A51: Withdrawal start (effective) | B51: =IF(N($B$30)<1,1,$B$30) | L51: =IF(S6Name="","",S6Name)
A52: Withdrawal end (effective) | B52: =IF(N($B$31)<1,HorizonM,MIN($B$31,HorizonM))
A53: Rank: Non-Registered | B53: =IFERROR(MATCH("Non-Registered",$B$33:$B$35,0),99)
A54: Rank: TFSA | B54: =IFERROR(MATCH("TFSA",$B$33:$B$35,0),99)
A55: Rank: RRSP/RRIF | B55: =IFERROR(MATCH("RRSP/RRIF",$B$33:$B$35,0),99)
A56: Contribution share → sub 1 | B56: =IF($B$25="Follow allocation %",N(S1Alloc),IF(AND(S1Name<>"",$B$25=S1Name),1,0))
A57: Contribution share → sub 2 | B57: =IF($B$25="Follow allocation %",N(S2Alloc),IF(AND(S2Name<>"",$B$25=S2Name),1,0))
A58: Contribution share → sub 3 | B58: =IF($B$25="Follow allocation %",N(S3Alloc),IF(AND(S3Name<>"",$B$25=S3Name),1,0))
A59: Contribution share → sub 4 | B59: =IF($B$25="Follow allocation %",N(S4Alloc),IF(AND(S4Name<>"",$B$25=S4Name),1,0))
A60: Contribution share → sub 5 | B60: =IF($B$25="Follow allocation %",N(S5Alloc),IF(AND(S5Name<>"",$B$25=S5Name),1,0))
A61: Contribution share → sub 6 | B61: =IF($B$25="Follow allocation %",N(S6Alloc),IF(AND(S6Name<>"",$B$25=S6Name),1,0))

Sheet Projection
A1: Projection — annual summary (all figures trace to the monthly Engine)
C2: Non-Registered | I2: TFSA | O2: RRSP/RRIF | U2: Total | AB2: Withdrawals Summary (cumulative)
A3: Year | B3: · | C3: Opening | D3: Contributions | E3: Growth | F3: Dividends | G3: Withdrawn | H3: Closing | I3: Opening | J3: Contributions | K3: Growth | L3: Dividends | M3: Withdrawn | N3: Closing | O3: Opening | P3: Contributions | Q3: Growth | R3: Dividends | S3: Withdrawn | T3: Closing | U3: Opening | V3: Contributions | W3: Growth | X3: Dividends | Y3: Withdrawn | Z3: Tax (standalone) | AA3: Closing | AB3: Total withdrawn | AC3: Funded by dividends/cash | AD3: Funded by asset sales | AE3: Realized gains | AF3: Status
A4: 1 | B4: =IF($A4<=HorizonY,1,0) | C4: =IF($B4=0,"",INDEX('Engine (Monthly)'!$AI$3:$AI$603,MIN(($A4-1)*12,HorizonM)+1)) | D4: =IF($B4=0,"",SUMIFS('Engine (Monthly)'!$X$4:$X$603,'Engine (Monthly)'!$C$4:$C$603,$A4)) | E4: =IF($B4=0,"",SUMIFS('Engine (Monthly)'!$AA$4:$AA$603,'Engine (Monthly)'!$C$4:$C$603,$A4)) | F4: =IF($B4=0,"",SUMIFS('Engine (Monthly)'!$Z$4:$Z$603,'Engine (Monthly)'!$C$4:$C$603,$A4)) | G4: =IF($B4=0,"",SUMIFS('Engine (Monthly)'!$AD$4:$AD$603,'Engine (Monthly)'!$C$4:$C$603,$A4)) | H4: =IF($B4=0,"",INDEX('Engine (Monthly)'!$AI$3:$AI$603,MIN($A4*12,HorizonM)+1)) | I4: =IF($B4=0,"",INDEX('Engine (Monthly)'!$BM$3:$BM$603,MIN(($A4-1)*12,HorizonM)+1)) | J4: =IF($B4=0,"",SUMIFS('Engine (Monthly)'!$BB$4:$BB$603,'Engine (Monthly)'!$C$4:$C$603,$A4)) | K4: =IF($B4=0,"",SUMIFS('Engine (Monthly)'!$BE$4:$BE$603,'Engine (Monthly)'!$C$4:$C$603,$A4)) | L4: =IF($B4=0,"",SUMIFS('Engine (Monthly)'!$BD$4:$BD$603,'Engine (Monthly)'!$C$4:$C$603,$A4)) | M4: =IF($B4=0,"",SUMIFS('Engine (Monthly)'!$BH$4:$BH$603,'Engine (Monthly)'!$C$4:$C$603,$A4)) | N4: =IF($B4=0,"",INDEX('Engine (Monthly)'!$BM$3:$BM$603,MIN($A4*12,HorizonM)+1)) | O4: =IF($B4=0,"",INDEX('Engine (Monthly)'!$CQ$3:$CQ$603,MIN(($A4-1)*12,HorizonM)+1)) | P4: =IF($B4=0,"",SUMIFS('Engine (Monthly)'!$CF$4:$CF$603,'Engine (Monthly)'!$C$4:$C$603,$A4)) | Q4: =IF($B4=0,"",SUMIFS('Engine (Monthly)'!$CI$4:$CI$603,'Engine (Monthly)'!$C$4:$C$603,$A4)) | R4: =IF($B4=0,"",SUMIFS('Engine (Monthly)'!$CH$4:$CH$603,'Engine (Monthly)'!$C$4:$C$603,$A4)) | S4: =IF($B4=0,"",SUMIFS('Engine (Monthly)'!$CL$4:$CL$603,'Engine (Monthly)'!$C$4:$C$603,$A4)) | T4: =IF($B4=0,"",INDEX('Engine (Monthly)'!$CQ$3:$CQ$603,MIN($A4*12,HorizonM)+1)) | U4: =IF($B4=0,"",$C4+$I4+$O4) | V4: =IF($B4=0,"",$D4+$J4+$P4) | W4: =IF($B4=0,"",$E4+$K4+$Q4) | X4: =IF($B4=0,"",$F4+$L4+$R4) | Y4: =IF($B4=0,"",$G4+$M4+$S4) | Z4: =IF($B4=0,"",'Tax Estimate'!$S4) | AA4: =IF($B4=0,"",$H4+$N4+$T4) | AB4: =IF($B4=0,"",SUMIFS('Engine (Monthly)'!$CY$4:$CY$603,'Engine (Monthly)'!$C$4:$C$603,"<="&$A4)) | AC4: =IF($B4=0,"",SUMIFS('Engine (Monthly)'!$CZ$4:$CZ$603,'Engine (Monthly)'!$C$4:$C$603,"<="&$A4)) | AD4: =IF($B4=0,"",SUMIFS('Engine (Monthly)'!$DA$4:$DA$603,'Engine (Monthly)'!$C$4:$C$603,"<="&$A4)) | AE4: =IF($B4=0,"",SUMIFS('Engine (Monthly)'!$CV$4:$CV$603,'Engine (Monthly)'!$C$4:$C$603,"<="&$A4)) | AF4: =IF($B4=0,"",IF(COUNTIFS('Engine (Monthly)'!$C$4:$C$603,$A4,'Engine (Monthly)'!$DB$4:$DB$603,1)>0,"⚠ shortfall","OK"))
A5: 2 | B5: =IF($A5<=HorizonY,1,0) | C5: =IF($B5=0,"",INDEX('Engine (Monthly)'!$AI$3:$AI$603,MIN(($A5-1)*12,HorizonM)+1)) | D5: =IF($B5=0,"",SUMIFS('Engine (Monthly)'!$X$4:$X$603,'Engine (Monthly)'!$C$4:$C$603,$A5)) | E5: =IF($B5=0,"",SUMIFS('Engine (Monthly)'!$AA$4:$AA$603,'Engine (Monthly)'!$C$4:$C$603,$A5)) | F5: =IF($B5=0,"",SUMIFS('Engine (Monthly)'!$Z$4:$Z$603,'Engine (Monthly)'!$C$4:$C$603,$A5)) | G5: =IF($B5=0,"",SUMIFS('Engine (Monthly)'!$AD$4:$AD$603,'Engine (Monthly)'!$C$4:$C$603,$A5)) | H5: =IF($B5=0,"",INDEX('Engine (Monthly)'!$AI$3:$AI$603,MIN($A5*12,HorizonM)+1)) | I5: =IF($B5=0,"",INDEX('Engine (Monthly)'!$BM$3:$BM$603,MIN(($A5-1)*12,HorizonM)+1)) | J5: =IF($B5=0,"",SUMIFS('Engine (Monthly)'!$BB$4:$BB$603,'Engine (Monthly)'!$C$4:$C$603,$A5)) | K5: =IF($B5=0,"",SUMIFS('Engine (Monthly)'!$BE$4:$BE$603,'Engine (Monthly)'!$C$4:$C$603,$A5)) | L5: =IF($B5=0,"",SUMIFS('Engine (Monthly)'!$BD$4:$BD$603,'Engine (Monthly)'!$C$4:$C$603,$A5)) | M5: =IF($B5=0,"",SUMIFS('Engine (Monthly)'!$BH$4:$BH$603,'Engine (Monthly)'!$C$4:$C$603,$A5)) | N5: =IF($B5=0,"",INDEX('Engine (Monthly)'!$BM$3:$BM$603,MIN($A5*12,HorizonM)+1)) | O5: =IF($B5=0,"",INDEX('Engine (Monthly)'!$CQ$3:$CQ$603,MIN(($A5-1)*12,HorizonM)+1)) | P5: =IF($B5=0,"",SUMIFS('Engine (Monthly)'!$CF$4:$CF$603,'Engine (Monthly)'!$C$4:$C$603,$A5)) | Q5: =IF($B5=0,"",SUMIFS('Engine (Monthly)'!$CI$4:$CI$603,'Engine (Monthly)'!$C$4:$C$603,$A5)) | R5: =IF($B5=0,"",SUMIFS('Engine (Monthly)'!$CH$4:$CH$603,'Engine (Monthly)'!$C$4:$C$603,$A5)) | S5: =IF($B5=0,"",SUMIFS('Engine (Monthly)'!$CL$4:$CL$603,'Engine (Monthly)'!$C$4:$C$603,$A5)) | T5: =IF($B5=0,"",INDEX('Engine (Monthly)'!$CQ$3:$CQ$603,MIN($A5*12,HorizonM)+1)) | U5: =IF($B5=0,"",$C5+$I5+$O5) | V5: =IF($B5=0,"",$D5+$J5+$P5) | W5: =IF($B5=0,"",$E5+$K5+$Q5) | X5: =IF($B5=0,"",$F5+$L5+$R5) | Y5: =IF($B5=0,"",$G5+$M5+$S5) | Z5: =IF($B5=0,"",'Tax Estimate'!$S5) | AA5: =IF($B5=0,"",$H5+$N5+$T5) | AB5: =IF($B5=0,"",SUMIFS('Engine (Monthly)'!$CY$4:$CY$603,'Engine (Monthly)'!$C$4:$C$603,"<="&$A5)) | AC5: =IF($B5=0,"",SUMIFS('Engine (Monthly)'!$CZ$4:$CZ$603,'Engine (Monthly)'!$C$4:$C$603,"<="&$A5)) | AD5: =IF($B5=0,"",SUMIFS('Engine (Monthly)'!$DA$4:$DA$603,'Engine (Monthly)'!$C$4:$C$603,"<="&$A5)) | AE5: =IF($B5=0,"",SUMIFS('Engine (Monthly)'!$CV$4:$CV$603,'Engine (Monthly)'!$C$4:$C$603,"<="&$A5)) | AF5: =IF($B5=0,"",IF(COUNTIFS('Engine (Monthly)'!$C$4:$C$603,$A5,'Engine (Monthly)'!$DB$4:$DB$603,1)>0,"⚠ shortfall","OK"))
A6: 3 | B6: =IF($A6<=HorizonY,1,0) | C6: =IF($B6=0,"",INDEX('Engine (Monthly)'!$AI$3:$AI$603,MIN(($A6-1)*12,HorizonM)+1)) | D6: =IF($B6=0,"",SUMIFS('Engine (Monthly)'!$X$4:$X$603,'Engine (Monthly)'!$C$4:$C$603,$A6)) | E6: =IF($B6=0,"",SUMIFS('Engine (Monthly)'!$AA$4:$AA$603,'Engine (Monthly)'!$C$4:$C$603,$A6)) | F6: =IF($B6=0,"",SUMIFS('Engine (Monthly)'!$Z$4:$Z$603,'Engine (Monthly)'!$C$4:$C$603,$A6)) | G6: =IF($B6=0,"",SUMIFS('Engine (Monthly)'!$AD$4:$AD$603,'Engine (Monthly)'!$C$4:$C$603,$A6)) | H6: =IF($B6=0,"",INDEX('Engine (Monthly)'!$AI$3:$AI$603,MIN($A6*12,HorizonM)+1)) | I6: =IF($B6=0,"",INDEX('Engine (Monthly)'!$BM$3:$BM$603,MIN(($A6-1)*12,HorizonM)+1)) | J6: =IF($B6=0,"",SUMIFS('Engine (Monthly)'!$BB$4:$BB$603,'Engine (Monthly)'!$C$4:$C$603,$A6)) | K6: =IF($B6=0,"",SUMIFS('Engine (Monthly)'!$BE$4:$BE$603,'Engine (Monthly)'!$C$4:$C$603,$A6)) | L6: =IF($B6=0,"",SUMIFS('Engine (Monthly)'!$BD$4:$BD$603,'Engine (Monthly)'!$C$4:$C$603,$A6)) | M6: =IF($B6=0,"",SUMIFS('Engine (Monthly)'!$BH$4:$BH$603,'Engine (Monthly)'!$C$4:$C$603,$A6)) | N6: =IF($B6=0,"",INDEX('Engine (Monthly)'!$BM$3:$BM$603,MIN($A6*12,HorizonM)+1)) | O6: =IF($B6=0,"",INDEX('Engine (Monthly)'!$CQ$3:$CQ$603,MIN(($A6-1)*12,HorizonM)+1)) | P6: =IF($B6=0,"",SUMIFS('Engine (Monthly)'!$CF$4:$CF$603,'Engine (Monthly)'!$C$4:$C$603,$A6)) | Q6: =IF($B6=0,"",SUMIFS('Engine (Monthly)'!$CI$4:$CI$603,'Engine (Monthly)'!$C$4:$C$603,$A6)) | R6: =IF($B6=0,"",SUMIFS('Engine (Monthly)'!$CH$4:$CH$603,'Engine (Monthly)'!$C$4:$C$603,$A6)) | S6: =IF($B6=0,"",SUMIFS('Engine (Monthly)'!$CL$4:$CL$603,'Engine (Monthly)'!$C$4:$C$603,$A6)) | T6: =IF($B6=0,"",INDEX('Engine (Monthly)'!$CQ$3:$CQ$603,MIN($A6*12,HorizonM)+1)) | U6: =IF($B6=0,"",$C6+$I6+$O6) | V6: =IF($B6=0,"",$D6+$J6+$P6) | W6: =IF($B6=0,"",$E6+$K6+$Q6) | X6: =IF($B6=0,"",$F6+$L6+$R6) | Y6: =IF($B6=0,"",$G6+$M6+$S6) | Z6: =IF($B6=0,"",'Tax Estimate'!$S6) | AA6: =IF($B6=0,"",$H6+$N6+$T6) | AB6: =IF($B6=0,"",SUMIFS('Engine (Monthly)'!$CY$4:$CY$603,'Engine (Monthly)'!$C$4:$C$603,"<="&$A6)) | AC6: =IF($B6=0,"",SUMIFS('Engine (Monthly)'!$CZ$4:$CZ$603,'Engine (Monthly)'!$C$4:$C$603,"<="&$A6)) | AD6: =IF($B6=0,"",SUMIFS('Engine (Monthly)'!$DA$4:$DA$603,'Engine (Monthly)'!$C$4:$C$603,"<="&$A6)) | AE6: =IF($B6=0,"",SUMIFS('Engine (Monthly)'!$CV$4:$CV$603,'Engine (Monthly)'!$C$4:$C$603,"<="&$A6)) | AF6: =IF($B6=0,"",IF(COUNTIFS('Engine (Monthly)'!$C$4:$C$603,$A6,'Engine (Monthly)'!$DB$4:$DB$603,1)>0,"⚠ shortfall","OK"))
A7: 4 | B7: =IF($A7<=HorizonY,1,0) | C7: =IF($B7=0,"",INDEX('Engine (Monthly)'!$AI$3:$AI$603,MIN(($A7-1)*12,HorizonM)+1)) | D7: =IF($B7=0,"",SUMIFS('Engine (Monthly)'!$X$4:$X$603,'Engine (Monthly)'!$C$4:$C$603,$A7)) | E7: =IF($B7=0,"",SUMIFS('Engine (Monthly)'!$AA$4:$AA$603,'Engine (Monthly)'!$C$4:$C$603,$A7)) | F7: =IF($B7=0,"",SUMIFS('Engine (Monthly)'!$Z$4:$Z$603,'Engine (Monthly)'!$C$4:$C$603,$A7)) | G7: =IF($B7=0,"",SUMIFS('Engine (Monthly)'!$AD$4:$AD$603,'Engine (Monthly)'!$C$4:$C$603,$A7)) | H7: =IF($B7=0,"",INDEX('Engine (Monthly)'!$AI$3:$AI$603,MIN($A7*12,HorizonM)+1)) | I7: =IF($B7=0,"",INDEX('Engine (Monthly)'!$BM$3:$BM$603,MIN(($A7-1)*12,HorizonM)+1)) | J7: =IF($B7=0,"",SUMIFS('Engine (Monthly)'!$BB$4:$BB$603,'Engine (Monthly)'!$C$4:$C$603,$A7)) | K7: =IF($B7=0,"",SUMIFS('Engine (Monthly)'!$BE$4:$BE$603,'Engine (Monthly)'!$C$4:$C$603,$A7)) | L7: =IF($B7=0,"",SUMIFS('Engine (Monthly)'!$BD$4:$BD$603,'Engine (Monthly)'!$C$4:$C$603,$A7)) | M7: =IF($B7=0,"",SUMIFS('Engine (Monthly)'!$BH$4:$BH$603,'Engine (Monthly)'!$C$4:$C$603,$A7)) | N7: =IF($B7=0,"",INDEX('Engine (Monthly)'!$BM$3:$BM$603,MIN($A7*12,HorizonM)+1)) | O7: =IF($B7=0,"",INDEX('Engine (Monthly)'!$CQ$3:$CQ$603,MIN(($A7-1)*12,HorizonM)+1)) | P7: =IF($B7=0,"",SUMIFS('Engine (Monthly)'!$CF$4:$CF$603,'Engine (Monthly)'!$C$4:$C$603,$A7)) | Q7: =IF($B7=0,"",SUMIFS('Engine (Monthly)'!$CI$4:$CI$603,'Engine (Monthly)'!$C$4:$C$603,$A7)) | R7: =IF($B7=0,"",SUMIFS('Engine (Monthly)'!$CH$4:$CH$603,'Engine (Monthly)'!$C$4:$C$603,$A7)) | S7: =IF($B7=0,"",SUMIFS('Engine (Monthly)'!$CL$4:$CL$603,'Engine (Monthly)'!$C$4:$C$603,$A7)) | T7: =IF($B7=0,"",INDEX('Engine (Monthly)'!$CQ$3:$CQ$603,MIN($A7*12,HorizonM)+1)) | U7: =IF($B7=0,"",$C7+$I7+$O7) | V7: =IF($B7=0,"",$D7+$J7+$P7) | W7: =IF($B7=0,"",$E7+$K7+$Q7) | X7: =IF($B7=0,"",$F7+$L7+$R7) | Y7: =IF($B7=0,"",$G7+$M7+$S7) | Z7: =IF($B7=0,"",'Tax Estimate'!$S7) | AA7: =IF($B7=0,"",$H7+$N7+$T7) | AB7: =IF($B7=0,"",SUMIFS('Engine (Monthly)'!$CY$4:$CY$603,'Engine (Monthly)'!$C$4:$C$603,"<="&$A7)) | AC7: =IF($B7=0,"",SUMIFS('Engine (Monthly)'!$CZ$4:$CZ$603,'Engine (Monthly)'!$C$4:$C$603,"<="&$A7)) | AD7: =IF($B7=0,"",SUMIFS('Engine (Monthly)'!$DA$4:$DA$603,'Engine (Monthly)'!$C$4:$C$603,"<="&$A7)) | AE7: =IF($B7=0,"",SUMIFS('Engine (Monthly)'!$CV$4:$CV$603,'Engine (Monthly)'!$C$4:$C$603,"<="&$A7)) | AF7: =IF($B7=0,"",IF(COUNTIFS('Engine (Monthly)'!$C$4:$C$603,$A7,'Engine (Monthly)'!$DB$4:$DB$603,1)>0,"⚠ shortfall","OK"))
A8: 5 | B8: =IF($A8<=HorizonY,1,0) | C8: =IF($B8=0,"",INDEX('Engine (Monthly)'!$AI$3:$AI$603,MIN(($A8-1)*12,HorizonM)+1)) | D8: =IF($B8=0,"",SUMIFS('Engine (Monthly)'!$X$4:$X$603,'Engine (Monthly)'!$C$4:$C$603,$A8)) | E8: =IF($B8=0,"",SUMIFS('Engine (Monthly)'!$AA$4:$AA$603,'Engine (Monthly)'!$C$4:$C$603,$A8)) | F8: =IF($B8=0,"",SUMIFS('Engine (Monthly)'!$Z$4:$Z$603,'Engine (Monthly)'!$C$4:$C$603,$A8)) | G8: =IF($B8=0,"",SUMIFS('Engine (Monthly)'!$AD$4:$AD$603,'Engine (Monthly)'!$C$4:$C$603,$A8)) | H8: =IF($B8=0,"",INDEX('Engine (Monthly)'!$AI$3:$AI$603,MIN($A8*12,HorizonM)+1)) | I8: =IF($B8=0,"",INDEX('Engine (Monthly)'!$BM$3:$BM$603,MIN(($A8-1)*12,HorizonM)+1)) | J8: =IF($B8=0,"",SUMIFS('Engine (Monthly)'!$BB$4:$BB$603,'Engine (Monthly)'!$C$4:$C$603,$A8)) | K8: =IF($B8=0,"",SUMIFS('Engine (Monthly)'!$BE$4:$BE$603,'Engine (Monthly)'!$C$4:$C$603,$A8)) | L8: =IF($B8=0,"",SUMIFS('Engine (Monthly)'!$BD$4:$BD$603,'Engine (Monthly)'!$C$4:$C$603,$A8)) | M8: =IF($B8=0,"",SUMIFS('Engine (Monthly)'!$BH$4:$BH$603,'Engine (Monthly)'!$C$4:$C$603,$A8)) | N8: =IF($B8=0,"",INDEX('Engine (Monthly)'!$BM$3:$BM$603,MIN($A8*12,HorizonM)+1)) | O8: =IF($B8=0,"",INDEX('Engine (Monthly)'!$CQ$3:$CQ$603,MIN(($A8-1)*12,HorizonM)+1)) | P8: =IF($B8=0,"",SUMIFS('Engine (Monthly)'!$CF$4:$CF$603,'Engine (Monthly)'!$C$4:$C$603,$A8)) | Q8: =IF($B8=0,"",SUMIFS('Engine (Monthly)'!$CI$4:$CI$603,'Engine (Monthly)'!$C$4:$C$603,$A8)) | R8: =IF($B8=0,"",SUMIFS('Engine (Monthly)'!$CH$4:$CH$603,'Engine (Monthly)'!$C$4:$C$603,$A8)) | S8: =IF($B8=0,"",SUMIFS('Engine (Monthly)'!$CL$4:$CL$603,'Engine (Monthly)'!$C$4:$C$603,$A8)) | T8: =IF($B8=0,"",INDEX('Engine (Monthly)'!$CQ$3:$CQ$603,MIN($A8*12,HorizonM)+1)) | U8: =IF($B8=0,"",$C8+$I8+$O8) | V8: =IF($B8=0,"",$D8+$J8+$P8) | W8: =IF($B8=0,"",$E8+$K8+$Q8) | X8: =IF($B8=0,"",$F8+$L8+$R8) | Y8: =IF($B8=0,"",$G8+$M8+$S8) | Z8: =IF($B8=0,"",'Tax Estimate'!$S8) | AA8: =IF($B8=0,"",$H8+$N8+$T8) | AB8: =IF($B8=0,"",SUMIFS('Engine (Monthly)'!$CY$4:$CY$603,'Engine (Monthly)'!$C$4:$C$603,"<="&$A8)) | AC8: =IF($B8=0,"",SUMIFS('Engine (Monthly)'!$CZ$4:$CZ$603,'Engine (Monthly)'!$C$4:$C$603,"<="&$A8)) | AD8: =IF($B8=0,"",SUMIFS('Engine (Monthly)'!$DA$4:$DA$603,'Engine (Monthly)'!$C$4:$C$603,"<="&$A8)) | AE8: =IF($B8=0,"",SUMIFS('Engine (Monthly)'!$CV$4:$CV$603,'Engine (Monthly)'!$C$4:$C$603,"<="&$A8)) | AF8: =IF($B8=0,"",IF(COUNTIFS('Engine (Monthly)'!$C$4:$C$603,$A8,'Engine (Monthly)'!$DB$4:$DB$603,1)>0,"⚠ shortfall","OK"))
A9: 6 | B9: =IF($A9<=HorizonY,1,0) | C9: =IF($B9=0,"",INDEX('Engine (Monthly)'!$AI$3:$AI$603,MIN(($A9-1)*12,HorizonM)+1)) | D9: =IF($B9=0,"",SUMIFS('Engine (Monthly)'!$X$4:$X$603,'Engine (Monthly)'!$C$4:$C$603,$A9)) | E9: =IF($B9=0,"",SUMIFS('Engine (Monthly)'!$AA$4:$AA$603,'Engine (Monthly)'!$C$4:$C$603,$A9)) | F9: =IF($B9=0,"",SUMIFS('Engine (Monthly)'!$Z$4:$Z$603,'Engine (Monthly)'!$C$4:$C$603,$A9)) | G9: =IF($B9=0,"",SUMIFS('Engine (Monthly)'!$AD$4:$AD$603,'Engine (Monthly)'!$C$4:$C$603,$A9)) | H9: =IF($B9=0,"",INDEX('Engine (Monthly)'!$AI$3:$AI$603,MIN($A9*12,HorizonM)+1)) | I9: =IF($B9=0,"",INDEX('Engine (Monthly)'!$BM$3:$BM$603,MIN(($A9-1)*12,HorizonM)+1)) | J9: =IF($B9=0,"",SUMIFS('Engine (Monthly)'!$BB$4:$BB$603,'Engine (Monthly)'!$C$4:$C$603,$A9)) | K9: =IF($B9=0,"",SUMIFS('Engine (Monthly)'!$BE$4:$BE$603,'Engine (Monthly)'!$C$4:$C$603,$A9)) | L9: =IF($B9=0,"",SUMIFS('Engine (Monthly)'!$BD$4:$BD$603,'Engine (Monthly)'!$C$4:$C$603,$A9)) | M9: =IF($B9=0,"",SUMIFS('Engine (Monthly)'!$BH$4:$BH$603,'Engine (Monthly)'!$C$4:$C$603,$A9)) | N9: =IF($B9=0,"",INDEX('Engine (Monthly)'!$BM$3:$BM$603,MIN($A9*12,HorizonM)+1)) | O9: =IF($B9=0,"",INDEX('Engine (Monthly)'!$CQ$3:$CQ$603,MIN(($A9-1)*12,HorizonM)+1)) | P9: =IF($B9=0,"",SUMIFS('Engine (Monthly)'!$CF$4:$CF$603,'Engine (Monthly)'!$C$4:$C$603,$A9)) | Q9: =IF($B9=0,"",SUMIFS('Engine (Monthly)'!$CI$4:$CI$603,'Engine (Monthly)'!$C$4:$C$603,$A9)) | R9: =IF($B9=0,"",SUMIFS('Engine (Monthly)'!$CH$4:$CH$603,'Engine (Monthly)'!$C$4:$C$603,$A9)) | S9: =IF($B9=0,"",SUMIFS('Engine (Monthly)'!$CL$4:$CL$603,'Engine (Monthly)'!$C$4:$C$603,$A9)) | T9: =IF($B9=0,"",INDEX('Engine (Monthly)'!$CQ$3:$CQ$603,MIN($A9*12,HorizonM)+1)) | U9: =IF($B9=0,"",$C9+$I9+$O9) | V9: =IF($B9=0,"",$D9+$J9+$P9) | W9: =IF($B9=0,"",$E9+$K9+$Q9) | X9: =IF($B9=0,"",$F9+$L9+$R9) | Y9: =IF($B9=0,"",$G9+$M9+$S9) | Z9: =IF($B9=0,"",'Tax Estimate'!$S9) | AA9: =IF($B9=0,"",$H9+$N9+$T9) | AB9: =IF($B9=0,"",SUMIFS('Engine (Monthly)'!$CY$4:$CY$603,'Engine (Monthly)'!$C$4:$C$603,"<="&$A9)) | AC9: =IF($B9=0,"",SUMIFS('Engine (Monthly)'!$CZ$4:$CZ$603,'Engine (Monthly)'!$C$4:$C$603,"<="&$A9)) | AD9: =IF($B9=0,"",SUMIFS('Engine (Monthly)'!$DA$4:$DA$603,'Engine (Monthly)'!$C$4:$C$603,"<="&$A9)) | AE9: =IF($B9=0,"",SUMIFS('Engine (Monthly)'!$CV$4:$CV$603,'Engine (Monthly)'!$C$4:$C$603,"<="&$A9)) | AF9: =IF($B9=0,"",IF(COUNTIFS('Engine (Monthly)'!$C$4:$C$603,$A9,'Engine (Monthly)'!$DB$4:$DB$603,1)>0,"⚠ shortfall","OK"))
A10: 7 | B10: =IF($A10<=HorizonY,1,0) | C10: =IF($B10=0,"",INDEX('Engine (Monthly)'!$AI$3:$AI$603,MIN(($A10-1)*12,HorizonM)+1)) | D10: =IF($B10=0,"",SUMIFS('Engine (Monthly)'!$X$4:$X$603,'Engine (Monthly)'!$C$4:$C$603,$A10)) | E10: =IF($B10=0,"",SUMIFS('Engine (Monthly)'!$AA$4:$AA$603,'Engine (Monthly)'!$C$4:$C$603,$A10)) | F10: =IF($B10=0,"",SUMIFS('Engine (Monthly)'!$Z$4:$Z$603,'Engine (Monthly)'!$C$4:$C$603,$A10)) | G10: =IF($B10=0,"",SUMIFS('Engine (Monthly)'!$AD$4:$AD$603,'Engine (Monthly)'!$C$4:$C$603,$A10)) | H10: =IF($B10=0,"",INDEX('Engine (Monthly)'!$AI$3:$AI$603,MIN($A10*12,HorizonM)+1)) | I10: =IF($B10=0,"",INDEX('Engine (Monthly)'!$BM$3:$BM$603,MIN(($A10-1)*12,HorizonM)+1)) | J10: =IF($B10=0,"",SUMIFS('Engine (Monthly)'!$BB$4:$BB$603,'Engine (Monthly)'!$C$4:$C$603,$A10)) | K10: =IF($B10=0,"",SUMIFS('Engine (Monthly)'!$BE$4:$BE$603,'Engine (Monthly)'!$C$4:$C$603,$A10)) | L10: =IF($B10=0,"",SUMIFS('Engine (Monthly)'!$BD$4:$BD$603,'Engine (Monthly)'!$C$4:$C$603,$A10)) | M10: =IF($B10=0,"",SUMIFS('Engine (Monthly)'!$BH$4:$BH$603,'Engine (Monthly)'!$C$4:$C$603,$A10)) | N10: =IF($B10=0,"",INDEX('Engine (Monthly)'!$BM$3:$BM$603,MIN($A10*12,HorizonM)+1)) | O10: =IF($B10=0,"",INDEX('Engine (Monthly)'!$CQ$3:$CQ$603,MIN(($A10-1)*12,HorizonM)+1)) | P10: =IF($B10=0,"",SUMIFS('Engine (Monthly)'!$CF$4:$CF$603,'Engine (Monthly)'!$C$4:$C$603,$A10)) | Q10: =IF($B10=0,"",SUMIFS('Engine (Monthly)'!$CI$4:$CI$603,'Engine (Monthly)'!$C$4:$C$603,$A10)) | R10: =IF($B10=0,"",SUMIFS('Engine (Monthly)'!$CH$4:$CH$603,'Engine (Monthly)'!$C$4:$C$603,$A10)) | S10: =IF($B10=0,"",SUMIFS('Engine (Monthly)'!$CL$4:$CL$603,'Engine (Monthly)'!$C$4:$C$603,$A10)) | T10: =IF($B10=0,"",INDEX('Engine (Monthly)'!$CQ$3:$CQ$603,MIN($A10*12,HorizonM)+1)) | U10: =IF($B10=0,"",$C10+$I10+$O10) | V10: =IF($B10=0,"",$D10+$J10+$P10) | W10: =IF($B10=0,"",$E10+$K10+$Q10) | X10: =IF($B10=0,"",$F10+$L10+$R10) | Y10: =IF($B10=0,"",$G10+$M10+$S10) | Z10: =IF($B10=0,"",'Tax Estimate'!$S10) | AA10: =IF($B10=0,"",$H10+$N10+$T10) | AB10: =IF($B10=0,"",SUMIFS('Engine (Monthly)'!$CY$4:$CY$603,'Engine (Monthly)'!$C$4:$C$603,"<="&$A10)) | AC10: =IF($B10=0,"",SUMIFS('Engine (Monthly)'!$CZ$4:$CZ$603,'Engine (Monthly)'!$C$4:$C$603,"<="&$A10)) | AD10: =IF($B10=0,"",SUMIFS('Engine (Monthly)'!$DA$4:$DA$603,'Engine (Monthly)'!$C$4:$C$603,"<="&$A10)) | AE10: =IF($B10=0,"",SUMIFS('Engine (Monthly)'!$CV$4:$CV$603,'Engine (Monthly)'!$C$4:$C$603,"<="&$A10)) | AF10: =IF($B10=0,"",IF(COUNTIFS('Engine (Monthly)'!$C$4:$C$603,$A10,'Engine (Monthly)'!$DB$4:$DB$603,1)>0,"⚠ shortfall","OK"))
A11: 8 | B11: =IF($A11<=HorizonY,1,0) | C11: =IF($B11=0,"",INDEX('Engine (Monthly)'!$AI$3:$AI$603,MIN(($A11-1)*12,HorizonM)+1)) | D11: =IF($B11=0,"",SUMIFS('Engine (Monthly)'!$X$4:$X$603,'Engine (Monthly)'!$C$4:$C$603,$A11)) | E11: =IF($B11=0,"",SUMIFS('Engine (Monthly)'!$AA$4:$AA$603,'Engine (Monthly)'!$C$4:$C$603,$A11)) | F11: =IF($B11=0,"",SUMIFS('Engine (Monthly)'!$Z$4:$Z$603,'Engine (Monthly)'!$C$4:$C$603,$A11)) | G11: =IF($B11=0,"",SUMIFS('Engine (Monthly)'!$AD$4:$AD$603,'Engine (Monthly)'!$C$4:$C$603,$A11)) | H11: =IF($B11=0,"",INDEX('Engine (Monthly)'!$AI$3:$AI$603,MIN($A11*12,HorizonM)+1)) | I11: =IF($B11=0,"",INDEX('Engine (Monthly)'!$BM$3:$BM$603,MIN(($A11-1)*12,HorizonM)+1)) | J11: =IF($B11=0,"",SUMIFS('Engine (Monthly)'!$BB$4:$BB$603,'Engine (Monthly)'!$C$4:$C$603,$A11)) | K11: =IF($B11=0,"",SUMIFS('Engine (Monthly)'!$BE$4:$BE$603,'Engine (Monthly)'!$C$4:$C$603,$A11)) | L11: =IF($B11=0,"",SUMIFS('Engine (Monthly)'!$BD$4:$BD$603,'Engine (Monthly)'!$C$4:$C$603,$A11)) | M11: =IF($B11=0,"",SUMIFS('Engine (Monthly)'!$BH$4:$BH$603,'Engine (Monthly)'!$C$4:$C$603,$A11)) | N11: =IF($B11=0,"",INDEX('Engine (Monthly)'!$BM$3:$BM$603,MIN($A11*12,HorizonM)+1)) | O11: =IF($B11=0,"",INDEX('Engine (Monthly)'!$CQ$3:$CQ$603,MIN(($A11-1)*12,HorizonM)+1)) | P11: =IF($B11=0,"",SUMIFS('Engine (Monthly)'!$CF$4:$CF$603,'Engine (Monthly)'!$C$4:$C$603,$A11)) | Q11: =IF($B11=0,"",SUMIFS('Engine (Monthly)'!$CI$4:$CI$603,'Engine (Monthly)'!$C$4:$C$603,$A11)) | R11: =IF($B11=0,"",SUMIFS('Engine (Monthly)'!$CH$4:$CH$603,'Engine (Monthly)'!$C$4:$C$603,$A11)) | S11: =IF($B11=0,"",SUMIFS('Engine (Monthly)'!$CL$4:$CL$603,'Engine (Monthly)'!$C$4:$C$603,$A11)) | T11: =IF($B11=0,"",INDEX('Engine (Monthly)'!$CQ$3:$CQ$603,MIN($A11*12,HorizonM)+1)) | U11: =IF($B11=0,"",$C11+$I11+$O11) | V11: =IF($B11=0,"",$D11+$J11+$P11) | W11: =IF($B11=0,"",$E11+$K11+$Q11) | X11: =IF($B11=0,"",$F11+$L11+$R11) | Y11: =IF($B11=0,"",$G11+$M11+$S11) | Z11: =IF($B11=0,"",'Tax Estimate'!$S11) | AA11: =IF($B11=0,"",$H11+$N11+$T11) | AB11: =IF($B11=0,"",SUMIFS('Engine (Monthly)'!$CY$4:$CY$603,'Engine (Monthly)'!$C$4:$C$603,"<="&$A11)) | AC11: =IF($B11=0,"",SUMIFS('Engine (Monthly)'!$CZ$4:$CZ$603,'Engine (Monthly)'!$C$4:$C$603,"<="&$A11)) | AD11: =IF($B11=0,"",SUMIFS('Engine (Monthly)'!$DA$4:$DA$603,'Engine (Monthly)'!$C$4:$C$603,"<="&$A11)) | AE11: =IF($B11=0,"",SUMIFS('Engine (Monthly)'!$CV$4:$CV$603,'Engine (Monthly)'!$C$4:$C$603,"<="&$A11)) | AF11: =IF($B11=0,"",IF(COUNTIFS('Engine (Monthly)'!$C$4:$C$603,$A11,'Engine (Monthly)'!$DB$4:$DB$603,1)>0,"⚠ shortfall","OK"))
A12: 9 | B12: =IF($A12<=HorizonY,1,0) | C12: =IF($B12=0,"",INDEX('Engine (Monthly)'!$AI$3:$AI$603,MIN(($A12-1)*12,HorizonM)+1)) | D12: =IF($B12=0,"",SUMIFS('Engine (Monthly)'!$X$4:$X$603,'Engine (Monthly)'!$C$4:$C$603,$A12)) | E12: =IF($B12=0,"",SUMIFS('Engine (Monthly)'!$AA$4:$AA$603,'Engine (Monthly)'!$C$4:$C$603,$A12)) | F12: =IF($B12=0,"",SUMIFS('Engine (Monthly)'!$Z$4:$Z$603,'Engine (Monthly)'!$C$4:$C$603,$A12)) | G12: =IF($B12=0,"",SUMIFS('Engine (Monthly)'!$AD$4:$AD$603,'Engine (Monthly)'!$C$4:$C$603,$A12)) | H12: =IF($B12=0,"",INDEX('Engine (Monthly)'!$AI$3:$AI$603,MIN($A12*12,HorizonM)+1)) | I12: =IF($B12=0,"",INDEX('Engine (Monthly)'!$BM$3:$BM$603,MIN(($A12-1)*12,HorizonM)+1)) | J12: =IF($B12=0,"",SUMIFS('Engine (Monthly)'!$BB$4:$BB$603,'Engine (Monthly)'!$C$4:$C$603,$A12)) | K12: =IF($B12=0,"",SUMIFS('Engine (Monthly)'!$BE$4:$BE$603,'Engine (Monthly)'!$C$4:$C$603,$A12)) | L12: =IF($B12=0,"",SUMIFS('Engine (Monthly)'!$BD$4:$BD$603,'Engine (Monthly)'!$C$4:$C$603,$A12)) | M12: =IF($B12=0,"",SUMIFS('Engine (Monthly)'!$BH$4:$BH$603,'Engine (Monthly)'!$C$4:$C$603,$A12)) | N12: =IF($B12=0,"",INDEX('Engine (Monthly)'!$BM$3:$BM$603,MIN($A12*12,HorizonM)+1)) | O12: =IF($B12=0,"",INDEX('Engine (Monthly)'!$CQ$3:$CQ$603,MIN(($A12-1)*12,HorizonM)+1)) | P12: =IF($B12=0,"",SUMIFS('Engine (Monthly)'!$CF$4:$CF$603,'Engine (Monthly)'!$C$4:$C$603,$A12)) | Q12: =IF($B12=0,"",SUMIFS('Engine (Monthly)'!$CI$4:$CI$603,'Engine (Monthly)'!$C$4:$C$603,$A12)) | R12: =IF($B12=0,"",SUMIFS('Engine (Monthly)'!$CH$4:$CH$603,'Engine (Monthly)'!$C$4:$C$603,$A12)) | S12: =IF($B12=0,"",SUMIFS('Engine (Monthly)'!$CL$4:$CL$603,'Engine (Monthly)'!$C$4:$C$603,$A12)) | T12: =IF($B12=0,"",INDEX('Engine (Monthly)'!$CQ$3:$CQ$603,MIN($A12*12,HorizonM)+1)) | U12: =IF($B12=0,"",$C12+$I12+$O12) | V12: =IF($B12=0,"",$D12+$J12+$P12) | W12: =IF($B12=0,"",$E12+$K12+$Q12) | X12: =IF($B12=0,"",$F12+$L12+$R12) | Y12: =IF($B12=0,"",$G12+$M12+$S12) | Z12: =IF($B12=0,"",'Tax Estimate'!$S12) | AA12: =IF($B12=0,"",$H12+$N12+$T12) | AB12: =IF($B12=0,"",SUMIFS('Engine (Monthly)'!$CY$4:$CY$603,'Engine (Monthly)'!$C$4:$C$603,"<="&$A12)) | AC12: =IF($B12=0,"",SUMIFS('Engine (Monthly)'!$CZ$4:$CZ$603,'Engine (Monthly)'!$C$4:$C$603,"<="&$A12)) | AD12: =IF($B12=0,"",SUMIFS('Engine (Monthly)'!$DA$4:$DA$603,'Engine (Monthly)'!$C$4:$C$603,"<="&$A12)) | AE12: =IF($B12=0,"",SUMIFS('Engine (Monthly)'!$CV$4:$CV$603,'Engine (Monthly)'!$C$4:$C$603,"<="&$A12)) | AF12: =IF($B12=0,"",IF(COUNTIFS('Engine (Monthly)'!$C$4:$C$603,$A12,'Engine (Monthly)'!$DB$4:$DB$603,1)>0,"⚠ shortfall","OK"))
A13: 10 | B13: =IF($A13<=HorizonY,1,0) | C13: =IF($B13=0,"",INDEX('Engine (Monthly)'!$AI$3:$AI$603,MIN(($A13-1)*12,HorizonM)+1)) | D13: =IF($B13=0,"",SUMIFS('Engine (Monthly)'!$X$4:$X$603,'Engine (Monthly)'!$C$4:$C$603,$A13)) | E13: =IF($B13=0,"",SUMIFS('Engine (Monthly)'!$AA$4:$AA$603,'Engine (Monthly)'!$C$4:$C$603,$A13)) | F13: =IF($B13=0,"",SUMIFS('Engine (Monthly)'!$Z$4:$Z$603,'Engine (Monthly)'!$C$4:$C$603,$A13)) | G13: =IF($B13=0,"",SUMIFS('Engine (Monthly)'!$AD$4:$AD$603,'Engine (Monthly)'!$C$4:$C$603,$A13)) | H13: =IF($B13=0,"",INDEX('Engine (Monthly)'!$AI$3:$AI$603,MIN($A13*12,HorizonM)+1)) | I13: =IF($B13=0,"",INDEX('Engine (Monthly)'!$BM$3:$BM$603,MIN(($A13-1)*12,HorizonM)+1)) | J13: =IF($B13=0,"",SUMIFS('Engine (Monthly)'!$BB$4:$BB$603,'Engine (Monthly)'!$C$4:$C$603,$A13)) | K13: =IF($B13=0,"",SUMIFS('Engine (Monthly)'!$BE$4:$BE$603,'Engine (Monthly)'!$C$4:$C$603,$A13)) | L13: =IF($B13=0,"",SUMIFS('Engine (Monthly)'!$BD$4:$BD$603,'Engine (Monthly)'!$C$4:$C$603,$A13)) | M13: =IF($B13=0,"",SUMIFS('Engine (Monthly)'!$BH$4:$BH$603,'Engine (Monthly)'!$C$4:$C$603,$A13)) | N13: =IF($B13=0,"",INDEX('Engine (Monthly)'!$BM$3:$BM$603,MIN($A13*12,HorizonM)+1)) | O13: =IF($B13=0,"",INDEX('Engine (Monthly)'!$CQ$3:$CQ$603,MIN(($A13-1)*12,HorizonM)+1)) | P13: =IF($B13=0,"",SUMIFS('Engine (Monthly)'!$CF$4:$CF$603,'Engine (Monthly)'!$C$4:$C$603,$A13)) | Q13: =IF($B13=0,"",SUMIFS('Engine (Monthly)'!$CI$4:$CI$603,'Engine (Monthly)'!$C$4:$C$603,$A13)) | R13: =IF($B13=0,"",SUMIFS('Engine (Monthly)'!$CH$4:$CH$603,'Engine (Monthly)'!$C$4:$C$603,$A13)) | S13: =IF($B13=0,"",SUMIFS('Engine (Monthly)'!$CL$4:$CL$603,'Engine (Monthly)'!$C$4:$C$603,$A13)) | T13: =IF($B13=0,"",INDEX('Engine (Monthly)'!$CQ$3:$CQ$603,MIN($A13*12,HorizonM)+1)) | U13: =IF($B13=0,"",$C13+$I13+$O13) | V13: =IF($B13=0,"",$D13+$J13+$P13) | W13: =IF($B13=0,"",$E13+$K13+$Q13) | X13: =IF($B13=0,"",$F13+$L13+$R13) | Y13: =IF($B13=0,"",$G13+$M13+$S13) | Z13: =IF($B13=0,"",'Tax Estimate'!$S13) | AA13: =IF($B13=0,"",$H13+$N13+$T13) | AB13: =IF($B13=0,"",SUMIFS('Engine (Monthly)'!$CY$4:$CY$603,'Engine (Monthly)'!$C$4:$C$603,"<="&$A13)) | AC13: =IF($B13=0,"",SUMIFS('Engine (Monthly)'!$CZ$4:$CZ$603,'Engine (Monthly)'!$C$4:$C$603,"<="&$A13)) | AD13: =IF($B13=0,"",SUMIFS('Engine (Monthly)'!$DA$4:$DA$603,'Engine (Monthly)'!$C$4:$C$603,"<="&$A13)) | AE13: =IF($B13=0,"",SUMIFS('Engine (Monthly)'!$CV$4:$CV$603,'Engine (Monthly)'!$C$4:$C$603,"<="&$A13)) | AF13: =IF($B13=0,"",IF(COUNTIFS('Engine (Monthly)'!$C$4:$C$603,$A13,'Engine (Monthly)'!$DB$4:$DB$603,1)>0,"⚠ shortfall","OK"))
A14: 11 | B14: =IF($A14<=HorizonY,1,0) | C14: =IF($B14=0,"",INDEX('Engine (Monthly)'!$AI$3:$AI$603,MIN(($A14-1)*12,HorizonM)+1)) | D14: =IF($B14=0,"",SUMIFS('Engine (Monthly)'!$X$4:$X$603,'Engine (Monthly)'!$C$4:$C$603,$A14)) | E14: =IF($B14=0,"",SUMIFS('Engine (Monthly)'!$AA$4:$AA$603,'Engine (Monthly)'!$C$4:$C$603,$A14)) | F14: =IF($B14=0,"",SUMIFS('Engine (Monthly)'!$Z$4:$Z$603,'Engine (Monthly)'!$C$4:$C$603,$A14)) | G14: =IF($B14=0,"",SUMIFS('Engine (Monthly)'!$AD$4:$AD$603,'Engine (Monthly)'!$C$4:$C$603,$A14)) | H14: =IF($B14=0,"",INDEX('Engine (Monthly)'!$AI$3:$AI$603,MIN($A14*12,HorizonM)+1)) | I14: =IF($B14=0,"",INDEX('Engine (Monthly)'!$BM$3:$BM$603,MIN(($A14-1)*12,HorizonM)+1)) | J14: =IF($B14=0,"",SUMIFS('Engine (Monthly)'!$BB$4:$BB$603,'Engine (Monthly)'!$C$4:$C$603,$A14)) | K14: =IF($B14=0,"",SUMIFS('Engine (Monthly)'!$BE$4:$BE$603,'Engine (Monthly)'!$C$4:$C$603,$A14)) | L14: =IF($B14=0,"",SUMIFS('Engine (Monthly)'!$BD$4:$BD$603,'Engine (Monthly)'!$C$4:$C$603,$A14)) | M14: =IF($B14=0,"",SUMIFS('Engine (Monthly)'!$BH$4:$BH$603,'Engine (Monthly)'!$C$4:$C$603,$A14)) | N14: =IF($B14=0,"",INDEX('Engine (Monthly)'!$BM$3:$BM$603,MIN($A14*12,HorizonM)+1)) | O14: =IF($B14=0,"",INDEX('Engine (Monthly)'!$CQ$3:$CQ$603,MIN(($A14-1)*12,HorizonM)+1)) | P14: =IF($B14=0,"",SUMIFS('Engine (Monthly)'!$CF$4:$CF$603,'Engine (Monthly)'!$C$4:$C$603,$A14)) | Q14: =IF($B14=0,"",SUMIFS('Engine (Monthly)'!$CI$4:$CI$603,'Engine (Monthly)'!$C$4:$C$603,$A14)) | R14: =IF($B14=0,"",SUMIFS('Engine (Monthly)'!$CH$4:$CH$603,'Engine (Monthly)'!$C$4:$C$603,$A14)) | S14: =IF($B14=0,"",SUMIFS('Engine (Monthly)'!$CL$4:$CL$603,'Engine (Monthly)'!$C$4:$C$603,$A14)) | T14: =IF($B14=0,"",INDEX('Engine (Monthly)'!$CQ$3:$CQ$603,MIN($A14*12,HorizonM)+1)) | U14: =IF($B14=0,"",$C14+$I14+$O14) | V14: =IF($B14=0,"",$D14+$J14+$P14) | W14: =IF($B14=0,"",$E14+$K14+$Q14) | X14: =IF($B14=0,"",$F14+$L14+$R14) | Y14: =IF($B14=0,"",$G14+$M14+$S14) | Z14: =IF($B14=0,"",'Tax Estimate'!$S14) | AA14: =IF($B14=0,"",$H14+$N14+$T14) | AB14: =IF($B14=0,"",SUMIFS('Engine (Monthly)'!$CY$4:$CY$603,'Engine (Monthly)'!$C$4:$C$603,"<="&$A14)) | AC14: =IF($B14=0,"",SUMIFS('Engine (Monthly)'!$CZ$4:$CZ$603,'Engine (Monthly)'!$C$4:$C$603,"<="&$A14)) | AD14: =IF($B14=0,"",SUMIFS('Engine (Monthly)'!$DA$4:$DA$603,'Engine (Monthly)'!$C$4:$C$603,"<="&$A14)) | AE14: =IF($B14=0,"",SUMIFS('Engine (Monthly)'!$CV$4:$CV$603,'Engine (Monthly)'!$C$4:$C$603,"<="&$A14)) | AF14: =IF($B14=0,"",IF(COUNTIFS('Engine (Monthly)'!$C$4:$C$603,$A14,'Engine (Monthly)'!$DB$4:$DB$603,1)>0,"⚠ shortfall","OK"))
A15: 12 | B15: =IF($A15<=HorizonY,1,0) | C15: =IF($B15=0,"",INDEX('Engine (Monthly)'!$AI$3:$AI$603,MIN(($A15-1)*12,HorizonM)+1)) | D15: =IF($B15=0,"",SUMIFS('Engine (Monthly)'!$X$4:$X$603,'Engine (Monthly)'!$C$4:$C$603,$A15)) | E15: =IF($B15=0,"",SUMIFS('Engine (Monthly)'!$AA$4:$AA$603,'Engine (Monthly)'!$C$4:$C$603,$A15)) | F15: =IF($B15=0,"",SUMIFS('Engine (Monthly)'!$Z$4:$Z$603,'Engine (Monthly)'!$C$4:$C$603,$A15)) | G15: =IF($B15=0,"",SUMIFS('Engine (Monthly)'!$AD$4:$AD$603,'Engine (Monthly)'!$C$4:$C$603,$A15)) | H15: =IF($B15=0,"",INDEX('Engine (Monthly)'!$AI$3:$AI$603,MIN($A15*12,HorizonM)+1)) | I15: =IF($B15=0,"",INDEX('Engine (Monthly)'!$BM$3:$BM$603,MIN(($A15-1)*12,HorizonM)+1)) | J15: =IF($B15=0,"",SUMIFS('Engine (Monthly)'!$BB$4:$BB$603,'Engine (Monthly)'!$C$4:$C$603,$A15)) | K15: =IF($B15=0,"",SUMIFS('Engine (Monthly)'!$BE$4:$BE$603,'Engine (Monthly)'!$C$4:$C$603,$A15)) | L15: =IF($B15=0,"",SUMIFS('Engine (Monthly)'!$BD$4:$BD$603,'Engine (Monthly)'!$C$4:$C$603,$A15)) | M15: =IF($B15=0,"",SUMIFS('Engine (Monthly)'!$BH$4:$BH$603,'Engine (Monthly)'!$C$4:$C$603,$A15)) | N15: =IF($B15=0,"",INDEX('Engine (Monthly)'!$BM$3:$BM$603,MIN($A15*12,HorizonM)+1)) | O15: =IF($B15=0,"",INDEX('Engine (Monthly)'!$CQ$3:$CQ$603,MIN(($A15-1)*12,HorizonM)+1)) | P15: =IF($B15=0,"",SUMIFS('Engine (Monthly)'!$CF$4:$CF$603,'Engine (Monthly)'!$C$4:$C$603,$A15)) | Q15: =IF($B15=0,"",SUMIFS('Engine (Monthly)'!$CI$4:$CI$603,'Engine (Monthly)'!$C$4:$C$603,$A15)) | R15: =IF($B15=0,"",SUMIFS('Engine (Monthly)'!$CH$4:$CH$603,'Engine (Monthly)'!$C$4:$C$603,$A15)) | S15: =IF($B15=0,"",SUMIFS('Engine (Monthly)'!$CL$4:$CL$603,'Engine (Monthly)'!$C$4:$C$603,$A15)) | T15: =IF($B15=0,"",INDEX('Engine (Monthly)'!$CQ$3:$CQ$603,MIN($A15*12,HorizonM)+1)) | U15: =IF($B15=0,"",$C15+$I15+$O15) | V15: =IF($B15=0,"",$D15+$J15+$P15) | W15: =IF($B15=0,"",$E15+$K15+$Q15) | X15: =IF($B15=0,"",$F15+$L15+$R15) | Y15: =IF($B15=0,"",$G15+$M15+$S15) | Z15: =IF($B15=0,"",'Tax Estimate'!$S15) | AA15: =IF($B15=0,"",$H15+$N15+$T15) | AB15: =IF($B15=0,"",SUMIFS('Engine (Monthly)'!$CY$4:$CY$603,'Engine (Monthly)'!$C$4:$C$603,"<="&$A15)) | AC15: =IF($B15=0,"",SUMIFS('Engine (Monthly)'!$CZ$4:$CZ$603,'Engine (Monthly)'!$C$4:$C$603,"<="&$A15)) | AD15: =IF($B15=0,"",SUMIFS('Engine (Monthly)'!$DA$4:$DA$603,'Engine (Monthly)'!$C$4:$C$603,"<="&$A15)) | AE15: =IF($B15=0,"",SUMIFS('Engine (Monthly)'!$CV$4:$CV$603,'Engine (Monthly)'!$C$4:$C$603,"<="&$A15)) | AF15: =IF($B15=0,"",IF(COUNTIFS('Engine (Monthly)'!$C$4:$C$603,$A15,'Engine (Monthly)'!$DB$4:$DB$603,1)>0,"⚠ shortfall","OK"))
... A53: 50 | B53: =IF($A53<=HorizonY,1,0) | C53: =IF($B53=0,"",INDEX('Engine (Monthly)'!$AI$3:$AI$603,MIN(($A53-1)*12,HorizonM)+1)) | D53: =IF($B53=0,"",SUMIFS('Engine (Monthly)'!$X$4:$X$603,'Engine (Monthly)'!$C$4:$C$603,$A53)) | E53: =IF($B53=0,"",SUMIFS('Engine (Monthly)'!$AA$4:$AA$603,'Engine (Monthly)'!$C$4:$C$603,$A53)) | F53: =IF($B53=0,"",SUMIFS('Engine (Monthly)'!$Z$4:$Z$603,'Engine (Monthly)'!$C$4:$C$603,$A53)) | G53: =IF($B53=0,"",SUMIFS('Engine (Monthly)'!$AD$4:$AD$603,'Engine (Monthly)'!$C$4:$C$603,$A53)) | H53: =IF($B53=0,"",INDEX('Engine (Monthly)'!$AI$3:$AI$603,MIN($A53*12,HorizonM)+1)) | I53: =IF($B53=0,"",INDEX('Engine (Monthly)'!$BM$3:$BM$603,MIN(($A53-1)*12,HorizonM)+1)) | J53: =IF($B53=0,"",SUMIFS('Engine (Monthly)'!$BB$4:$BB$603,'Engine (Monthly)'!$C$4:$C$603,$A53)) | K53: =IF($B53=0,"",SUMIFS('Engine (Monthly)'!$BE$4:$BE$603,'Engine (Monthly)'!$C$4:$C$603,$A53)) | L53: =IF($B53=0,"",SUMIFS('Engine (Monthly)'!$BD$4:$BD$603,'Engine (Monthly)'!$C$4:$C$603,$A53)) | M53: =IF($B53=0,"",SUMIFS('Engine (Monthly)'!$BH$4:$BH$603,'Engine (Monthly)'!$C$4:$C$603,$A53)) | N53: =IF($B53=0,"",INDEX('Engine (Monthly)'!$BM$3:$BM$603,MIN($A53*12,HorizonM)+1)) | O53: =IF($B53=0,"",INDEX('Engine (Monthly)'!$CQ$3:$CQ$603,MIN(($A53-1)*12,HorizonM)+1)) | P53: =IF($B53=0,"",SUMIFS('Engine (Monthly)'!$CF$4:$CF$603,'Engine (Monthly)'!$C$4:$C$603,$A53)) | Q53: =IF($B53=0,"",SUMIFS('Engine (Monthly)'!$CI$4:$CI$603,'Engine (Monthly)'!$C$4:$C$603,$A53)) | R53: =IF($B53=0,"",SUMIFS('Engine (Monthly)'!$CH$4:$CH$603,'Engine (Monthly)'!$C$4:$C$603,$A53)) | S53: =IF($B53=0,"",SUMIFS('Engine (Monthly)'!$CL$4:$CL$603,'Engine (Monthly)'!$C$4:$C$603,$A53)) | T53: =IF($B53=0,"",INDEX('Engine (Monthly)'!$CQ$3:$CQ$603,MIN($A53*12,HorizonM)+1)) | U53: =IF($B53=0,"",$C53+$I53+$O53) | V53: =IF($B53=0,"",$D53+$J53+$P53) | W53: =IF($B53=0,"",$E53+$K53+$Q53) | X53: =IF($B53=0,"",$F53+$L53+$R53) | Y53: =IF($B53=0,"",$G53+$M53+$S53) | Z53: =IF($B53=0,"",'Tax Estimate'!$S53) | AA53: =IF($B53=0,"",$H53+$N53+$T53) | AB53: =IF($B53=0,"",SUMIFS('Engine (Monthly)'!$CY$4:$CY$603,'Engine (Monthly)'!$C$4:$C$603,"<="&$A53)) | AC53: =IF($B53=0,"",SUMIFS('Engine (Monthly)'!$CZ$4:$CZ$603,'Engine (Monthly)'!$C$4:$C$603,"<="&$A53)) | AD53: =IF($B53=0,"",SUMIFS('Engine (Monthly)'!$DA$4:$DA$603,'Engine (Monthly)'!$C$4:$C$603,"<="&$A53)) | AE53: =IF($B53=0,"",SUMIFS('Engine (Monthly)'!$CV$4:$CV$603,'Engine (Monthly)'!$C$4:$C$603,"<="&$A53)) | AF53: =IF($B53=0,"",IF(COUNTIFS('Engine (Monthly)'!$C$4:$C$603,$A53,'Engine (Monthly)'!$DB$4:$DB$603,1)>0,"⚠ shortfall","OK"))

Sheet Tax Estimate
A1: Tax Estimate — CRA federal + Ontario, tax year 2026 rules | V1: Tax on other income alone: | X1: =MAX(0,SUMPRODUCT((N(OtherInc)>FedThr)*((N(OtherInc))-FedThr)*FedDlt)-(FedBPAMax-(FedBPAMax-FedBPAMin)*MIN(1,MAX(0,((N(OtherInc))-FedPhLow)/(FedPhHigh-FedPhLow))))*FedLowRate) | Y1: =MAX(0,SUMPRODUCT((N(OtherInc)>ONThr)*((N(OtherInc))-ONThr)*ONDlt)-ONBPA*ONLowRate) | Z1: =$X$1+$Y$1+ONSurR1*MAX(0,$Y$1-ONSur1)+ONSurR2*MAX(0,$Y$1-ONSur2)
A2: Standalone = portfolio is the only income. Stacked = portfolio on top of other income (shows the incremental tax only). Excluded by design: AMT, Ontario Health Premium, OAS clawback, CPP/EI — a large single-year sale may trigger AMT; confirm with an accountant.
A3: Year | B3: · | C3: Eligible dividends (NR) | D3: Non-eligible dividends (NR) | E3: Foreign / interest (NR) | F3: Realized capital gains | G3: RRSP/RRIF withdrawals | H3: TFSA withdrawals (tax-free) | I3: Grossed-up eligible | J3: Grossed-up non-eligible | K3: Taxable income (standalone) | L3: Fed tax before credits | M3: Fed BPA | N3: Federal tax | O3: ON tax before credits | P3: ON basic tax | Q3: ON surtax | R3: Ontario tax | S3: TOTAL TAX (standalone) | T3: Effective rate on cash income | U3: Taxable income (stacked) | V3: Stk fed before credits | W3: Stk fed BPA | X3: Stk federal tax | Y3: Stk ON before credits | Z3: Stk ON basic | AA3: Stk ON surtax | AB3: Stk Ontario tax | AC3: Stk total (all income) | AD3: INCREMENTAL TAX (stacked view) | AE3: T·A fed | AF3: T·A ON basic | AG3: T·A total | AH3: T·B fed | AI3: T·B ON basic | AJ3: T·B total | AK3: T·C fed | AL3: T·C ON basic | AM3: T·C total | AN3: Tax: interest/foreign | AO3: Tax: RRSP withdrawals | AP3: Tax: capital gains | AQ3: Tax: dividends (net of credits)
A4: 1 | B4: =IF($A4<=HorizonY,1,0) | C4: =SUMIFS('Engine (Monthly)'!$CR$4:$CR$603,'Engine (Monthly)'!$C$4:$C$603,$A4) | D4: =SUMIFS('Engine (Monthly)'!$CS$4:$CS$603,'Engine (Monthly)'!$C$4:$C$603,$A4) | E4: =SUMIFS('Engine (Monthly)'!$CT$4:$CT$603,'Engine (Monthly)'!$C$4:$C$603,$A4) | F4: =MAX(0,SUMIFS('Engine (Monthly)'!$CV$4:$CV$603,'Engine (Monthly)'!$C$4:$C$603,$A4)) | G4: =SUMIFS('Engine (Monthly)'!$CL$4:$CL$603,'Engine (Monthly)'!$C$4:$C$603,$A4) | H4: =SUMIFS('Engine (Monthly)'!$BH$4:$BH$603,'Engine (Monthly)'!$C$4:$C$603,$A4) | I4: =$C4*(1+GUE) | J4: =$D4*(1+GUN) | K4: =$I4+$J4+$E4+CGInc*$F4+$G4 | L4: =SUMPRODUCT(($K4>FedThr)*(($K4)-FedThr)*FedDlt) | M4: =(FedBPAMax-(FedBPAMax-FedBPAMin)*MIN(1,MAX(0,(($K4)-FedPhLow)/(FedPhHigh-FedPhLow)))) | N4: =MAX(0,$L4-$M4*FedLowRate-$I4*FDTCE-$J4*FDTCN) | O4: =SUMPRODUCT(($K4>ONThr)*(($K4)-ONThr)*ONDlt) | P4: =MAX(0,$O4-ONBPA*ONLowRate) | Q4: =ONSurR1*MAX(0,$P4-ONSur1)+ONSurR2*MAX(0,$P4-ONSur2) | R4: =MAX(0,$P4+$Q4-$I4*ODTCE-$J4*ODTCN) | S4: =$N4+$R4 | T4: =IF($C4+$D4+$E4+$F4+$G4>0,$S4/($C4+$D4+$E4+$F4+$G4),0) | U4: =$K4+N(OtherInc) | V4: =SUMPRODUCT(($U4>FedThr)*(($U4)-FedThr)*FedDlt) | W4: =(FedBPAMax-(FedBPAMax-FedBPAMin)*MIN(1,MAX(0,(($U4)-FedPhLow)/(FedPhHigh-FedPhLow)))) | X4: =MAX(0,$V4-$W4*FedLowRate-$I4*FDTCE-$J4*FDTCN) | Y4: =SUMPRODUCT(($U4>ONThr)*(($U4)-ONThr)*ONDlt) | Z4: =MAX(0,$Y4-ONBPA*ONLowRate) | AA4: =ONSurR1*MAX(0,$Z4-ONSur1)+ONSurR2*MAX(0,$Z4-ONSur2) | AB4: =MAX(0,$Z4+$AA4-$I4*ODTCE-$J4*ODTCN) | AC4: =$X4+$AB4 | AD4: =IF($B4=0,0,$AC4-BaseTaxTotal) | AE4: =MAX(0,SUMPRODUCT((N(OtherInc)+$E4>FedThr)*((N(OtherInc)+$E4)-FedThr)*FedDlt)-(FedBPAMax-(FedBPAMax-FedBPAMin)*MIN(1,MAX(0,((N(OtherInc)+$E4)-FedPhLow)/(FedPhHigh-FedPhLow))))*FedLowRate) | AF4: =MAX(0,SUMPRODUCT((N(OtherInc)+$E4>ONThr)*((N(OtherInc)+$E4)-ONThr)*ONDlt)-ONBPA*ONLowRate) | AG4: =$AE4+$AF4+ONSurR1*MAX(0,$AF4-ONSur1)+ONSurR2*MAX(0,$AF4-ONSur2) | AH4: =MAX(0,SUMPRODUCT((N(OtherInc)+$E4+$G4>FedThr)*((N(OtherInc)+$E4+$G4)-FedThr)*FedDlt)-(FedBPAMax-(FedBPAMax-FedBPAMin)*MIN(1,MAX(0,((N(OtherInc)+$E4+$G4)-FedPhLow)/(FedPhHigh-FedPhLow))))*FedLowRate) | AI4: =MAX(0,SUMPRODUCT((N(OtherInc)+$E4+$G4>ONThr)*((N(OtherInc)+$E4+$G4)-ONThr)*ONDlt)-ONBPA*ONLowRate) | AJ4: =$AH4+$AI4+ONSurR1*MAX(0,$AI4-ONSur1)+ONSurR2*MAX(0,$AI4-ONSur2) | AK4: =MAX(0,SUMPRODUCT((N(OtherInc)+$E4+$G4+CGInc*$F4>FedThr)*((N(OtherInc)+$E4+$G4+CGInc*$F4)-FedThr)*FedDlt)-(FedBPAMax-(FedBPAMax-FedBPAMin)*MIN(1,MAX(0,((N(OtherInc)+$E4+$G4+CGInc*$F4)-FedPhLow)/(FedPhHigh-FedPhLow))))*FedLowRate) | AL4: =MAX(0,SUMPRODUCT((N(OtherInc)+$E4+$G4+CGInc*$F4>ONThr)*((N(OtherInc)+$E4+$G4+CGInc*$F4)-ONThr)*ONDlt)-ONBPA*ONLowRate) | AM4: =$AK4+$AL4+ONSurR1*MAX(0,$AL4-ONSur1)+ONSurR2*MAX(0,$AL4-ONSur2) | AN4: =IF($B4=0,0,$AG4-BaseTaxTotal) | AO4: =$AJ4-$AG4 | AP4: =$AM4-$AJ4 | AQ4: =$AC4-$AM4
A5: 2 | B5: =IF($A5<=HorizonY,1,0) | C5: =SUMIFS('Engine (Monthly)'!$CR$4:$CR$603,'Engine (Monthly)'!$C$4:$C$603,$A5) | D5: =SUMIFS('Engine (Monthly)'!$CS$4:$CS$603,'Engine (Monthly)'!$C$4:$C$603,$A5) | E5: =SUMIFS('Engine (Monthly)'!$CT$4:$CT$603,'Engine (Monthly)'!$C$4:$C$603,$A5) | F5: =MAX(0,SUMIFS('Engine (Monthly)'!$CV$4:$CV$603,'Engine (Monthly)'!$C$4:$C$603,$A5)) | G5: =SUMIFS('Engine (Monthly)'!$CL$4:$CL$603,'Engine (Monthly)'!$C$4:$C$603,$A5) | H5: =SUMIFS('Engine (Monthly)'!$BH$4:$BH$603,'Engine (Monthly)'!$C$4:$C$603,$A5) | I5: =$C5*(1+GUE) | J5: =$D5*(1+GUN) | K5: =$I5+$J5+$E5+CGInc*$F5+$G5 | L5: =SUMPRODUCT(($K5>FedThr)*(($K5)-FedThr)*FedDlt) | M5: =(FedBPAMax-(FedBPAMax-FedBPAMin)*MIN(1,MAX(0,(($K5)-FedPhLow)/(FedPhHigh-FedPhLow)))) | N5: =MAX(0,$L5-$M5*FedLowRate-$I5*FDTCE-$J5*FDTCN) | O5: =SUMPRODUCT(($K5>ONThr)*(($K5)-ONThr)*ONDlt) | P5: =MAX(0,$O5-ONBPA*ONLowRate) | Q5: =ONSurR1*MAX(0,$P5-ONSur1)+ONSurR2*MAX(0,$P5-ONSur2) | R5: =MAX(0,$P5+$Q5-$I5*ODTCE-$J5*ODTCN) | S5: =$N5+$R5 | T5: =IF($C5+$D5+$E5+$F5+$G5>0,$S5/($C5+$D5+$E5+$F5+$G5),0) | U5: =$K5+N(OtherInc) | V5: =SUMPRODUCT(($U5>FedThr)*(($U5)-FedThr)*FedDlt) | W5: =(FedBPAMax-(FedBPAMax-FedBPAMin)*MIN(1,MAX(0,(($U5)-FedPhLow)/(FedPhHigh-FedPhLow)))) | X5: =MAX(0,$V5-$W5*FedLowRate-$I5*FDTCE-$J5*FDTCN) | Y5: =SUMPRODUCT(($U5>ONThr)*(($U5)-ONThr)*ONDlt) | Z5: =MAX(0,$Y5-ONBPA*ONLowRate) | AA5: =ONSurR1*MAX(0,$Z5-ONSur1)+ONSurR2*MAX(0,$Z5-ONSur2) | AB5: =MAX(0,$Z5+$AA5-$I5*ODTCE-$J5*ODTCN) | AC5: =$X5+$AB5 | AD5: =IF($B5=0,0,$AC5-BaseTaxTotal) | AE5: =MAX(0,SUMPRODUCT((N(OtherInc)+$E5>FedThr)*((N(OtherInc)+$E5)-FedThr)*FedDlt)-(FedBPAMax-(FedBPAMax-FedBPAMin)*MIN(1,MAX(0,((N(OtherInc)+$E5)-FedPhLow)/(FedPhHigh-FedPhLow))))*FedLowRate) | AF5: =MAX(0,SUMPRODUCT((N(OtherInc)+$E5>ONThr)*((N(OtherInc)+$E5)-ONThr)*ONDlt)-ONBPA*ONLowRate) | AG5: =$AE5+$AF5+ONSurR1*MAX(0,$AF5-ONSur1)+ONSurR2*MAX(0,$AF5-ONSur2) | AH5: =MAX(0,SUMPRODUCT((N(OtherInc)+$E5+$G5>FedThr)*((N(OtherInc)+$E5+$G5)-FedThr)*FedDlt)-(FedBPAMax-(FedBPAMax-FedBPAMin)*MIN(1,MAX(0,((N(OtherInc)+$E5+$G5)-FedPhLow)/(FedPhHigh-FedPhLow))))*FedLowRate) | AI5: =MAX(0,SUMPRODUCT((N(OtherInc)+$E5+$G5>ONThr)*((N(OtherInc)+$E5+$G5)-ONThr)*ONDlt)-ONBPA*ONLowRate) | AJ5: =$AH5+$AI5+ONSurR1*MAX(0,$AI5-ONSur1)+ONSurR2*MAX(0,$AI5-ONSur2) | AK5: =MAX(0,SUMPRODUCT((N(OtherInc)+$E5+$G5+CGInc*$F5>FedThr)*((N(OtherInc)+$E5+$G5+CGInc*$F5)-FedThr)*FedDlt)-(FedBPAMax-(FedBPAMax-FedBPAMin)*MIN(1,MAX(0,((N(OtherInc)+$E5+$G5+CGInc*$F5)-FedPhLow)/(FedPhHigh-FedPhLow))))*FedLowRate) | AL5: =MAX(0,SUMPRODUCT((N(OtherInc)+$E5+$G5+CGInc*$F5>ONThr)*((N(OtherInc)+$E5+$G5+CGInc*$F5)-ONThr)*ONDlt)-ONBPA*ONLowRate) | AM5: =$AK5+$AL5+ONSurR1*MAX(0,$AL5-ONSur1)+ONSurR2*MAX(0,$AL5-ONSur2) | AN5: =IF($B5=0,0,$AG5-BaseTaxTotal) | AO5: =$AJ5-$AG5 | AP5: =$AM5-$AJ5 | AQ5: =$AC5-$AM5
A6: 3 | B6: =IF($A6<=HorizonY,1,0) | C6: =SUMIFS('Engine (Monthly)'!$CR$4:$CR$603,'Engine (Monthly)'!$C$4:$C$603,$A6) | D6: =SUMIFS('Engine (Monthly)'!$CS$4:$CS$603,'Engine (Monthly)'!$C$4:$C$603,$A6) | E6: =SUMIFS('Engine (Monthly)'!$CT$4:$CT$603,'Engine (Monthly)'!$C$4:$C$603,$A6) | F6: =MAX(0,SUMIFS('Engine (Monthly)'!$CV$4:$CV$603,'Engine (Monthly)'!$C$4:$C$603,$A6)) | G6: =SUMIFS('Engine (Monthly)'!$CL$4:$CL$603,'Engine (Monthly)'!$C$4:$C$603,$A6) | H6: =SUMIFS('Engine (Monthly)'!$BH$4:$BH$603,'Engine (Monthly)'!$C$4:$C$603,$A6) | I6: =$C6*(1+GUE) | J6: =$D6*(1+GUN) | K6: =$I6+$J6+$E6+CGInc*$F6+$G6 | L6: =SUMPRODUCT(($K6>FedThr)*(($K6)-FedThr)*FedDlt) | M6: =(FedBPAMax-(FedBPAMax-FedBPAMin)*MIN(1,MAX(0,(($K6)-FedPhLow)/(FedPhHigh-FedPhLow)))) | N6: =MAX(0,$L6-$M6*FedLowRate-$I6*FDTCE-$J6*FDTCN) | O6: =SUMPRODUCT(($K6>ONThr)*(($K6)-ONThr)*ONDlt) | P6: =MAX(0,$O6-ONBPA*ONLowRate) | Q6: =ONSurR1*MAX(0,$P6-ONSur1)+ONSurR2*MAX(0,$P6-ONSur2) | R6: =MAX(0,$P6+$Q6-$I6*ODTCE-$J6*ODTCN) | S6: =$N6+$R6 | T6: =IF($C6+$D6+$E6+$F6+$G6>0,$S6/($C6+$D6+$E6+$F6+$G6),0) | U6: =$K6+N(OtherInc) | V6: =SUMPRODUCT(($U6>FedThr)*(($U6)-FedThr)*FedDlt) | W6: =(FedBPAMax-(FedBPAMax-FedBPAMin)*MIN(1,MAX(0,(($U6)-FedPhLow)/(FedPhHigh-FedPhLow)))) | X6: =MAX(0,$V6-$W6*FedLowRate-$I6*FDTCE-$J6*FDTCN) | Y6: =SUMPRODUCT(($U6>ONThr)*(($U6)-ONThr)*ONDlt) | Z6: =MAX(0,$Y6-ONBPA*ONLowRate) | AA6: =ONSurR1*MAX(0,$Z6-ONSur1)+ONSurR2*MAX(0,$Z6-ONSur2) | AB6: =MAX(0,$Z6+$AA6-$I6*ODTCE-$J6*ODTCN) | AC6: =$X6+$AB6 | AD6: =IF($B6=0,0,$AC6-BaseTaxTotal) | AE6: =MAX(0,SUMPRODUCT((N(OtherInc)+$E6>FedThr)*((N(OtherInc)+$E6)-FedThr)*FedDlt)-(FedBPAMax-(FedBPAMax-FedBPAMin)*MIN(1,MAX(0,((N(OtherInc)+$E6)-FedPhLow)/(FedPhHigh-FedPhLow))))*FedLowRate) | AF6: =MAX(0,SUMPRODUCT((N(OtherInc)+$E6>ONThr)*((N(OtherInc)+$E6)-ONThr)*ONDlt)-ONBPA*ONLowRate) | AG6: =$AE6+$AF6+ONSurR1*MAX(0,$AF6-ONSur1)+ONSurR2*MAX(0,$AF6-ONSur2) | AH6: =MAX(0,SUMPRODUCT((N(OtherInc)+$E6+$G6>FedThr)*((N(OtherInc)+$E6+$G6)-FedThr)*FedDlt)-(FedBPAMax-(FedBPAMax-FedBPAMin)*MIN(1,MAX(0,((N(OtherInc)+$E6+$G6)-FedPhLow)/(FedPhHigh-FedPhLow))))*FedLowRate) | AI6: =MAX(0,SUMPRODUCT((N(OtherInc)+$E6+$G6>ONThr)*((N(OtherInc)+$E6+$G6)-ONThr)*ONDlt)-ONBPA*ONLowRate) | AJ6: =$AH6+$AI6+ONSurR1*MAX(0,$AI6-ONSur1)+ONSurR2*MAX(0,$AI6-ONSur2) | AK6: =MAX(0,SUMPRODUCT((N(OtherInc)+$E6+$G6+CGInc*$F6>FedThr)*((N(OtherInc)+$E6+$G6+CGInc*$F6)-FedThr)*FedDlt)-(FedBPAMax-(FedBPAMax-FedBPAMin)*MIN(1,MAX(0,((N(OtherInc)+$E6+$G6+CGInc*$F6)-FedPhLow)/(FedPhHigh-FedPhLow))))*FedLowRate) | AL6: =MAX(0,SUMPRODUCT((N(OtherInc)+$E6+$G6+CGInc*$F6>ONThr)*((N(OtherInc)+$E6+$G6+CGInc*$F6)-ONThr)*ONDlt)-ONBPA*ONLowRate) | AM6: =$AK6+$AL6+ONSurR1*MAX(0,$AL6-ONSur1)+ONSurR2*MAX(0,$AL6-ONSur2) | AN6: =IF($B6=0,0,$AG6-BaseTaxTotal) | AO6: =$AJ6-$AG6 | AP6: =$AM6-$AJ6 | AQ6: =$AC6-$AM6
A7: 4 | B7: =IF($A7<=HorizonY,1,0) | C7: =SUMIFS('Engine (Monthly)'!$CR$4:$CR$603,'Engine (Monthly)'!$C$4:$C$603,$A7) | D7: =SUMIFS('Engine (Monthly)'!$CS$4:$CS$603,'Engine (Monthly)'!$C$4:$C$603,$A7) | E7: =SUMIFS('Engine (Monthly)'!$CT$4:$CT$603,'Engine (Monthly)'!$C$4:$C$603,$A7) | F7: =MAX(0,SUMIFS('Engine (Monthly)'!$CV$4:$CV$603,'Engine (Monthly)'!$C$4:$C$603,$A7)) | G7: =SUMIFS('Engine (Monthly)'!$CL$4:$CL$603,'Engine (Monthly)'!$C$4:$C$603,$A7) | H7: =SUMIFS('Engine (Monthly)'!$BH$4:$BH$603,'Engine (Monthly)'!$C$4:$C$603,$A7) | I7: =$C7*(1+GUE) | J7: =$D7*(1+GUN) | K7: =$I7+$J7+$E7+CGInc*$F7+$G7 | L7: =SUMPRODUCT(($K7>FedThr)*(($K7)-FedThr)*FedDlt) | M7: =(FedBPAMax-(FedBPAMax-FedBPAMin)*MIN(1,MAX(0,(($K7)-FedPhLow)/(FedPhHigh-FedPhLow)))) | N7: =MAX(0,$L7-$M7*FedLowRate-$I7*FDTCE-$J7*FDTCN) | O7: =SUMPRODUCT(($K7>ONThr)*(($K7)-ONThr)*ONDlt) | P7: =MAX(0,$O7-ONBPA*ONLowRate) | Q7: =ONSurR1*MAX(0,$P7-ONSur1)+ONSurR2*MAX(0,$P7-ONSur2) | R7: =MAX(0,$P7+$Q7-$I7*ODTCE-$J7*ODTCN) | S7: =$N7+$R7 | T7: =IF($C7+$D7+$E7+$F7+$G7>0,$S7/($C7+$D7+$E7+$F7+$G7),0) | U7: =$K7+N(OtherInc) | V7: =SUMPRODUCT(($U7>FedThr)*(($U7)-FedThr)*FedDlt) | W7: =(FedBPAMax-(FedBPAMax-FedBPAMin)*MIN(1,MAX(0,(($U7)-FedPhLow)/(FedPhHigh-FedPhLow)))) | X7: =MAX(0,$V7-$W7*FedLowRate-$I7*FDTCE-$J7*FDTCN) | Y7: =SUMPRODUCT(($U7>ONThr)*(($U7)-ONThr)*ONDlt) | Z7: =MAX(0,$Y7-ONBPA*ONLowRate) | AA7: =ONSurR1*MAX(0,$Z7-ONSur1)+ONSurR2*MAX(0,$Z7-ONSur2) | AB7: =MAX(0,$Z7+$AA7-$I7*ODTCE-$J7*ODTCN) | AC7: =$X7+$AB7 | AD7: =IF($B7=0,0,$AC7-BaseTaxTotal) | AE7: =MAX(0,SUMPRODUCT((N(OtherInc)+$E7>FedThr)*((N(OtherInc)+$E7)-FedThr)*FedDlt)-(FedBPAMax-(FedBPAMax-FedBPAMin)*MIN(1,MAX(0,((N(OtherInc)+$E7)-FedPhLow)/(FedPhHigh-FedPhLow))))*FedLowRate) | AF7: =MAX(0,SUMPRODUCT((N(OtherInc)+$E7>ONThr)*((N(OtherInc)+$E7)-ONThr)*ONDlt)-ONBPA*ONLowRate) | AG7: =$AE7+$AF7+ONSurR1*MAX(0,$AF7-ONSur1)+ONSurR2*MAX(0,$AF7-ONSur2) | AH7: =MAX(0,SUMPRODUCT((N(OtherInc)+$E7+$G7>FedThr)*((N(OtherInc)+$E7+$G7)-FedThr)*FedDlt)-(FedBPAMax-(FedBPAMax-FedBPAMin)*MIN(1,MAX(0,((N(OtherInc)+$E7+$G7)-FedPhLow)/(FedPhHigh-FedPhLow))))*FedLowRate) | AI7: =MAX(0,SUMPRODUCT((N(OtherInc)+$E7+$G7>ONThr)*((N(OtherInc)+$E7+$G7)-ONThr)*ONDlt)-ONBPA*ONLowRate) | AJ7: =$AH7+$AI7+ONSurR1*MAX(0,$AI7-ONSur1)+ONSurR2*MAX(0,$AI7-ONSur2) | AK7: =MAX(0,SUMPRODUCT((N(OtherInc)+$E7+$G7+CGInc*$F7>FedThr)*((N(OtherInc)+$E7+$G7+CGInc*$F7)-FedThr)*FedDlt)-(FedBPAMax-(FedBPAMax-FedBPAMin)*MIN(1,MAX(0,((N(OtherInc)+$E7+$G7+CGInc*$F7)-FedPhLow)/(FedPhHigh-FedPhLow))))*FedLowRate) | AL7: =MAX(0,SUMPRODUCT((N(OtherInc)+$E7+$G7+CGInc*$F7>ONThr)*((N(OtherInc)+$E7+$G7+CGInc*$F7)-ONThr)*ONDlt)-ONBPA*ONLowRate) | AM7: =$AK7+$AL7+ONSurR1*MAX(0,$AL7-ONSur1)+ONSurR2*MAX(0,$AL7-ONSur2) | AN7: =IF($B7=0,0,$AG7-BaseTaxTotal) | AO7: =$AJ7-$AG7 | AP7: =$AM7-$AJ7 | AQ7: =$AC7-$AM7
A8: 5 | B8: =IF($A8<=HorizonY,1,0) | C8: =SUMIFS('Engine (Monthly)'!$CR$4:$CR$603,'Engine (Monthly)'!$C$4:$C$603,$A8) | D8: =SUMIFS('Engine (Monthly)'!$CS$4:$CS$603,'Engine (Monthly)'!$C$4:$C$603,$A8) | E8: =SUMIFS('Engine (Monthly)'!$CT$4:$CT$603,'Engine (Monthly)'!$C$4:$C$603,$A8) | F8: =MAX(0,SUMIFS('Engine (Monthly)'!$CV$4:$CV$603,'Engine (Monthly)'!$C$4:$C$603,$A8)) | G8: =SUMIFS('Engine (Monthly)'!$CL$4:$CL$603,'Engine (Monthly)'!$C$4:$C$603,$A8) | H8: =SUMIFS('Engine (Monthly)'!$BH$4:$BH$603,'Engine (Monthly)'!$C$4:$C$603,$A8) | I8: =$C8*(1+GUE) | J8: =$D8*(1+GUN) | K8: =$I8+$J8+$E8+CGInc*$F8+$G8 | L8: =SUMPRODUCT(($K8>FedThr)*(($K8)-FedThr)*FedDlt) | M8: =(FedBPAMax-(FedBPAMax-FedBPAMin)*MIN(1,MAX(0,(($K8)-FedPhLow)/(FedPhHigh-FedPhLow)))) | N8: =MAX(0,$L8-$M8*FedLowRate-$I8*FDTCE-$J8*FDTCN) | O8: =SUMPRODUCT(($K8>ONThr)*(($K8)-ONThr)*ONDlt) | P8: =MAX(0,$O8-ONBPA*ONLowRate) | Q8: =ONSurR1*MAX(0,$P8-ONSur1)+ONSurR2*MAX(0,$P8-ONSur2) | R8: =MAX(0,$P8+$Q8-$I8*ODTCE-$J8*ODTCN) | S8: =$N8+$R8 | T8: =IF($C8+$D8+$E8+$F8+$G8>0,$S8/($C8+$D8+$E8+$F8+$G8),0) | U8: =$K8+N(OtherInc) | V8: =SUMPRODUCT(($U8>FedThr)*(($U8)-FedThr)*FedDlt) | W8: =(FedBPAMax-(FedBPAMax-FedBPAMin)*MIN(1,MAX(0,(($U8)-FedPhLow)/(FedPhHigh-FedPhLow)))) | X8: =MAX(0,$V8-$W8*FedLowRate-$I8*FDTCE-$J8*FDTCN) | Y8: =SUMPRODUCT(($U8>ONThr)*(($U8)-ONThr)*ONDlt) | Z8: =MAX(0,$Y8-ONBPA*ONLowRate) | AA8: =ONSurR1*MAX(0,$Z8-ONSur1)+ONSurR2*MAX(0,$Z8-ONSur2) | AB8: =MAX(0,$Z8+$AA8-$I8*ODTCE-$J8*ODTCN) | AC8: =$X8+$AB8 | AD8: =IF($B8=0,0,$AC8-BaseTaxTotal) | AE8: =MAX(0,SUMPRODUCT((N(OtherInc)+$E8>FedThr)*((N(OtherInc)+$E8)-FedThr)*FedDlt)-(FedBPAMax-(FedBPAMax-FedBPAMin)*MIN(1,MAX(0,((N(OtherInc)+$E8)-FedPhLow)/(FedPhHigh-FedPhLow))))*FedLowRate) | AF8: =MAX(0,SUMPRODUCT((N(OtherInc)+$E8>ONThr)*((N(OtherInc)+$E8)-ONThr)*ONDlt)-ONBPA*ONLowRate) | AG8: =$AE8+$AF8+ONSurR1*MAX(0,$AF8-ONSur1)+ONSurR2*MAX(0,$AF8-ONSur2) | AH8: =MAX(0,SUMPRODUCT((N(OtherInc)+$E8+$G8>FedThr)*((N(OtherInc)+$E8+$G8)-FedThr)*FedDlt)-(FedBPAMax-(FedBPAMax-FedBPAMin)*MIN(1,MAX(0,((N(OtherInc)+$E8+$G8)-FedPhLow)/(FedPhHigh-FedPhLow))))*FedLowRate) | AI8: =MAX(0,SUMPRODUCT((N(OtherInc)+$E8+$G8>ONThr)*((N(OtherInc)+$E8+$G8)-ONThr)*ONDlt)-ONBPA*ONLowRate) | AJ8: =$AH8+$AI8+ONSurR1*MAX(0,$AI8-ONSur1)+ONSurR2*MAX(0,$AI8-ONSur2) | AK8: =MAX(0,SUMPRODUCT((N(OtherInc)+$E8+$G8+CGInc*$F8>FedThr)*((N(OtherInc)+$E8+$G8+CGInc*$F8)-FedThr)*FedDlt)-(FedBPAMax-(FedBPAMax-FedBPAMin)*MIN(1,MAX(0,((N(OtherInc)+$E8+$G8+CGInc*$F8)-FedPhLow)/(FedPhHigh-FedPhLow))))*FedLowRate) | AL8: =MAX(0,SUMPRODUCT((N(OtherInc)+$E8+$G8+CGInc*$F8>ONThr)*((N(OtherInc)+$E8+$G8+CGInc*$F8)-ONThr)*ONDlt)-ONBPA*ONLowRate) | AM8: =$AK8+$AL8+ONSurR1*MAX(0,$AL8-ONSur1)+ONSurR2*MAX(0,$AL8-ONSur2) | AN8: =IF($B8=0,0,$AG8-BaseTaxTotal) | AO8: =$AJ8-$AG8 | AP8: =$AM8-$AJ8 | AQ8: =$AC8-$AM8
A9: 6 | B9: =IF($A9<=HorizonY,1,0) | C9: =SUMIFS('Engine (Monthly)'!$CR$4:$CR$603,'Engine (Monthly)'!$C$4:$C$603,$A9) | D9: =SUMIFS('Engine (Monthly)'!$CS$4:$CS$603,'Engine (Monthly)'!$C$4:$C$603,$A9) | E9: =SUMIFS('Engine (Monthly)'!$CT$4:$CT$603,'Engine (Monthly)'!$C$4:$C$603,$A9) | F9: =MAX(0,SUMIFS('Engine (Monthly)'!$CV$4:$CV$603,'Engine (Monthly)'!$C$4:$C$603,$A9)) | G9: =SUMIFS('Engine (Monthly)'!$CL$4:$CL$603,'Engine (Monthly)'!$C$4:$C$603,$A9) | H9: =SUMIFS('Engine (Monthly)'!$BH$4:$BH$603,'Engine (Monthly)'!$C$4:$C$603,$A9) | I9: =$C9*(1+GUE) | J9: =$D9*(1+GUN) | K9: =$I9+$J9+$E9+CGInc*$F9+$G9 | L9: =SUMPRODUCT(($K9>FedThr)*(($K9)-FedThr)*FedDlt) | M9: =(FedBPAMax-(FedBPAMax-FedBPAMin)*MIN(1,MAX(0,(($K9)-FedPhLow)/(FedPhHigh-FedPhLow)))) | N9: =MAX(0,$L9-$M9*FedLowRate-$I9*FDTCE-$J9*FDTCN) | O9: =SUMPRODUCT(($K9>ONThr)*(($K9)-ONThr)*ONDlt) | P9: =MAX(0,$O9-ONBPA*ONLowRate) | Q9: =ONSurR1*MAX(0,$P9-ONSur1)+ONSurR2*MAX(0,$P9-ONSur2) | R9: =MAX(0,$P9+$Q9-$I9*ODTCE-$J9*ODTCN) | S9: =$N9+$R9 | T9: =IF($C9+$D9+$E9+$F9+$G9>0,$S9/($C9+$D9+$E9+$F9+$G9),0) | U9: =$K9+N(OtherInc) | V9: =SUMPRODUCT(($U9>FedThr)*(($U9)-FedThr)*FedDlt) | W9: =(FedBPAMax-(FedBPAMax-FedBPAMin)*MIN(1,MAX(0,(($U9)-FedPhLow)/(FedPhHigh-FedPhLow)))) | X9: =MAX(0,$V9-$W9*FedLowRate-$I9*FDTCE-$J9*FDTCN) | Y9: =SUMPRODUCT(($U9>ONThr)*(($U9)-ONThr)*ONDlt) | Z9: =MAX(0,$Y9-ONBPA*ONLowRate) | AA9: =ONSurR1*MAX(0,$Z9-ONSur1)+ONSurR2*MAX(0,$Z9-ONSur2) | AB9: =MAX(0,$Z9+$AA9-$I9*ODTCE-$J9*ODTCN) | AC9: =$X9+$AB9 | AD9: =IF($B9=0,0,$AC9-BaseTaxTotal) | AE9: =MAX(0,SUMPRODUCT((N(OtherInc)+$E9>FedThr)*((N(OtherInc)+$E9)-FedThr)*FedDlt)-(FedBPAMax-(FedBPAMax-FedBPAMin)*MIN(1,MAX(0,((N(OtherInc)+$E9)-FedPhLow)/(FedPhHigh-FedPhLow))))*FedLowRate) | AF9: =MAX(0,SUMPRODUCT((N(OtherInc)+$E9>ONThr)*((N(OtherInc)+$E9)-ONThr)*ONDlt)-ONBPA*ONLowRate) | AG9: =$AE9+$AF9+ONSurR1*MAX(0,$AF9-ONSur1)+ONSurR2*MAX(0,$AF9-ONSur2) | AH9: =MAX(0,SUMPRODUCT((N(OtherInc)+$E9+$G9>FedThr)*((N(OtherInc)+$E9+$G9)-FedThr)*FedDlt)-(FedBPAMax-(FedBPAMax-FedBPAMin)*MIN(1,MAX(0,((N(OtherInc)+$E9+$G9)-FedPhLow)/(FedPhHigh-FedPhLow))))*FedLowRate) | AI9: =MAX(0,SUMPRODUCT((N(OtherInc)+$E9+$G9>ONThr)*((N(OtherInc)+$E9+$G9)-ONThr)*ONDlt)-ONBPA*ONLowRate) | AJ9: =$AH9+$AI9+ONSurR1*MAX(0,$AI9-ONSur1)+ONSurR2*MAX(0,$AI9-ONSur2) | AK9: =MAX(0,SUMPRODUCT((N(OtherInc)+$E9+$G9+CGInc*$F9>FedThr)*((N(OtherInc)+$E9+$G9+CGInc*$F9)-FedThr)*FedDlt)-(FedBPAMax-(FedBPAMax-FedBPAMin)*MIN(1,MAX(0,((N(OtherInc)+$E9+$G9+CGInc*$F9)-FedPhLow)/(FedPhHigh-FedPhLow))))*FedLowRate) | AL9: =MAX(0,SUMPRODUCT((N(OtherInc)+$E9+$G9+CGInc*$F9>ONThr)*((N(OtherInc)+$E9+$G9+CGInc*$F9)-ONThr)*ONDlt)-ONBPA*ONLowRate) | AM9: =$AK9+$AL9+ONSurR1*MAX(0,$AL9-ONSur1)+ONSurR2*MAX(0,$AL9-ONSur2) | AN9: =IF($B9=0,0,$AG9-BaseTaxTotal) | AO9: =$AJ9-$AG9 | AP9: =$AM9-$AJ9 | AQ9: =$AC9-$AM9
A10: 7 | B10: =IF($A10<=HorizonY,1,0) | C10: =SUMIFS('Engine (Monthly)'!$CR$4:$CR$603,'Engine (Monthly)'!$C$4:$C$603,$A10) | D10: =SUMIFS('Engine (Monthly)'!$CS$4:$CS$603,'Engine (Monthly)'!$C$4:$C$603,$A10) | E10: =SUMIFS('Engine (Monthly)'!$CT$4:$CT$603,'Engine (Monthly)'!$C$4:$C$603,$A10) | F10: =MAX(0,SUMIFS('Engine (Monthly)'!$CV$4:$CV$603,'Engine (Monthly)'!$C$4:$C$603,$A10)) | G10: =SUMIFS('Engine (Monthly)'!$CL$4:$CL$603,'Engine (Monthly)'!$C$4:$C$603,$A10) | H10: =SUMIFS('Engine (Monthly)'!$BH$4:$BH$603,'Engine (Monthly)'!$C$4:$C$603,$A10) | I10: =$C10*(1+GUE) | J10: =$D10*(1+GUN) | K10: =$I10+$J10+$E10+CGInc*$F10+$G10 | L10: =SUMPRODUCT(($K10>FedThr)*(($K10)-FedThr)*FedDlt) | M10: =(FedBPAMax-(FedBPAMax-FedBPAMin)*MIN(1,MAX(0,(($K10)-FedPhLow)/(FedPhHigh-FedPhLow)))) | N10: =MAX(0,$L10-$M10*FedLowRate-$I10*FDTCE-$J10*FDTCN) | O10: =SUMPRODUCT(($K10>ONThr)*(($K10)-ONThr)*ONDlt) | P10: =MAX(0,$O10-ONBPA*ONLowRate) | Q10: =ONSurR1*MAX(0,$P10-ONSur1)+ONSurR2*MAX(0,$P10-ONSur2) | R10: =MAX(0,$P10+$Q10-$I10*ODTCE-$J10*ODTCN) | S10: =$N10+$R10 | T10: =IF($C10+$D10+$E10+$F10+$G10>0,$S10/($C10+$D10+$E10+$F10+$G10),0) | U10: =$K10+N(OtherInc) | V10: =SUMPRODUCT(($U10>FedThr)*(($U10)-FedThr)*FedDlt) | W10: =(FedBPAMax-(FedBPAMax-FedBPAMin)*MIN(1,MAX(0,(($U10)-FedPhLow)/(FedPhHigh-FedPhLow)))) | X10: =MAX(0,$V10-$W10*FedLowRate-$I10*FDTCE-$J10*FDTCN) | Y10: =SUMPRODUCT(($U10>ONThr)*(($U10)-ONThr)*ONDlt) | Z10: =MAX(0,$Y10-ONBPA*ONLowRate) | AA10: =ONSurR1*MAX(0,$Z10-ONSur1)+ONSurR2*MAX(0,$Z10-ONSur2) | AB10: =MAX(0,$Z10+$AA10-$I10*ODTCE-$J10*ODTCN) | AC10: =$X10+$AB10 | AD10: =IF($B10=0,0,$AC10-BaseTaxTotal) | AE10: =MAX(0,SUMPRODUCT((N(OtherInc)+$E10>FedThr)*((N(OtherInc)+$E10)-FedThr)*FedDlt)-(FedBPAMax-(FedBPAMax-FedBPAMin)*MIN(1,MAX(0,((N(OtherInc)+$E10)-FedPhLow)/(FedPhHigh-FedPhLow))))*FedLowRate) | AF10: =MAX(0,SUMPRODUCT((N(OtherInc)+$E10>ONThr)*((N(OtherInc)+$E10)-ONThr)*ONDlt)-ONBPA*ONLowRate) | AG10: =$AE10+$AF10+ONSurR1*MAX(0,$AF10-ONSur1)+ONSurR2*MAX(0,$AF10-ONSur2) | AH10: =MAX(0,SUMPRODUCT((N(OtherInc)+$E10+$G10>FedThr)*((N(OtherInc)+$E10+$G10)-FedThr)*FedDlt)-(FedBPAMax-(FedBPAMax-FedBPAMin)*MIN(1,MAX(0,((N(OtherInc)+$E10+$G10)-FedPhLow)/(FedPhHigh-FedPhLow))))*FedLowRate) | AI10: =MAX(0,SUMPRODUCT((N(OtherInc)+$E10+$G10>ONThr)*((N(OtherInc)+$E10+$G10)-ONThr)*ONDlt)-ONBPA*ONLowRate) | AJ10: =$AH10+$AI10+ONSurR1*MAX(0,$AI10-ONSur1)+ONSurR2*MAX(0,$AI10-ONSur2) | AK10: =MAX(0,SUMPRODUCT((N(OtherInc)+$E10+$G10+CGInc*$F10>FedThr)*((N(OtherInc)+$E10+$G10+CGInc*$F10)-FedThr)*FedDlt)-(FedBPAMax-(FedBPAMax-FedBPAMin)*MIN(1,MAX(0,((N(OtherInc)+$E10+$G10+CGInc*$F10)-FedPhLow)/(FedPhHigh-FedPhLow))))*FedLowRate) | AL10: =MAX(0,SUMPRODUCT((N(OtherInc)+$E10+$G10+CGInc*$F10>ONThr)*((N(OtherInc)+$E10+$G10+CGInc*$F10)-ONThr)*ONDlt)-ONBPA*ONLowRate) | AM10: =$AK10+$AL10+ONSurR1*MAX(0,$AL10-ONSur1)+ONSurR2*MAX(0,$AL10-ONSur2) | AN10: =IF($B10=0,0,$AG10-BaseTaxTotal) | AO10: =$AJ10-$AG10 | AP10: =$AM10-$AJ10 | AQ10: =$AC10-$AM10
A11: 8 | B11: =IF($A11<=HorizonY,1,0) | C11: =SUMIFS('Engine (Monthly)'!$CR$4:$CR$603,'Engine (Monthly)'!$C$4:$C$603,$A11) | D11: =SUMIFS('Engine (Monthly)'!$CS$4:$CS$603,'Engine (Monthly)'!$C$4:$C$603,$A11) | E11: =SUMIFS('Engine (Monthly)'!$CT$4:$CT$603,'Engine (Monthly)'!$C$4:$C$603,$A11) | F11: =MAX(0,SUMIFS('Engine (Monthly)'!$CV$4:$CV$603,'Engine (Monthly)'!$C$4:$C$603,$A11)) | G11: =SUMIFS('Engine (Monthly)'!$CL$4:$CL$603,'Engine (Monthly)'!$C$4:$C$603,$A11) | H11: =SUMIFS('Engine (Monthly)'!$BH$4:$BH$603,'Engine (Monthly)'!$C$4:$C$603,$A11) | I11: =$C11*(1+GUE) | J11: =$D11*(1+GUN) | K11: =$I11+$J11+$E11+CGInc*$F11+$G11 | L11: =SUMPRODUCT(($K11>FedThr)*(($K11)-FedThr)*FedDlt) | M11: =(FedBPAMax-(FedBPAMax-FedBPAMin)*MIN(1,MAX(0,(($K11)-FedPhLow)/(FedPhHigh-FedPhLow)))) | N11: =MAX(0,$L11-$M11*FedLowRate-$I11*FDTCE-$J11*FDTCN) | O11: =SUMPRODUCT(($K11>ONThr)*(($K11)-ONThr)*ONDlt) | P11: =MAX(0,$O11-ONBPA*ONLowRate) | Q11: =ONSurR1*MAX(0,$P11-ONSur1)+ONSurR2*MAX(0,$P11-ONSur2) | R11: =MAX(0,$P11+$Q11-$I11*ODTCE-$J11*ODTCN) | S11: =$N11+$R11 | T11: =IF($C11+$D11+$E11+$F11+$G11>0,$S11/($C11+$D11+$E11+$F11+$G11),0) | U11: =$K11+N(OtherInc) | V11: =SUMPRODUCT(($U11>FedThr)*(($U11)-FedThr)*FedDlt) | W11: =(FedBPAMax-(FedBPAMax-FedBPAMin)*MIN(1,MAX(0,(($U11)-FedPhLow)/(FedPhHigh-FedPhLow)))) | X11: =MAX(0,$V11-$W11*FedLowRate-$I11*FDTCE-$J11*FDTCN) | Y11: =SUMPRODUCT(($U11>ONThr)*(($U11)-ONThr)*ONDlt) | Z11: =MAX(0,$Y11-ONBPA*ONLowRate) | AA11: =ONSurR1*MAX(0,$Z11-ONSur1)+ONSurR2*MAX(0,$Z11-ONSur2) | AB11: =MAX(0,$Z11+$AA11-$I11*ODTCE-$J11*ODTCN) | AC11: =$X11+$AB11 | AD11: =IF($B11=0,0,$AC11-BaseTaxTotal) | AE11: =MAX(0,SUMPRODUCT((N(OtherInc)+$E11>FedThr)*((N(OtherInc)+$E11)-FedThr)*FedDlt)-(FedBPAMax-(FedBPAMax-FedBPAMin)*MIN(1,MAX(0,((N(OtherInc)+$E11)-FedPhLow)/(FedPhHigh-FedPhLow))))*FedLowRate) | AF11: =MAX(0,SUMPRODUCT((N(OtherInc)+$E11>ONThr)*((N(OtherInc)+$E11)-ONThr)*ONDlt)-ONBPA*ONLowRate) | AG11: =$AE11+$AF11+ONSurR1*MAX(0,$AF11-ONSur1)+ONSurR2*MAX(0,$AF11-ONSur2) | AH11: =MAX(0,SUMPRODUCT((N(OtherInc)+$E11+$G11>FedThr)*((N(OtherInc)+$E11+$G11)-FedThr)*FedDlt)-(FedBPAMax-(FedBPAMax-FedBPAMin)*MIN(1,MAX(0,((N(OtherInc)+$E11+$G11)-FedPhLow)/(FedPhHigh-FedPhLow))))*FedLowRate) | AI11: =MAX(0,SUMPRODUCT((N(OtherInc)+$E11+$G11>ONThr)*((N(OtherInc)+$E11+$G11)-ONThr)*ONDlt)-ONBPA*ONLowRate) | AJ11: =$AH11+$AI11+ONSurR1*MAX(0,$AI11-ONSur1)+ONSurR2*MAX(0,$AI11-ONSur2) | AK11: =MAX(0,SUMPRODUCT((N(OtherInc)+$E11+$G11+CGInc*$F11>FedThr)*((N(OtherInc)+$E11+$G11+CGInc*$F11)-FedThr)*FedDlt)-(FedBPAMax-(FedBPAMax-FedBPAMin)*MIN(1,MAX(0,((N(OtherInc)+$E11+$G11+CGInc*$F11)-FedPhLow)/(FedPhHigh-FedPhLow))))*FedLowRate) | AL11: =MAX(0,SUMPRODUCT((N(OtherInc)+$E11+$G11+CGInc*$F11>ONThr)*((N(OtherInc)+$E11+$G11+CGInc*$F11)-ONThr)*ONDlt)-ONBPA*ONLowRate) | AM11: =$AK11+$AL11+ONSurR1*MAX(0,$AL11-ONSur1)+ONSurR2*MAX(0,$AL11-ONSur2) | AN11: =IF($B11=0,0,$AG11-BaseTaxTotal) | AO11: =$AJ11-$AG11 | AP11: =$AM11-$AJ11 | AQ11: =$AC11-$AM11
A12: 9 | B12: =IF($A12<=HorizonY,1,0) | C12: =SUMIFS('Engine (Monthly)'!$CR$4:$CR$603,'Engine (Monthly)'!$C$4:$C$603,$A12) | D12: =SUMIFS('Engine (Monthly)'!$CS$4:$CS$603,'Engine (Monthly)'!$C$4:$C$603,$A12) | E12: =SUMIFS('Engine (Monthly)'!$CT$4:$CT$603,'Engine (Monthly)'!$C$4:$C$603,$A12) | F12: =MAX(0,SUMIFS('Engine (Monthly)'!$CV$4:$CV$603,'Engine (Monthly)'!$C$4:$C$603,$A12)) | G12: =SUMIFS('Engine (Monthly)'!$CL$4:$CL$603,'Engine (Monthly)'!$C$4:$C$603,$A12) | H12: =SUMIFS('Engine (Monthly)'!$BH$4:$BH$603,'Engine (Monthly)'!$C$4:$C$603,$A12) | I12: =$C12*(1+GUE) | J12: =$D12*(1+GUN) | K12: =$I12+$J12+$E12+CGInc*$F12+$G12 | L12: =SUMPRODUCT(($K12>FedThr)*(($K12)-FedThr)*FedDlt) | M12: =(FedBPAMax-(FedBPAMax-FedBPAMin)*MIN(1,MAX(0,(($K12)-FedPhLow)/(FedPhHigh-FedPhLow)))) | N12: =MAX(0,$L12-$M12*FedLowRate-$I12*FDTCE-$J12*FDTCN) | O12: =SUMPRODUCT(($K12>ONThr)*(($K12)-ONThr)*ONDlt) | P12: =MAX(0,$O12-ONBPA*ONLowRate) | Q12: =ONSurR1*MAX(0,$P12-ONSur1)+ONSurR2*MAX(0,$P12-ONSur2) | R12: =MAX(0,$P12+$Q12-$I12*ODTCE-$J12*ODTCN) | S12: =$N12+$R12 | T12: =IF($C12+$D12+$E12+$F12+$G12>0,$S12/($C12+$D12+$E12+$F12+$G12),0) | U12: =$K12+N(OtherInc) | V12: =SUMPRODUCT(($U12>FedThr)*(($U12)-FedThr)*FedDlt) | W12: =(FedBPAMax-(FedBPAMax-FedBPAMin)*MIN(1,MAX(0,(($U12)-FedPhLow)/(FedPhHigh-FedPhLow)))) | X12: =MAX(0,$V12-$W12*FedLowRate-$I12*FDTCE-$J12*FDTCN) | Y12: =SUMPRODUCT(($U12>ONThr)*(($U12)-ONThr)*ONDlt) | Z12: =MAX(0,$Y12-ONBPA*ONLowRate) | AA12: =ONSurR1*MAX(0,$Z12-ONSur1)+ONSurR2*MAX(0,$Z12-ONSur2) | AB12: =MAX(0,$Z12+$AA12-$I12*ODTCE-$J12*ODTCN) | AC12: =$X12+$AB12 | AD12: =IF($B12=0,0,$AC12-BaseTaxTotal) | AE12: =MAX(0,SUMPRODUCT((N(OtherInc)+$E12>FedThr)*((N(OtherInc)+$E12)-FedThr)*FedDlt)-(FedBPAMax-(FedBPAMax-FedBPAMin)*MIN(1,MAX(0,((N(OtherInc)+$E12)-FedPhLow)/(FedPhHigh-FedPhLow))))*FedLowRate) | AF12: =MAX(0,SUMPRODUCT((N(OtherInc)+$E12>ONThr)*((N(OtherInc)+$E12)-ONThr)*ONDlt)-ONBPA*ONLowRate) | AG12: =$AE12+$AF12+ONSurR1*MAX(0,$AF12-ONSur1)+ONSurR2*MAX(0,$AF12-ONSur2) | AH12: =MAX(0,SUMPRODUCT((N(OtherInc)+$E12+$G12>FedThr)*((N(OtherInc)+$E12+$G12)-FedThr)*FedDlt)-(FedBPAMax-(FedBPAMax-FedBPAMin)*MIN(1,MAX(0,((N(OtherInc)+$E12+$G12)-FedPhLow)/(FedPhHigh-FedPhLow))))*FedLowRate) | AI12: =MAX(0,SUMPRODUCT((N(OtherInc)+$E12+$G12>ONThr)*((N(OtherInc)+$E12+$G12)-ONThr)*ONDlt)-ONBPA*ONLowRate) | AJ12: =$AH12+$AI12+ONSurR1*MAX(0,$AI12-ONSur1)+ONSurR2*MAX(0,$AI12-ONSur2) | AK12: =MAX(0,SUMPRODUCT((N(OtherInc)+$E12+$G12+CGInc*$F12>FedThr)*((N(OtherInc)+$E12+$G12+CGInc*$F12)-FedThr)*FedDlt)-(FedBPAMax-(FedBPAMax-FedBPAMin)*MIN(1,MAX(0,((N(OtherInc)+$E12+$G12+CGInc*$F12)-FedPhLow)/(FedPhHigh-FedPhLow))))*FedLowRate) | AL12: =MAX(0,SUMPRODUCT((N(OtherInc)+$E12+$G12+CGInc*$F12>ONThr)*((N(OtherInc)+$E12+$G12+CGInc*$F12)-ONThr)*ONDlt)-ONBPA*ONLowRate) | AM12: =$AK12+$AL12+ONSurR1*MAX(0,$AL12-ONSur1)+ONSurR2*MAX(0,$AL12-ONSur2) | AN12: =IF($B12=0,0,$AG12-BaseTaxTotal) | AO12: =$AJ12-$AG12 | AP12: =$AM12-$AJ12 | AQ12: =$AC12-$AM12
A13: 10 | B13: =IF($A13<=HorizonY,1,0) | C13: =SUMIFS('Engine (Monthly)'!$CR$4:$CR$603,'Engine (Monthly)'!$C$4:$C$603,$A13) | D13: =SUMIFS('Engine (Monthly)'!$CS$4:$CS$603,'Engine (Monthly)'!$C$4:$C$603,$A13) | E13: =SUMIFS('Engine (Monthly)'!$CT$4:$CT$603,'Engine (Monthly)'!$C$4:$C$603,$A13) | F13: =MAX(0,SUMIFS('Engine (Monthly)'!$CV$4:$CV$603,'Engine (Monthly)'!$C$4:$C$603,$A13)) | G13: =SUMIFS('Engine (Monthly)'!$CL$4:$CL$603,'Engine (Monthly)'!$C$4:$C$603,$A13) | H13: =SUMIFS('Engine (Monthly)'!$BH$4:$BH$603,'Engine (Monthly)'!$C$4:$C$603,$A13) | I13: =$C13*(1+GUE) | J13: =$D13*(1+GUN) | K13: =$I13+$J13+$E13+CGInc*$F13+$G13 | L13: =SUMPRODUCT(($K13>FedThr)*(($K13)-FedThr)*FedDlt) | M13: =(FedBPAMax-(FedBPAMax-FedBPAMin)*MIN(1,MAX(0,(($K13)-FedPhLow)/(FedPhHigh-FedPhLow)))) | N13: =MAX(0,$L13-$M13*FedLowRate-$I13*FDTCE-$J13*FDTCN) | O13: =SUMPRODUCT(($K13>ONThr)*(($K13)-ONThr)*ONDlt) | P13: =MAX(0,$O13-ONBPA*ONLowRate) | Q13: =ONSurR1*MAX(0,$P13-ONSur1)+ONSurR2*MAX(0,$P13-ONSur2) | R13: =MAX(0,$P13+$Q13-$I13*ODTCE-$J13*ODTCN) | S13: =$N13+$R13 | T13: =IF($C13+$D13+$E13+$F13+$G13>0,$S13/($C13+$D13+$E13+$F13+$G13),0) | U13: =$K13+N(OtherInc) | V13: =SUMPRODUCT(($U13>FedThr)*(($U13)-FedThr)*FedDlt) | W13: =(FedBPAMax-(FedBPAMax-FedBPAMin)*MIN(1,MAX(0,(($U13)-FedPhLow)/(FedPhHigh-FedPhLow)))) | X13: =MAX(0,$V13-$W13*FedLowRate-$I13*FDTCE-$J13*FDTCN) | Y13: =SUMPRODUCT(($U13>ONThr)*(($U13)-ONThr)*ONDlt) | Z13: =MAX(0,$Y13-ONBPA*ONLowRate) | AA13: =ONSurR1*MAX(0,$Z13-ONSur1)+ONSurR2*MAX(0,$Z13-ONSur2) | AB13: =MAX(0,$Z13+$AA13-$I13*ODTCE-$J13*ODTCN) | AC13: =$X13+$AB13 | AD13: =IF($B13=0,0,$AC13-BaseTaxTotal) | AE13: =MAX(0,SUMPRODUCT((N(OtherInc)+$E13>FedThr)*((N(OtherInc)+$E13)-FedThr)*FedDlt)-(FedBPAMax-(FedBPAMax-FedBPAMin)*MIN(1,MAX(0,((N(OtherInc)+$E13)-FedPhLow)/(FedPhHigh-FedPhLow))))*FedLowRate) | AF13: =MAX(0,SUMPRODUCT((N(OtherInc)+$E13>ONThr)*((N(OtherInc)+$E13)-ONThr)*ONDlt)-ONBPA*ONLowRate) | AG13: =$AE13+$AF13+ONSurR1*MAX(0,$AF13-ONSur1)+ONSurR2*MAX(0,$AF13-ONSur2) | AH13: =MAX(0,SUMPRODUCT((N(OtherInc)+$E13+$G13>FedThr)*((N(OtherInc)+$E13+$G13)-FedThr)*FedDlt)-(FedBPAMax-(FedBPAMax-FedBPAMin)*MIN(1,MAX(0,((N(OtherInc)+$E13+$G13)-FedPhLow)/(FedPhHigh-FedPhLow))))*FedLowRate) | AI13: =MAX(0,SUMPRODUCT((N(OtherInc)+$E13+$G13>ONThr)*((N(OtherInc)+$E13+$G13)-ONThr)*ONDlt)-ONBPA*ONLowRate) | AJ13: =$AH13+$AI13+ONSurR1*MAX(0,$AI13-ONSur1)+ONSurR2*MAX(0,$AI13-ONSur2) | AK13: =MAX(0,SUMPRODUCT((N(OtherInc)+$E13+$G13+CGInc*$F13>FedThr)*((N(OtherInc)+$E13+$G13+CGInc*$F13)-FedThr)*FedDlt)-(FedBPAMax-(FedBPAMax-FedBPAMin)*MIN(1,MAX(0,((N(OtherInc)+$E13+$G13+CGInc*$F13)-FedPhLow)/(FedPhHigh-FedPhLow))))*FedLowRate) | AL13: =MAX(0,SUMPRODUCT((N(OtherInc)+$E13+$G13+CGInc*$F13>ONThr)*((N(OtherInc)+$E13+$G13+CGInc*$F13)-ONThr)*ONDlt)-ONBPA*ONLowRate) | AM13: =$AK13+$AL13+ONSurR1*MAX(0,$AL13-ONSur1)+ONSurR2*MAX(0,$AL13-ONSur2) | AN13: =IF($B13=0,0,$AG13-BaseTaxTotal) | AO13: =$AJ13-$AG13 | AP13: =$AM13-$AJ13 | AQ13: =$AC13-$AM13
A14: 11 | B14: =IF($A14<=HorizonY,1,0) | C14: =SUMIFS('Engine (Monthly)'!$CR$4:$CR$603,'Engine (Monthly)'!$C$4:$C$603,$A14) | D14: =SUMIFS('Engine (Monthly)'!$CS$4:$CS$603,'Engine (Monthly)'!$C$4:$C$603,$A14) | E14: =SUMIFS('Engine (Monthly)'!$CT$4:$CT$603,'Engine (Monthly)'!$C$4:$C$603,$A14) | F14: =MAX(0,SUMIFS('Engine (Monthly)'!$CV$4:$CV$603,'Engine (Monthly)'!$C$4:$C$603,$A14)) | G14: =SUMIFS('Engine (Monthly)'!$CL$4:$CL$603,'Engine (Monthly)'!$C$4:$C$603,$A14) | H14: =SUMIFS('Engine (Monthly)'!$BH$4:$BH$603,'Engine (Monthly)'!$C$4:$C$603,$A14) | I14: =$C14*(1+GUE) | J14: =$D14*(1+GUN) | K14: =$I14+$J14+$E14+CGInc*$F14+$G14 | L14: =SUMPRODUCT(($K14>FedThr)*(($K14)-FedThr)*FedDlt) | M14: =(FedBPAMax-(FedBPAMax-FedBPAMin)*MIN(1,MAX(0,(($K14)-FedPhLow)/(FedPhHigh-FedPhLow)))) | N14: =MAX(0,$L14-$M14*FedLowRate-$I14*FDTCE-$J14*FDTCN) | O14: =SUMPRODUCT(($K14>ONThr)*(($K14)-ONThr)*ONDlt) | P14: =MAX(0,$O14-ONBPA*ONLowRate) | Q14: =ONSurR1*MAX(0,$P14-ONSur1)+ONSurR2*MAX(0,$P14-ONSur2) | R14: =MAX(0,$P14+$Q14-$I14*ODTCE-$J14*ODTCN) | S14: =$N14+$R14 | T14: =IF($C14+$D14+$E14+$F14+$G14>0,$S14/($C14+$D14+$E14+$F14+$G14),0) | U14: =$K14+N(OtherInc) | V14: =SUMPRODUCT(($U14>FedThr)*(($U14)-FedThr)*FedDlt) | W14: =(FedBPAMax-(FedBPAMax-FedBPAMin)*MIN(1,MAX(0,(($U14)-FedPhLow)/(FedPhHigh-FedPhLow)))) | X14: =MAX(0,$V14-$W14*FedLowRate-$I14*FDTCE-$J14*FDTCN) | Y14: =SUMPRODUCT(($U14>ONThr)*(($U14)-ONThr)*ONDlt) | Z14: =MAX(0,$Y14-ONBPA*ONLowRate) | AA14: =ONSurR1*MAX(0,$Z14-ONSur1)+ONSurR2*MAX(0,$Z14-ONSur2) | AB14: =MAX(0,$Z14+$AA14-$I14*ODTCE-$J14*ODTCN) | AC14: =$X14+$AB14 | AD14: =IF($B14=0,0,$AC14-BaseTaxTotal) | AE14: =MAX(0,SUMPRODUCT((N(OtherInc)+$E14>FedThr)*((N(OtherInc)+$E14)-FedThr)*FedDlt)-(FedBPAMax-(FedBPAMax-FedBPAMin)*MIN(1,MAX(0,((N(OtherInc)+$E14)-FedPhLow)/(FedPhHigh-FedPhLow))))*FedLowRate) | AF14: =MAX(0,SUMPRODUCT((N(OtherInc)+$E14>ONThr)*((N(OtherInc)+$E14)-ONThr)*ONDlt)-ONBPA*ONLowRate) | AG14: =$AE14+$AF14+ONSurR1*MAX(0,$AF14-ONSur1)+ONSurR2*MAX(0,$AF14-ONSur2) | AH14: =MAX(0,SUMPRODUCT((N(OtherInc)+$E14+$G14>FedThr)*((N(OtherInc)+$E14+$G14)-FedThr)*FedDlt)-(FedBPAMax-(FedBPAMax-FedBPAMin)*MIN(1,MAX(0,((N(OtherInc)+$E14+$G14)-FedPhLow)/(FedPhHigh-FedPhLow))))*FedLowRate) | AI14: =MAX(0,SUMPRODUCT((N(OtherInc)+$E14+$G14>ONThr)*((N(OtherInc)+$E14+$G14)-ONThr)*ONDlt)-ONBPA*ONLowRate) | AJ14: =$AH14+$AI14+ONSurR1*MAX(0,$AI14-ONSur1)+ONSurR2*MAX(0,$AI14-ONSur2) | AK14: =MAX(0,SUMPRODUCT((N(OtherInc)+$E14+$G14+CGInc*$F14>FedThr)*((N(OtherInc)+$E14+$G14+CGInc*$F14)-FedThr)*FedDlt)-(FedBPAMax-(FedBPAMax-FedBPAMin)*MIN(1,MAX(0,((N(OtherInc)+$E14+$G14+CGInc*$F14)-FedPhLow)/(FedPhHigh-FedPhLow))))*FedLowRate) | AL14: =MAX(0,SUMPRODUCT((N(OtherInc)+$E14+$G14+CGInc*$F14>ONThr)*((N(OtherInc)+$E14+$G14+CGInc*$F14)-ONThr)*ONDlt)-ONBPA*ONLowRate) | AM14: =$AK14+$AL14+ONSurR1*MAX(0,$AL14-ONSur1)+ONSurR2*MAX(0,$AL14-ONSur2) | AN14: =IF($B14=0,0,$AG14-BaseTaxTotal) | AO14: =$AJ14-$AG14 | AP14: =$AM14-$AJ14 | AQ14: =$AC14-$AM14
A15: 12 | B15: =IF($A15<=HorizonY,1,0) | C15: =SUMIFS('Engine (Monthly)'!$CR$4:$CR$603,'Engine (Monthly)'!$C$4:$C$603,$A15) | D15: =SUMIFS('Engine (Monthly)'!$CS$4:$CS$603,'Engine (Monthly)'!$C$4:$C$603,$A15) | E15: =SUMIFS('Engine (Monthly)'!$CT$4:$CT$603,'Engine (Monthly)'!$C$4:$C$603,$A15) | F15: =MAX(0,SUMIFS('Engine (Monthly)'!$CV$4:$CV$603,'Engine (Monthly)'!$C$4:$C$603,$A15)) | G15: =SUMIFS('Engine (Monthly)'!$CL$4:$CL$603,'Engine (Monthly)'!$C$4:$C$603,$A15) | H15: =SUMIFS('Engine (Monthly)'!$BH$4:$BH$603,'Engine (Monthly)'!$C$4:$C$603,$A15) | I15: =$C15*(1+GUE) | J15: =$D15*(1+GUN) | K15: =$I15+$J15+$E15+CGInc*$F15+$G15 | L15: =SUMPRODUCT(($K15>FedThr)*(($K15)-FedThr)*FedDlt) | M15: =(FedBPAMax-(FedBPAMax-FedBPAMin)*MIN(1,MAX(0,(($K15)-FedPhLow)/(FedPhHigh-FedPhLow)))) | N15: =MAX(0,$L15-$M15*FedLowRate-$I15*FDTCE-$J15*FDTCN) | O15: =SUMPRODUCT(($K15>ONThr)*(($K15)-ONThr)*ONDlt) | P15: =MAX(0,$O15-ONBPA*ONLowRate) | Q15: =ONSurR1*MAX(0,$P15-ONSur1)+ONSurR2*MAX(0,$P15-ONSur2) | R15: =MAX(0,$P15+$Q15-$I15*ODTCE-$J15*ODTCN) | S15: =$N15+$R15 | T15: =IF($C15+$D15+$E15+$F15+$G15>0,$S15/($C15+$D15+$E15+$F15+$G15),0) | U15: =$K15+N(OtherInc) | V15: =SUMPRODUCT(($U15>FedThr)*(($U15)-FedThr)*FedDlt) | W15: =(FedBPAMax-(FedBPAMax-FedBPAMin)*MIN(1,MAX(0,(($U15)-FedPhLow)/(FedPhHigh-FedPhLow)))) | X15: =MAX(0,$V15-$W15*FedLowRate-$I15*FDTCE-$J15*FDTCN) | Y15: =SUMPRODUCT(($U15>ONThr)*(($U15)-ONThr)*ONDlt) | Z15: =MAX(0,$Y15-ONBPA*ONLowRate) | AA15: =ONSurR1*MAX(0,$Z15-ONSur1)+ONSurR2*MAX(0,$Z15-ONSur2) | AB15: =MAX(0,$Z15+$AA15-$I15*ODTCE-$J15*ODTCN) | AC15: =$X15+$AB15 | AD15: =IF($B15=0,0,$AC15-BaseTaxTotal) | AE15: =MAX(0,SUMPRODUCT((N(OtherInc)+$E15>FedThr)*((N(OtherInc)+$E15)-FedThr)*FedDlt)-(FedBPAMax-(FedBPAMax-FedBPAMin)*MIN(1,MAX(0,((N(OtherInc)+$E15)-FedPhLow)/(FedPhHigh-FedPhLow))))*FedLowRate) | AF15: =MAX(0,SUMPRODUCT((N(OtherInc)+$E15>ONThr)*((N(OtherInc)+$E15)-ONThr)*ONDlt)-ONBPA*ONLowRate) | AG15: =$AE15+$AF15+ONSurR1*MAX(0,$AF15-ONSur1)+ONSurR2*MAX(0,$AF15-ONSur2) | AH15: =MAX(0,SUMPRODUCT((N(OtherInc)+$E15+$G15>FedThr)*((N(OtherInc)+$E15+$G15)-FedThr)*FedDlt)-(FedBPAMax-(FedBPAMax-FedBPAMin)*MIN(1,MAX(0,((N(OtherInc)+$E15+$G15)-FedPhLow)/(FedPhHigh-FedPhLow))))*FedLowRate) | AI15: =MAX(0,SUMPRODUCT((N(OtherInc)+$E15+$G15>ONThr)*((N(OtherInc)+$E15+$G15)-ONThr)*ONDlt)-ONBPA*ONLowRate) | AJ15: =$AH15+$AI15+ONSurR1*MAX(0,$AI15-ONSur1)+ONSurR2*MAX(0,$AI15-ONSur2) | AK15: =MAX(0,SUMPRODUCT((N(OtherInc)+$E15+$G15+CGInc*$F15>FedThr)*((N(OtherInc)+$E15+$G15+CGInc*$F15)-FedThr)*FedDlt)-(FedBPAMax-(FedBPAMax-FedBPAMin)*MIN(1,MAX(0,((N(OtherInc)+$E15+$G15+CGInc*$F15)-FedPhLow)/(FedPhHigh-FedPhLow))))*FedLowRate) | AL15: =MAX(0,SUMPRODUCT((N(OtherInc)+$E15+$G15+CGInc*$F15>ONThr)*((N(OtherInc)+$E15+$G15+CGInc*$F15)-ONThr)*ONDlt)-ONBPA*ONLowRate) | AM15: =$AK15+$AL15+ONSurR1*MAX(0,$AL15-ONSur1)+ONSurR2*MAX(0,$AL15-ONSur2) | AN15: =IF($B15=0,0,$AG15-BaseTaxTotal) | AO15: =$AJ15-$AG15 | AP15: =$AM15-$AJ15 | AQ15: =$AC15-$AM15
... A53: 50 | B53: =IF($A53<=HorizonY,1,0) | C53: =SUMIFS('Engine (Monthly)'!$CR$4:$CR$603,'Engine (Monthly)'!$C$4:$C$603,$A53) | D53: =SUMIFS('Engine (Monthly)'!$CS$4:$CS$603,'Engine (Monthly)'!$C$4:$C$603,$A53) | E53: =SUMIFS('Engine (Monthly)'!$CT$4:$CT$603,'Engine (Monthly)'!$C$4:$C$603,$A53) | F53: =MAX(0,SUMIFS('Engine (Monthly)'!$CV$4:$CV$603,'Engine (Monthly)'!$C$4:$C$603,$A53)) | G53: =SUMIFS('Engine (Monthly)'!$CL$4:$CL$603,'Engine (Monthly)'!$C$4:$C$603,$A53) | H53: =SUMIFS('Engine (Monthly)'!$BH$4:$BH$603,'Engine (Monthly)'!$C$4:$C$603,$A53) | I53: =$C53*(1+GUE) | J53: =$D53*(1+GUN) | K53: =$I53+$J53+$E53+CGInc*$F53+$G53 | L53: =SUMPRODUCT(($K53>FedThr)*(($K53)-FedThr)*FedDlt) | M53: =(FedBPAMax-(FedBPAMax-FedBPAMin)*MIN(1,MAX(0,(($K53)-FedPhLow)/(FedPhHigh-FedPhLow)))) | N53: =MAX(0,$L53-$M53*FedLowRate-$I53*FDTCE-$J53*FDTCN) | O53: =SUMPRODUCT(($K53>ONThr)*(($K53)-ONThr)*ONDlt) | P53: =MAX(0,$O53-ONBPA*ONLowRate) | Q53: =ONSurR1*MAX(0,$P53-ONSur1)+ONSurR2*MAX(0,$P53-ONSur2) | R53: =MAX(0,$P53+$Q53-$I53*ODTCE-$J53*ODTCN) | S53: =$N53+$R53 | T53: =IF($C53+$D53+$E53+$F53+$G53>0,$S53/($C53+$D53+$E53+$F53+$G53),0) | U53: =$K53+N(OtherInc) | V53: =SUMPRODUCT(($U53>FedThr)*(($U53)-FedThr)*FedDlt) | W53: =(FedBPAMax-(FedBPAMax-FedBPAMin)*MIN(1,MAX(0,(($U53)-FedPhLow)/(FedPhHigh-FedPhLow)))) | X53: =MAX(0,$V53-$W53*FedLowRate-$I53*FDTCE-$J53*FDTCN) | Y53: =SUMPRODUCT(($U53>ONThr)*(($U53)-ONThr)*ONDlt) | Z53: =MAX(0,$Y53-ONBPA*ONLowRate) | AA53: =ONSurR1*MAX(0,$Z53-ONSur1)+ONSurR2*MAX(0,$Z53-ONSur2) | AB53: =MAX(0,$Z53+$AA53-$I53*ODTCE-$J53*ODTCN) | AC53: =$X53+$AB53 | AD53: =IF($B53=0,0,$AC53-BaseTaxTotal) | AE53: =MAX(0,SUMPRODUCT((N(OtherInc)+$E53>FedThr)*((N(OtherInc)+$E53)-FedThr)*FedDlt)-(FedBPAMax-(FedBPAMax-FedBPAMin)*MIN(1,MAX(0,((N(OtherInc)+$E53)-FedPhLow)/(FedPhHigh-FedPhLow))))*FedLowRate) | AF53: =MAX(0,SUMPRODUCT((N(OtherInc)+$E53>ONThr)*((N(OtherInc)+$E53)-ONThr)*ONDlt)-ONBPA*ONLowRate) | AG53: =$AE53+$AF53+ONSurR1*MAX(0,$AF53-ONSur1)+ONSurR2*MAX(0,$AF53-ONSur2) | AH53: =MAX(0,SUMPRODUCT((N(OtherInc)+$E53+$G53>FedThr)*((N(OtherInc)+$E53+$G53)-FedThr)*FedDlt)-(FedBPAMax-(FedBPAMax-FedBPAMin)*MIN(1,MAX(0,((N(OtherInc)+$E53+$G53)-FedPhLow)/(FedPhHigh-FedPhLow))))*FedLowRate) | AI53: =MAX(0,SUMPRODUCT((N(OtherInc)+$E53+$G53>ONThr)*((N(OtherInc)+$E53+$G53)-ONThr)*ONDlt)-ONBPA*ONLowRate) | AJ53: =$AH53+$AI53+ONSurR1*MAX(0,$AI53-ONSur1)+ONSurR2*MAX(0,$AI53-ONSur2) | AK53: =MAX(0,SUMPRODUCT((N(OtherInc)+$E53+$G53+CGInc*$F53>FedThr)*((N(OtherInc)+$E53+$G53+CGInc*$F53)-FedThr)*FedDlt)-(FedBPAMax-(FedBPAMax-FedBPAMin)*MIN(1,MAX(0,((N(OtherInc)+$E53+$G53+CGInc*$F53)-FedPhLow)/(FedPhHigh-FedPhLow))))*FedLowRate) | AL53: =MAX(0,SUMPRODUCT((N(OtherInc)+$E53+$G53+CGInc*$F53>ONThr)*((N(OtherInc)+$E53+$G53+CGInc*$F53)-ONThr)*ONDlt)-ONBPA*ONLowRate) | AM53: =$AK53+$AL53+ONSurR1*MAX(0,$AL53-ONSur1)+ONSurR2*MAX(0,$AL53-ONSur2) | AN53: =IF($B53=0,0,$AG53-BaseTaxTotal) | AO53: =$AJ53-$AG53 | AP53: =$AM53-$AJ53 | AQ53: =$AC53-$AM53
A56: General strategies — not tax advice
A57: • Prioritize TFSA room — everything inside is tax-free, including withdrawals.
A58: • Hold interest-bearing assets (bonds, GICs, foreign dividends) inside registered accounts; hold eligible-dividend payers in non-registered accounts where the dividend tax credit applies.
A59: • Spread large sales across tax years to stay in lower brackets and reduce AMT risk.
A60: • RRSP contributions in high-income years can offset RRSP/RRIF withdrawal income.
A61: • Harvest capital losses in non-registered accounts to offset realized gains.
A62: • Spousal RRSPs and pension income splitting can shift income to a lower-bracket spouse.

Sheet Engine (Monthly)
A1: Row 1 = calculation helpers (monthly rate multipliers & contribution shares). | F1: =POWER(1+N(S1Ret)+DeltaBase,1/12) | G1: =POWER(1+N(S2Ret)+DeltaBase,1/12) | H1: =POWER(1+N(S3Ret)+DeltaBase,1/12) | I1: =POWER(1+N(S4Ret)+DeltaBase,1/12) | J1: =POWER(1+N(S5Ret)+DeltaBase,1/12) | K1: =POWER(1+N(S6Ret)+DeltaBase,1/12) | L1: =POWER(1+N(S1Yld),1/12)-1 | M1: =POWER(1+N(S2Yld),1/12)-1 | N1: =POWER(1+N(S3Yld),1/12)-1 | O1: =POWER(1+N(S4Yld),1/12)-1 | P1: =POWER(1+N(S5Yld),1/12)-1 | Q1: =POWER(1+N(S6Yld),1/12)-1 | R1: =N(DS1)*N(S1NR) | S1: =N(DS2)*N(S2NR) | T1: =N(DS3)*N(S3NR) | U1: =N(DS4)*N(S4NR) | V1: =N(DS5)*N(S5NR) | W1: =N(DS6)*N(S6NR) | AJ1: =POWER(1+N(S1Ret)+DeltaBase,1/12) | AK1: =POWER(1+N(S2Ret)+DeltaBase,1/12) | AL1: =POWER(1+N(S3Ret)+DeltaBase,1/12) | AM1: =POWER(1+N(S4Ret)+DeltaBase,1/12) | AN1: =POWER(1+N(S5Ret)+DeltaBase,1/12) | AO1: =POWER(1+N(S6Ret)+DeltaBase,1/12) | AP1: =POWER(1+N(S1Yld),1/12)-1 | AQ1: =POWER(1+N(S2Yld),1/12)-1 | AR1: =POWER(1+N(S3Yld),1/12)-1 | AS1: =POWER(1+N(S4Yld),1/12)-1 | AT1: =POWER(1+N(S5Yld),1/12)-1 | AU1: =POWER(1+N(S6Yld),1/12)-1 | AV1: =N(DS1)*N(S1TF) | AW1: =N(DS2)*N(S2TF) | AX1: =N(DS3)*N(S3TF) | AY1: =N(DS4)*N(S4TF) | AZ1: =N(DS5)*N(S5TF) | BA1: =N(DS6)*N(S6TF) | BN1: =POWER(1+N(S1Ret)+DeltaBase,1/12) | BO1: =POWER(1+N(S2Ret)+DeltaBase,1/12) | BP1: =POWER(1+N(S3Ret)+DeltaBase,1/12) | BQ1: =POWER(1+N(S4Ret)+DeltaBase,1/12) | BR1: =POWER(1+N(S5Ret)+DeltaBase,1/12) | BS1: =POWER(1+N(S6Ret)+DeltaBase,1/12) | BT1: =POWER(1+N(S1Yld),1/12)-1 | BU1: =POWER(1+N(S2Yld),1/12)-1 | BV1: =POWER(1+N(S3Yld),1/12)-1 | BW1: =POWER(1+N(S4Yld),1/12)-1 | BX1: =POWER(1+N(S5Yld),1/12)-1 | BY1: =POWER(1+N(S6Yld),1/12)-1 | BZ1: =N(DS1)*N(S1RR) | CA1: =N(DS2)*N(S2RR) | CB1: =N(DS3)*N(S3RR) | CC1: =N(DS4)*N(S4RR) | CD1: =N(DS5)*N(S5RR) | CE1: =N(DS6)*N(S6RR)
A2: Month | B2: Active | C2: Year | D2: Contribution $ | E2: Withdrawal target $ | F2: NR S1 post-growth | G2: NR S2 post-growth | H2: NR S3 post-growth | I2: NR S4 post-growth | J2: NR S5 post-growth | K2: NR S6 post-growth | L2: NR S1 dividends | M2: NR S2 dividends | N2: NR S3 dividends | O2: NR S4 dividends | P2: NR S5 dividends | Q2: NR S6 dividends | R2: NR S1 closing | S2: NR S2 closing | T2: NR S3 closing | U2: NR S4 closing | V2: NR S5 closing | W2: NR S6 closing | X2: NR contribution | Y2: NR balance post-growth | Z2: NR dividends | AA2: NR growth | AB2: NR capacity | AC2: NR capacity ahead | AD2: NR withdrawn | AE2: NR from divs/cash | AF2: NR sold | AG2: NR reinvested | AH2: NR cash bucket | AI2: NR balance | AJ2: TF S1 post-growth | AK2: TF S2 post-growth | AL2: TF S3 post-growth | AM2: TF S4 post-growth | AN2: TF S5 post-growth | AO2: TF S6 post-growth | AP2: TF S1 dividends | AQ2: TF S2 dividends | AR2: TF S3 dividends | AS2: TF S4 dividends | AT2: TF S5 dividends | AU2: TF S6 dividends | AV2: TF S1 closing | AW2: TF S2 closing | AX2: TF S3 closing | AY2: TF S4 closing | AZ2: TF S5 closing | BA2: TF S6 closing | BB2: TF contribution | BC2: TF balance post-growth | BD2: TF dividends | BE2: TF growth | BF2: TF capacity | BG2: TF capacity ahead | BH2: TF withdrawn | BI2: TF from divs/cash | BJ2: TF sold | BK2: TF reinvested | BL2: TF cash bucket | BM2: TF balance | BN2: RR S1 post-growth | BO2: RR S2 post-growth | BP2: RR S3 post-growth | BQ2: RR S4 post-growth | BR2: RR S5 post-growth | BS2: RR S6 post-growth | BT2: RR S1 dividends | BU2: RR S2 dividends | BV2: RR S3 dividends | BW2: RR S4 dividends | BX2: RR S5 dividends | BY2: RR S6 dividends | BZ2: RR S1 closing | CA2: RR S2 closing | CB2: RR S3 closing | CC2: RR S4 closing | CD2: RR S5 closing | CE2: RR S6 closing | CF2: RR contribution | CG2: RR balance post-growth | CH2: RR dividends | CI2: RR growth | CJ2: RR capacity | CK2: RR capacity ahead | CL2: RR withdrawn | CM2: RR from divs/cash | CN2: RR sold | CO2: RR reinvested | CP2: RR cash bucket | CQ2: RR balance | CR2: NR divs — eligible | CS2: NR divs — non-eligible | CT2: NR divs — foreign/interest | CU2: ACB base (pre-sale) | CV2: Realized gain (NR) | CW2: ACB (closing) | CX2: Total balance | CY2: Total withdrawn | CZ2: Funded by divs/cash | DA2: Funded by sales | DB2: Shortfall flag
A3: 0 | B3: 1 | C3: 0 | D3: 0 | E3: 0 | F3: 0 | G3: 0 | H3: 0 | I3: 0 | J3: 0 | K3: 0 | L3: 0 | M3: 0 | N3: 0 | O3: 0 | P3: 0 | Q3: 0 | R3: =StartValue*N(S1Alloc)*N(S1NR) | S3: =StartValue*N(S2Alloc)*N(S2NR) | T3: =StartValue*N(S3Alloc)*N(S3NR) | U3: =StartValue*N(S4Alloc)*N(S4NR) | V3: =StartValue*N(S5Alloc)*N(S5NR) | W3: =StartValue*N(S6Alloc)*N(S6NR) | X3: 0 | Y3: 0 | Z3: 0 | AA3: 0 | AB3: 0 | AC3: 0 | AD3: 0 | AE3: 0 | AF3: 0 | AG3: 0 | AH3: 0 | AI3: =SUM(R3:W3) | AJ3: 0 | AK3: 0 | AL3: 0 | AM3: 0 | AN3: 0 | AO3: 0 | AP3: 0 | AQ3: 0 | AR3: 0 | AS3: 0 | AT3: 0 | AU3: 0 | AV3: =StartValue*N(S1Alloc)*N(S1TF) | AW3: =StartValue*N(S2Alloc)*N(S2TF) | AX3: =StartValue*N(S3Alloc)*N(S3TF) | AY3: =StartValue*N(S4Alloc)*N(S4TF) | AZ3: =StartValue*N(S5Alloc)*N(S5TF) | BA3: =StartValue*N(S6Alloc)*N(S6TF) | BB3: 0 | BC3: 0 | BD3: 0 | BE3: 0 | BF3: 0 | BG3: 0 | BH3: 0 | BI3: 0 | BJ3: 0 | BK3: 0 | BL3: 0 | BM3: =SUM(AV3:BA3) | BN3: 0 | BO3: 0 | BP3: 0 | BQ3: 0 | BR3: 0 | BS3: 0 | BT3: 0 | BU3: 0 | BV3: 0 | BW3: 0 | BX3: 0 | BY3: 0 | BZ3: =StartValue*N(S1Alloc)*N(S1RR) | CA3: =StartValue*N(S2Alloc)*N(S2RR) | CB3: =StartValue*N(S3Alloc)*N(S3RR) | CC3: =StartValue*N(S4Alloc)*N(S4RR) | CD3: =StartValue*N(S5Alloc)*N(S5RR) | CE3: =StartValue*N(S6Alloc)*N(S6RR) | CF3: 0 | CG3: 0 | CH3: 0 | CI3: 0 | CJ3: 0 | CK3: 0 | CL3: 0 | CM3: 0 | CN3: 0 | CO3: 0 | CP3: 0 | CQ3: =SUM(BZ3:CE3) | CR3: 0 | CS3: 0 | CT3: 0 | CU3: =N(ACBPct)*SUM(R3:W3) | CV3: 0 | CW3: =N(ACBPct)*SUM(R3:W3) | CX3: =AI3+BM3+CQ3 | CY3: 0 | CZ3: 0 | DA3: 0 | DB3: 0
A4: =A3+1 | B4: =IF($A4<=HorizonM,1,0) | C4: =INT(($A4-1)/12)+1 | D4: =IF($B4=0,0,IF(AND($A4>=CStartEff,$A4<=CEndEff),ContribMonthly*POWER(1+N(ContribEsc),INT(($A4-CStartEff)/12)),0)) | E4: =IF($B4=0,0,IF(AND($A4>=WdStartEff,$A4<=WdEndEff),IF(WdFreq="Annual",IF(MOD($A4-WdStartEff,12)=0,N(WdAmt),0),WdMonthlyBase)*IF(WdIndexed="Yes",POWER(1+N(Inflation),INT(($A4-WdStartEff)/12)),1),0)) | F4: =IF($B4=0,R3,(R3+$D4*R$1)*F$1) | G4: =IF($B4=0,S3,(S3+$D4*S$1)*G$1) | H4: =IF($B4=0,T3,(T3+$D4*T$1)*H$1) | I4: =IF($B4=0,U3,(U3+$D4*U$1)*I$1) | J4: =IF($B4=0,V3,(V3+$D4*V$1)*J$1) | K4: =IF($B4=0,W3,(W3+$D4*W$1)*K$1) | L4: =IF($B4=0,0,(R3+$D4*R$1)*L$1) | M4: =IF($B4=0,0,(S3+$D4*S$1)*M$1) | N4: =IF($B4=0,0,(T3+$D4*T$1)*N$1) | O4: =IF($B4=0,0,(U3+$D4*U$1)*O$1) | P4: =IF($B4=0,0,(V3+$D4*V$1)*P$1) | Q4: =IF($B4=0,0,(W3+$D4*W$1)*Q$1) | R4: =IF(Y4=0,F4,F4*(1-(AF4-AG4)/Y4)) | S4: =IF(Y4=0,G4,G4*(1-(AF4-AG4)/Y4)) | T4: =IF(Y4=0,H4,H4*(1-(AF4-AG4)/Y4)) | U4: =IF(Y4=0,I4,I4*(1-(AF4-AG4)/Y4)) | V4: =IF(Y4=0,J4,J4*(1-(AF4-AG4)/Y4)) | W4: =IF(Y4=0,K4,K4*(1-(AF4-AG4)/Y4)) | X4: =$D4*(R$1+S$1+T$1+U$1+V$1+W$1) | Y4: =SUM(F4:K4) | Z4: =SUM(L4:Q4) | AA4: =Y4-SUM(R3:W3)-X4 | AB4: =AH3+Z4+Y4 | AC4: =IF(RankTF<RankNR,BF4,0)+IF(RankRR<RankNR,CJ4,0) | AD4: =MAX(0,MIN(AB4,$E4-AC4)) | AE4: =MIN(AD4,AH3+Z4) | AF4: =AD4-AE4 | AG4: =IF(DRIP="Yes",AH3+Z4-AE4,0) | AH4: =IF(DRIP="Yes",0,AH3+Z4-AE4) | AI4: =SUM(R4:W4)+AH4 | AJ4: =IF($B4=0,AV3,(AV3+$D4*AV$1)*AJ$1) | AK4: =IF($B4=0,AW3,(AW3+$D4*AW$1)*AK$1) | AL4: =IF($B4=0,AX3,(AX3+$D4*AX$1)*AL$1) | AM4: =IF($B4=0,AY3,(AY3+$D4*AY$1)*AM$1) | AN4: =IF($B4=0,AZ3,(AZ3+$D4*AZ$1)*AN$1) | AO4: =IF($B4=0,BA3,(BA3+$D4*BA$1)*AO$1) | AP4: =IF($B4=0,0,(AV3+$D4*AV$1)*AP$1) | AQ4: =IF($B4=0,0,(AW3+$D4*AW$1)*AQ$1) | AR4: =IF($B4=0,0,(AX3+$D4*AX$1)*AR$1) | AS4: =IF($B4=0,0,(AY3+$D4*AY$1)*AS$1) | AT4: =IF($B4=0,0,(AZ3+$D4*AZ$1)*AT$1) | AU4: =IF($B4=0,0,(BA3+$D4*BA$1)*AU$1) | AV4: =IF(BC4=0,AJ4,AJ4*(1-(BJ4-BK4)/BC4)) | AW4: =IF(BC4=0,AK4,AK4*(1-(BJ4-BK4)/BC4)) | AX4: =IF(BC4=0,AL4,AL4*(1-(BJ4-BK4)/BC4)) | AY4: =IF(BC4=0,AM4,AM4*(1-(BJ4-BK4)/BC4)) | AZ4: =IF(BC4=0,AN4,AN4*(1-(BJ4-BK4)/BC4)) | BA4: =IF(BC4=0,AO4,AO4*(1-(BJ4-BK4)/BC4)) | BB4: =$D4*(AV$1+AW$1+AX$1+AY$1+AZ$1+BA$1) | BC4: =SUM(AJ4:AO4) | BD4: =SUM(AP4:AU4) | BE4: =BC4-SUM(AV3:BA3)-BB4 | BF4: =BL3+BD4+BC4 | BG4: =IF(RankNR<RankTF,AB4,0)+IF(RankRR<RankTF,CJ4,0) | BH4: =MAX(0,MIN(BF4,$E4-BG4)) | BI4: =MIN(BH4,BL3+BD4) | BJ4: =BH4-BI4 | BK4: =IF(DRIP="Yes",BL3+BD4-BI4,0) | BL4: =IF(DRIP="Yes",0,BL3+BD4-BI4) | BM4: =SUM(AV4:BA4)+BL4 | BN4: =IF($B4=0,BZ3,(BZ3+$D4*BZ$1)*BN$1) | BO4: =IF($B4=0,CA3,(CA3+$D4*CA$1)*BO$1) | BP4: =IF($B4=0,CB3,(CB3+$D4*CB$1)*BP$1) | BQ4: =IF($B4=0,CC3,(CC3+$D4*CC$1)*BQ$1) | BR4: =IF($B4=0,CD3,(CD3+$D4*CD$1)*BR$1) | BS4: =IF($B4=0,CE3,(CE3+$D4*CE$1)*BS$1) | BT4: =IF($B4=0,0,(BZ3+$D4*BZ$1)*BT$1) | BU4: =IF($B4=0,0,(CA3+$D4*CA$1)*BU$1) | BV4: =IF($B4=0,0,(CB3+$D4*CB$1)*BV$1) | BW4: =IF($B4=0,0,(CC3+$D4*CC$1)*BW$1) | BX4: =IF($B4=0,0,(CD3+$D4*CD$1)*BX$1) | BY4: =IF($B4=0,0,(CE3+$D4*CE$1)*BY$1) | BZ4: =IF(CG4=0,BN4,BN4*(1-(CN4-CO4)/CG4)) | CA4: =IF(CG4=0,BO4,BO4*(1-(CN4-CO4)/CG4)) | CB4: =IF(CG4=0,BP4,BP4*(1-(CN4-CO4)/CG4)) | CC4: =IF(CG4=0,BQ4,BQ4*(1-(CN4-CO4)/CG4)) | CD4: =IF(CG4=0,BR4,BR4*(1-(CN4-CO4)/CG4)) | CE4: =IF(CG4=0,BS4,BS4*(1-(CN4-CO4)/CG4)) | CF4: =$D4*(BZ$1+CA$1+CB$1+CC$1+CD$1+CE$1) | CG4: =SUM(BN4:BS4) | CH4: =SUM(BT4:BY4) | CI4: =CG4-SUM(BZ3:CE3)-CF4 | CJ4: =CP3+CH4+CG4 | CK4: =IF(RankNR<RankRR,AB4,0)+IF(RankTF<RankRR,BF4,0) | CL4: =MAX(0,MIN(CJ4,$E4-CK4)) | CM4: =MIN(CL4,CP3+CH4) | CN4: =CL4-CM4 | CO4: =IF(DRIP="Yes",CP3+CH4-CM4,0) | CP4: =IF(DRIP="Yes",0,CP3+CH4-CM4) | CQ4: =SUM(BZ4:CE4)+CP4 | CR4: =IF(S1Type="Eligible",L4,0)+IF(S2Type="Eligible",M4,0)+IF(S3Type="Eligible",N4,0)+IF(S4Type="Eligible",O4,0)+IF(S5Type="Eligible",P4,0)+IF(S6Type="Eligible",Q4,0) | CS4: =IF(S1Type="Non-eligible",L4,0)+IF(S2Type="Non-eligible",M4,0)+IF(S3Type="Non-eligible",N4,0)+IF(S4Type="Non-eligible",O4,0)+IF(S5Type="Non-eligible",P4,0)+IF(S6Type="Non-eligible",Q4,0) | CT4: =IF(S1Type="Foreign / interest",L4,0)+IF(S2Type="Foreign / interest",M4,0)+IF(S3Type="Foreign / interest",N4,0)+IF(S4Type="Foreign / interest",O4,0)+IF(S5Type="Foreign / interest",P4,0)+IF(S6Type="Foreign / interest",Q4,0) | CU4: =CW3+X4 | CV4: =IF(Y4=0,0,AF4*(1-CU4/Y4)) | CW4: =IF(Y4=0,CU4,CU4*(1-AF4/Y4))+AG4 | CX4: =AI4+BM4+CQ4 | CY4: =AD4+BH4+CL4 | CZ4: =AE4+BI4+CM4 | DA4: =AF4+BJ4+CN4 | DB4: =IF(AND($B4=1,$E4-CY4>0.01),1,0)
A5: =A4+1 | B5: =IF($A5<=HorizonM,1,0) | C5: =INT(($A5-1)/12)+1 | D5: =IF($B5=0,0,IF(AND($A5>=CStartEff,$A5<=CEndEff),ContribMonthly*POWER(1+N(ContribEsc),INT(($A5-CStartEff)/12)),0)) | E5: =IF($B5=0,0,IF(AND($A5>=WdStartEff,$A5<=WdEndEff),IF(WdFreq="Annual",IF(MOD($A5-WdStartEff,12)=0,N(WdAmt),0),WdMonthlyBase)*IF(WdIndexed="Yes",POWER(1+N(Inflation),INT(($A5-WdStartEff)/12)),1),0)) | F5: =IF($B5=0,R4,(R4+$D5*R$1)*F$1) | G5: =IF($B5=0,S4,(S4+$D5*S$1)*G$1) | H5: =IF($B5=0,T4,(T4+$D5*T$1)*H$1) | I5: =IF($B5=0,U4,(U4+$D5*U$1)*I$1) | J5: =IF($B5=0,V4,(V4+$D5*V$1)*J$1) | K5: =IF($B5=0,W4,(W4+$D5*W$1)*K$1) | L5: =IF($B5=0,0,(R4+$D5*R$1)*L$1) | M5: =IF($B5=0,0,(S4+$D5*S$1)*M$1) | N5: =IF($B5=0,0,(T4+$D5*T$1)*N$1) | O5: =IF($B5=0,0,(U4+$D5*U$1)*O$1) | P5: =IF($B5=0,0,(V4+$D5*V$1)*P$1) | Q5: =IF($B5=0,0,(W4+$D5*W$1)*Q$1) | R5: =IF(Y5=0,F5,F5*(1-(AF5-AG5)/Y5)) | S5: =IF(Y5=0,G5,G5*(1-(AF5-AG5)/Y5)) | T5: =IF(Y5=0,H5,H5*(1-(AF5-AG5)/Y5)) | U5: =IF(Y5=0,I5,I5*(1-(AF5-AG5)/Y5)) | V5: =IF(Y5=0,J5,J5*(1-(AF5-AG5)/Y5)) | W5: =IF(Y5=0,K5,K5*(1-(AF5-AG5)/Y5)) | X5: =$D5*(R$1+S$1+T$1+U$1+V$1+W$1) | Y5: =SUM(F5:K5) | Z5: =SUM(L5:Q5) | AA5: =Y5-SUM(R4:W4)-X5 | AB5: =AH4+Z5+Y5 | AC5: =IF(RankTF<RankNR,BF5,0)+IF(RankRR<RankNR,CJ5,0) | AD5: =MAX(0,MIN(AB5,$E5-AC5)) | AE5: =MIN(AD5,AH4+Z5) | AF5: =AD5-AE5 | AG5: =IF(DRIP="Yes",AH4+Z5-AE5,0) | AH5: =IF(DRIP="Yes",0,AH4+Z5-AE5) | AI5: =SUM(R5:W5)+AH5 | AJ5: =IF($B5=0,AV4,(AV4+$D5*AV$1)*AJ$1) | AK5: =IF($B5=0,AW4,(AW4+$D5*AW$1)*AK$1) | AL5: =IF($B5=0,AX4,(AX4+$D5*AX$1)*AL$1) | AM5: =IF($B5=0,AY4,(AY4+$D5*AY$1)*AM$1) | AN5: =IF($B5=0,AZ4,(AZ4+$D5*AZ$1)*AN$1) | AO5: =IF($B5=0,BA4,(BA4+$D5*BA$1)*AO$1) | AP5: =IF($B5=0,0,(AV4+$D5*AV$1)*AP$1) | AQ5: =IF($B5=0,0,(AW4+$D5*AW$1)*AQ$1) | AR5: =IF($B5=0,0,(AX4+$D5*AX$1)*AR$1) | AS5: =IF($B5=0,0,(AY4+$D5*AY$1)*AS$1) | AT5: =IF($B5=0,0,(AZ4+$D5*AZ$1)*AT$1) | AU5: =IF($B5=0,0,(BA4+$D5*BA$1)*AU$1) | AV5: =IF(BC5=0,AJ5,AJ5*(1-(BJ5-BK5)/BC5)) | AW5: =IF(BC5=0,AK5,AK5*(1-(BJ5-BK5)/BC5)) | AX5: =IF(BC5=0,AL5,AL5*(1-(BJ5-BK5)/BC5)) | AY5: =IF(BC5=0,AM5,AM5*(1-(BJ5-BK5)/BC5)) | AZ5: =IF(BC5=0,AN5,AN5*(1-(BJ5-BK5)/BC5)) | BA5: =IF(BC5=0,AO5,AO5*(1-(BJ5-BK5)/BC5)) | BB5: =$D5*(AV$1+AW$1+AX$1+AY$1+AZ$1+BA$1) | BC5: =SUM(AJ5:AO5) | BD5: =SUM(AP5:AU5) | BE5: =BC5-SUM(AV4:BA4)-BB5 | BF5: =BL4+BD5+BC5 | BG5: =IF(RankNR<RankTF,AB5,0)+IF(RankRR<RankTF,CJ5,0) | BH5: =MAX(0,MIN(BF5,$E5-BG5)) | BI5: =MIN(BH5,BL4+BD5) | BJ5: =BH5-BI5 | BK5: =IF(DRIP="Yes",BL4+BD5-BI5,0) | BL5: =IF(DRIP="Yes",0,BL4+BD5-BI5) | BM5: =SUM(AV5:BA5)+BL5 | BN5: =IF($B5=0,BZ4,(BZ4+$D5*BZ$1)*BN$1) | BO5: =IF($B5=0,CA4,(CA4+$D5*CA$1)*BO$1) | BP5: =IF($B5=0,CB4,(CB4+$D5*CB$1)*BP$1) | BQ5: =IF($B5=0,CC4,(CC4+$D5*CC$1)*BQ$1) | BR5: =IF($B5=0,CD4,(CD4+$D5*CD$1)*BR$1) | BS5: =IF($B5=0,CE4,(CE4+$D5*CE$1)*BS$1) | BT5: =IF($B5=0,0,(BZ4+$D5*BZ$1)*BT$1) | BU5: =IF($B5=0,0,(CA4+$D5*CA$1)*BU$1) | BV5: =IF($B5=0,0,(CB4+$D5*CB$1)*BV$1) | BW5: =IF($B5=0,0,(CC4+$D5*CC$1)*BW$1) | BX5: =IF($B5=0,0,(CD4+$D5*CD$1)*BX$1) | BY5: =IF($B5=0,0,(CE4+$D5*CE$1)*BY$1) | BZ5: =IF(CG5=0,BN5,BN5*(1-(CN5-CO5)/CG5)) | CA5: =IF(CG5=0,BO5,BO5*(1-(CN5-CO5)/CG5)) | CB5: =IF(CG5=0,BP5,BP5*(1-(CN5-CO5)/CG5)) | CC5: =IF(CG5=0,BQ5,BQ5*(1-(CN5-CO5)/CG5)) | CD5: =IF(CG5=0,BR5,BR5*(1-(CN5-CO5)/CG5)) | CE5: =IF(CG5=0,BS5,BS5*(1-(CN5-CO5)/CG5)) | CF5: =$D5*(BZ$1+CA$1+CB$1+CC$1+CD$1+CE$1) | CG5: =SUM(BN5:BS5) | CH5: =SUM(BT5:BY5) | CI5: =CG5-SUM(BZ4:CE4)-CF5 | CJ5: =CP4+CH5+CG5 | CK5: =IF(RankNR<RankRR,AB5,0)+IF(RankTF<RankRR,BF5,0) | CL5: =MAX(0,MIN(CJ5,$E5-CK5)) | CM5: =MIN(CL5,CP4+CH5) | CN5: =CL5-CM5 | CO5: =IF(DRIP="Yes",CP4+CH5-CM5,0) | CP5: =IF(DRIP="Yes",0,CP4+CH5-CM5) | CQ5: =SUM(BZ5:CE5)+CP5 | CR5: =IF(S1Type="Eligible",L5,0)+IF(S2Type="Eligible",M5,0)+IF(S3Type="Eligible",N5,0)+IF(S4Type="Eligible",O5,0)+IF(S5Type="Eligible",P5,0)+IF(S6Type="Eligible",Q5,0) | CS5: =IF(S1Type="Non-eligible",L5,0)+IF(S2Type="Non-eligible",M5,0)+IF(S3Type="Non-eligible",N5,0)+IF(S4Type="Non-eligible",O5,0)+IF(S5Type="Non-eligible",P5,0)+IF(S6Type="Non-eligible",Q5,0) | CT5: =IF(S1Type="Foreign / interest",L5,0)+IF(S2Type="Foreign / interest",M5,0)+IF(S3Type="Foreign / interest",N5,0)+IF(S4Type="Foreign / interest",O5,0)+IF(S5Type="Foreign / interest",P5,0)+IF(S6Type="Foreign / interest",Q5,0) | CU5: =CW4+X5 | CV5: =IF(Y5=0,0,AF5*(1-CU5/Y5)) | CW5: =IF(Y5=0,CU5,CU5*(1-AF5/Y5))+AG5 | CX5: =AI5+BM5+CQ5 | CY5: =AD5+BH5+CL5 | CZ5: =AE5+BI5+CM5 | DA5: =AF5+BJ5+CN5 | DB5: =IF(AND($B5=1,$E5-CY5>0.01),1,0)
A6: =A5+1 | B6: =IF($A6<=HorizonM,1,0) | C6: =INT(($A6-1)/12)+1 | D6: =IF($B6=0,0,IF(AND($A6>=CStartEff,$A6<=CEndEff),ContribMonthly*POWER(1+N(ContribEsc),INT(($A6-CStartEff)/12)),0)) | E6: =IF($B6=0,0,IF(AND($A6>=WdStartEff,$A6<=WdEndEff),IF(WdFreq="Annual",IF(MOD($A6-WdStartEff,12)=0,N(WdAmt),0),WdMonthlyBase)*IF(WdIndexed="Yes",POWER(1+N(Inflation),INT(($A6-WdStartEff)/12)),1),0)) | F6: =IF($B6=0,R5,(R5+$D6*R$1)*F$1) | G6: =IF($B6=0,S5,(S5+$D6*S$1)*G$1) | H6: =IF($B6=0,T5,(T5+$D6*T$1)*H$1) | I6: =IF($B6=0,U5,(U5+$D6*U$1)*I$1) | J6: =IF($B6=0,V5,(V5+$D6*V$1)*J$1) | K6: =IF($B6=0,W5,(W5+$D6*W$1)*K$1) | L6: =IF($B6=0,0,(R5+$D6*R$1)*L$1) | M6: =IF($B6=0,0,(S5+$D6*S$1)*M$1) | N6: =IF($B6=0,0,(T5+$D6*T$1)*N$1) | O6: =IF($B6=0,0,(U5+$D6*U$1)*O$1) | P6: =IF($B6=0,0,(V5+$D6*V$1)*P$1) | Q6: =IF($B6=0,0,(W5+$D6*W$1)*Q$1) | R6: =IF(Y6=0,F6,F6*(1-(AF6-AG6)/Y6)) | S6: =IF(Y6=0,G6,G6*(1-(AF6-AG6)/Y6)) | T6: =IF(Y6=0,H6,H6*(1-(AF6-AG6)/Y6)) | U6: =IF(Y6=0,I6,I6*(1-(AF6-AG6)/Y6)) | V6: =IF(Y6=0,J6,J6*(1-(AF6-AG6)/Y6)) | W6: =IF(Y6=0,K6,K6*(1-(AF6-AG6)/Y6)) | X6: =$D6*(R$1+S$1+T$1+U$1+V$1+W$1) | Y6: =SUM(F6:K6) | Z6: =SUM(L6:Q6) | AA6: =Y6-SUM(R5:W5)-X6 | AB6: =AH5+Z6+Y6 | AC6: =IF(RankTF<RankNR,BF6,0)+IF(RankRR<RankNR,CJ6,0) | AD6: =MAX(0,MIN(AB6,$E6-AC6)) | AE6: =MIN(AD6,AH5+Z6) | AF6: =AD6-AE6 | AG6: =IF(DRIP="Yes",AH5+Z6-AE6,0) | AH6: =IF(DRIP="Yes",0,AH5+Z6-AE6) | AI6: =SUM(R6:W6)+AH6 | AJ6: =IF($B6=0,AV5,(AV5+$D6*AV$1)*AJ$1) | AK6: =IF($B6=0,AW5,(AW5+$D6*AW$1)*AK$1) | AL6: =IF($B6=0,AX5,(AX5+$D6*AX$1)*AL$1) | AM6: =IF($B6=0,AY5,(AY5+$D6*AY$1)*AM$1) | AN6: =IF($B6=0,AZ5,(AZ5+$D6*AZ$1)*AN$1) | AO6: =IF($B6=0,BA5,(BA5+$D6*BA$1)*AO$1) | AP6: =IF($B6=0,0,(AV5+$D6*AV$1)*AP$1) | AQ6: =IF($B6=0,0,(AW5+$D6*AW$1)*AQ$1) | AR6: =IF($B6=0,0,(AX5+$D6*AX$1)*AR$1) | AS6: =IF($B6=0,0,(AY5+$D6*AY$1)*AS$1) | AT6: =IF($B6=0,0,(AZ5+$D6*AZ$1)*AT$1) | AU6: =IF($B6=0,0,(BA5+$D6*BA$1)*AU$1) | AV6: =IF(BC6=0,AJ6,AJ6*(1-(BJ6-BK6)/BC6)) | AW6: =IF(BC6=0,AK6,AK6*(1-(BJ6-BK6)/BC6)) | AX6: =IF(BC6=0,AL6,AL6*(1-(BJ6-BK6)/BC6)) | AY6: =IF(BC6=0,AM6,AM6*(1-(BJ6-BK6)/BC6)) | AZ6: =IF(BC6=0,AN6,AN6*(1-(BJ6-BK6)/BC6)) | BA6: =IF(BC6=0,AO6,AO6*(1-(BJ6-BK6)/BC6)) | BB6: =$D6*(AV$1+AW$1+AX$1+AY$1+AZ$1+BA$1) | BC6: =SUM(AJ6:AO6) | BD6: =SUM(AP6:AU6) | BE6: =BC6-SUM(AV5:BA5)-BB6 | BF6: =BL5+BD6+BC6 | BG6: =IF(RankNR<RankTF,AB6,0)+IF(RankRR<RankTF,CJ6,0) | BH6: =MAX(0,MIN(BF6,$E6-BG6)) | BI6: =MIN(BH6,BL5+BD6) | BJ6: =BH6-BI6 | BK6: =IF(DRIP="Yes",BL5+BD6-BI6,0) | BL6: =IF(DRIP="Yes",0,BL5+BD6-BI6) | BM6: =SUM(AV6:BA6)+BL6 | BN6: =IF($B6=0,BZ5,(BZ5+$D6*BZ$1)*BN$1) | BO6: =IF($B6=0,CA5,(CA5+$D6*CA$1)*BO$1) | BP6: =IF($B6=0,CB5,(CB5+$D6*CB$1)*BP$1) | BQ6: =IF($B6=0,CC5,(CC5+$D6*CC$1)*BQ$1) | BR6: =IF($B6=0,CD5,(CD5+$D6*CD$1)*BR$1) | BS6: =IF($B6=0,CE5,(CE5+$D6*CE$1)*BS$1) | BT6: =IF($B6=0,0,(BZ5+$D6*BZ$1)*BT$1) | BU6: =IF($B6=0,0,(CA5+$D6*CA$1)*BU$1) | BV6: =IF($B6=0,0,(CB5+$D6*CB$1)*BV$1) | BW6: =IF($B6=0,0,(CC5+$D6*CC$1)*BW$1) | BX6: =IF($B6=0,0,(CD5+$D6*CD$1)*BX$1) | BY6: =IF($B6=0,0,(CE5+$D6*CE$1)*BY$1) | BZ6: =IF(CG6=0,BN6,BN6*(1-(CN6-CO6)/CG6)) | CA6: =IF(CG6=0,BO6,BO6*(1-(CN6-CO6)/CG6)) | CB6: =IF(CG6=0,BP6,BP6*(1-(CN6-CO6)/CG6)) | CC6: =IF(CG6=0,BQ6,BQ6*(1-(CN6-CO6)/CG6)) | CD6: =IF(CG6=0,BR6,BR6*(1-(CN6-CO6)/CG6)) | CE6: =IF(CG6=0,BS6,BS6*(1-(CN6-CO6)/CG6)) | CF6: =$D6*(BZ$1+CA$1+CB$1+CC$1+CD$1+CE$1) | CG6: =SUM(BN6:BS6) | CH6: =SUM(BT6:BY6) | CI6: =CG6-SUM(BZ5:CE5)-CF6 | CJ6: =CP5+CH6+CG6 | CK6: =IF(RankNR<RankRR,AB6,0)+IF(RankTF<RankRR,BF6,0) | CL6: =MAX(0,MIN(CJ6,$E6-CK6)) | CM6: =MIN(CL6,CP5+CH6) | CN6: =CL6-CM6 | CO6: =IF(DRIP="Yes",CP5+CH6-CM6,0) | CP6: =IF(DRIP="Yes",0,CP5+CH6-CM6) | CQ6: =SUM(BZ6:CE6)+CP6 | CR6: =IF(S1Type="Eligible",L6,0)+IF(S2Type="Eligible",M6,0)+IF(S3Type="Eligible",N6,0)+IF(S4Type="Eligible",O6,0)+IF(S5Type="Eligible",P6,0)+IF(S6Type="Eligible",Q6,0) | CS6: =IF(S1Type="Non-eligible",L6,0)+IF(S2Type="Non-eligible",M6,0)+IF(S3Type="Non-eligible",N6,0)+IF(S4Type="Non-eligible",O6,0)+IF(S5Type="Non-eligible",P6,0)+IF(S6Type="Non-eligible",Q6,0) | CT6: =IF(S1Type="Foreign / interest",L6,0)+IF(S2Type="Foreign / interest",M6,0)+IF(S3Type="Foreign / interest",N6,0)+IF(S4Type="Foreign / interest",O6,0)+IF(S5Type="Foreign / interest",P6,0)+IF(S6Type="Foreign / interest",Q6,0) | CU6: =CW5+X6 | CV6: =IF(Y6=0,0,AF6*(1-CU6/Y6)) | CW6: =IF(Y6=0,CU6,CU6*(1-AF6/Y6))+AG6 | CX6: =AI6+BM6+CQ6 | CY6: =AD6+BH6+CL6 | CZ6: =AE6+BI6+CM6 | DA6: =AF6+BJ6+CN6 | DB6: =IF(AND($B6=1,$E6-CY6>0.01),1,0)
A7: =A6+1 | B7: =IF($A7<=HorizonM,1,0) | C7: =INT(($A7-1)/12)+1 | D7: =IF($B7=0,0,IF(AND($A7>=CStartEff,$A7<=CEndEff),ContribMonthly*POWER(1+N(ContribEsc),INT(($A7-CStartEff)/12)),0)) | E7: =IF($B7=0,0,IF(AND($A7>=WdStartEff,$A7<=WdEndEff),IF(WdFreq="Annual",IF(MOD($A7-WdStartEff,12)=0,N(WdAmt),0),WdMonthlyBase)*IF(WdIndexed="Yes",POWER(1+N(Inflation),INT(($A7-WdStartEff)/12)),1),0)) | F7: =IF($B7=0,R6,(R6+$D7*R$1)*F$1) | G7: =IF($B7=0,S6,(S6+$D7*S$1)*G$1) | H7: =IF($B7=0,T6,(T6+$D7*T$1)*H$1) | I7: =IF($B7=0,U6,(U6+$D7*U$1)*I$1) | J7: =IF($B7=0,V6,(V6+$D7*V$1)*J$1) | K7: =IF($B7=0,W6,(W6+$D7*W$1)*K$1) | L7: =IF($B7=0,0,(R6+$D7*R$1)*L$1) | M7: =IF($B7=0,0,(S6+$D7*S$1)*M$1) | N7: =IF($B7=0,0,(T6+$D7*T$1)*N$1) | O7: =IF($B7=0,0,(U6+$D7*U$1)*O$1) | P7: =IF($B7=0,0,(V6+$D7*V$1)*P$1) | Q7: =IF($B7=0,0,(W6+$D7*W$1)*Q$1) | R7: =IF(Y7=0,F7,F7*(1-(AF7-AG7)/Y7)) | S7: =IF(Y7=0,G7,G7*(1-(AF7-AG7)/Y7)) | T7: =IF(Y7=0,H7,H7*(1-(AF7-AG7)/Y7)) | U7: =IF(Y7=0,I7,I7*(1-(AF7-AG7)/Y7)) | V7: =IF(Y7=0,J7,J7*(1-(AF7-AG7)/Y7)) | W7: =IF(Y7=0,K7,K7*(1-(AF7-AG7)/Y7)) | X7: =$D7*(R$1+S$1+T$1+U$1+V$1+W$1) | Y7: =SUM(F7:K7) | Z7: =SUM(L7:Q7) | AA7: =Y7-SUM(R6:W6)-X7 | AB7: =AH6+Z7+Y7 | AC7: =IF(RankTF<RankNR,BF7,0)+IF(RankRR<RankNR,CJ7,0) | AD7: =MAX(0,MIN(AB7,$E7-AC7)) | AE7: =MIN(AD7,AH6+Z7) | AF7: =AD7-AE7 | AG7: =IF(DRIP="Yes",AH6+Z7-AE7,0) | AH7: =IF(DRIP="Yes",0,AH6+Z7-AE7) | AI7: =SUM(R7:W7)+AH7 | AJ7: =IF($B7=0,AV6,(AV6+$D7*AV$1)*AJ$1) | AK7: =IF($B7=0,AW6,(AW6+$D7*AW$1)*AK$1) | AL7: =IF($B7=0,AX6,(AX6+$D7*AX$1)*AL$1) | AM7: =IF($B7=0,AY6,(AY6+$D7*AY$1)*AM$1) | AN7: =IF($B7=0,AZ6,(AZ6+$D7*AZ$1)*AN$1) | AO7: =IF($B7=0,BA6,(BA6+$D7*BA$1)*AO$1) | AP7: =IF($B7=0,0,(AV6+$D7*AV$1)*AP$1) | AQ7: =IF($B7=0,0,(AW6+$D7*AW$1)*AQ$1) | AR7: =IF($B7=0,0,(AX6+$D7*AX$1)*AR$1) | AS7: =IF($B7=0,0,(AY6+$D7*AY$1)*AS$1) | AT7: =IF($B7=0,0,(AZ6+$D7*AZ$1)*AT$1) | AU7: =IF($B7=0,0,(BA6+$D7*BA$1)*AU$1) | AV7: =IF(BC7=0,AJ7,AJ7*(1-(BJ7-BK7)/BC7)) | AW7: =IF(BC7=0,AK7,AK7*(1-(BJ7-BK7)/BC7)) | AX7: =IF(BC7=0,AL7,AL7*(1-(BJ7-BK7)/BC7)) | AY7: =IF(BC7=0,AM7,AM7*(1-(BJ7-BK7)/BC7)) | AZ7: =IF(BC7=0,AN7,AN7*(1-(BJ7-BK7)/BC7)) | BA7: =IF(BC7=0,AO7,AO7*(1-(BJ7-BK7)/BC7)) | BB7: =$D7*(AV$1+AW$1+AX$1+AY$1+AZ$1+BA$1) | BC7: =SUM(AJ7:AO7) | BD7: =SUM(AP7:AU7) | BE7: =BC7-SUM(AV6:BA6)-BB7 | BF7: =BL6+BD7+BC7 | BG7: =IF(RankNR<RankTF,AB7,0)+IF(RankRR<RankTF,CJ7,0) | BH7: =MAX(0,MIN(BF7,$E7-BG7)) | BI7: =MIN(BH7,BL6+BD7) | BJ7: =BH7-BI7 | BK7: =IF(DRIP="Yes",BL6+BD7-BI7,0) | BL7: =IF(DRIP="Yes",0,BL6+BD7-BI7) | BM7: =SUM(AV7:BA7)+BL7 | BN7: =IF($B7=0,BZ6,(BZ6+$D7*BZ$1)*BN$1) | BO7: =IF($B7=0,CA6,(CA6+$D7*CA$1)*BO$1) | BP7: =IF($B7=0,CB6,(CB6+$D7*CB$1)*BP$1) | BQ7: =IF($B7=0,CC6,(CC6+$D7*CC$1)*BQ$1) | BR7: =IF($B7=0,CD6,(CD6+$D7*CD$1)*BR$1) | BS7: =IF($B7=0,CE6,(CE6+$D7*CE$1)*BS$1) | BT7: =IF($B7=0,0,(BZ6+$D7*BZ$1)*BT$1) | BU7: =IF($B7=0,0,(CA6+$D7*CA$1)*BU$1) | BV7: =IF($B7=0,0,(CB6+$D7*CB$1)*BV$1) | BW7: =IF($B7=0,0,(CC6+$D7*CC$1)*BW$1) | BX7: =IF($B7=0,0,(CD6+$D7*CD$1)*BX$1) | BY7: =IF($B7=0,0,(CE6+$D7*CE$1)*BY$1) | BZ7: =IF(CG7=0,BN7,BN7*(1-(CN7-CO7)/CG7)) | CA7: =IF(CG7=0,BO7,BO7*(1-(CN7-CO7)/CG7)) | CB7: =IF(CG7=0,BP7,BP7*(1-(CN7-CO7)/CG7)) | CC7: =IF(CG7=0,BQ7,BQ7*(1-(CN7-CO7)/CG7)) | CD7: =IF(CG7=0,BR7,BR7*(1-(CN7-CO7)/CG7)) | CE7: =IF(CG7=0,BS7,BS7*(1-(CN7-CO7)/CG7)) | CF7: =$D7*(BZ$1+CA$1+CB$1+CC$1+CD$1+CE$1) | CG7: =SUM(BN7:BS7) | CH7: =SUM(BT7:BY7) | CI7: =CG7-SUM(BZ6:CE6)-CF7 | CJ7: =CP6+CH7+CG7 | CK7: =IF(RankNR<RankRR,AB7,0)+IF(RankTF<RankRR,BF7,0) | CL7: =MAX(0,MIN(CJ7,$E7-CK7)) | CM7: =MIN(CL7,CP6+CH7) | CN7: =CL7-CM7 | CO7: =IF(DRIP="Yes",CP6+CH7-CM7,0) | CP7: =IF(DRIP="Yes",0,CP6+CH7-CM7) | CQ7: =SUM(BZ7:CE7)+CP7 | CR7: =IF(S1Type="Eligible",L7,0)+IF(S2Type="Eligible",M7,0)+IF(S3Type="Eligible",N7,0)+IF(S4Type="Eligible",O7,0)+IF(S5Type="Eligible",P7,0)+IF(S6Type="Eligible",Q7,0) | CS7: =IF(S1Type="Non-eligible",L7,0)+IF(S2Type="Non-eligible",M7,0)+IF(S3Type="Non-eligible",N7,0)+IF(S4Type="Non-eligible",O7,0)+IF(S5Type="Non-eligible",P7,0)+IF(S6Type="Non-eligible",Q7,0) | CT7: =IF(S1Type="Foreign / interest",L7,0)+IF(S2Type="Foreign / interest",M7,0)+IF(S3Type="Foreign / interest",N7,0)+IF(S4Type="Foreign / interest",O7,0)+IF(S5Type="Foreign / interest",P7,0)+IF(S6Type="Foreign / interest",Q7,0) | CU7: =CW6+X7 | CV7: =IF(Y7=0,0,AF7*(1-CU7/Y7)) | CW7: =IF(Y7=0,CU7,CU7*(1-AF7/Y7))+AG7 | CX7: =AI7+BM7+CQ7 | CY7: =AD7+BH7+CL7 | CZ7: =AE7+BI7+CM7 | DA7: =AF7+BJ7+CN7 | DB7: =IF(AND($B7=1,$E7-CY7>0.01),1,0)
A8: =A7+1 | B8: =IF($A8<=HorizonM,1,0) | C8: =INT(($A8-1)/12)+1 | D8: =IF($B8=0,0,IF(AND($A8>=CStartEff,$A8<=CEndEff),ContribMonthly*POWER(1+N(ContribEsc),INT(($A8-CStartEff)/12)),0)) | E8: =IF($B8=0,0,IF(AND($A8>=WdStartEff,$A8<=WdEndEff),IF(WdFreq="Annual",IF(MOD($A8-WdStartEff,12)=0,N(WdAmt),0),WdMonthlyBase)*IF(WdIndexed="Yes",POWER(1+N(Inflation),INT(($A8-WdStartEff)/12)),1),0)) | F8: =IF($B8=0,R7,(R7+$D8*R$1)*F$1) | G8: =IF($B8=0,S7,(S7+$D8*S$1)*G$1) | H8: =IF($B8=0,T7,(T7+$D8*T$1)*H$1) | I8: =IF($B8=0,U7,(U7+$D8*U$1)*I$1) | J8: =IF($B8=0,V7,(V7+$D8*V$1)*J$1) | K8: =IF($B8=0,W7,(W7+$D8*W$1)*K$1) | L8: =IF($B8=0,0,(R7+$D8*R$1)*L$1) | M8: =IF($B8=0,0,(S7+$D8*S$1)*M$1) | N8: =IF($B8=0,0,(T7+$D8*T$1)*N$1) | O8: =IF($B8=0,0,(U7+$D8*U$1)*O$1) | P8: =IF($B8=0,0,(V7+$D8*V$1)*P$1) | Q8: =IF($B8=0,0,(W7+$D8*W$1)*Q$1) | R8: =IF(Y8=0,F8,F8*(1-(AF8-AG8)/Y8)) | S8: =IF(Y8=0,G8,G8*(1-(AF8-AG8)/Y8)) | T8: =IF(Y8=0,H8,H8*(1-(AF8-AG8)/Y8)) | U8: =IF(Y8=0,I8,I8*(1-(AF8-AG8)/Y8)) | V8: =IF(Y8=0,J8,J8*(1-(AF8-AG8)/Y8)) | W8: =IF(Y8=0,K8,K8*(1-(AF8-AG8)/Y8)) | X8: =$D8*(R$1+S$1+T$1+U$1+V$1+W$1) | Y8: =SUM(F8:K8) | Z8: =SUM(L8:Q8) | AA8: =Y8-SUM(R7:W7)-X8 | AB8: =AH7+Z8+Y8 | AC8: =IF(RankTF<RankNR,BF8,0)+IF(RankRR<RankNR,CJ8,0) | AD8: =MAX(0,MIN(AB8,$E8-AC8)) | AE8: =MIN(AD8,AH7+Z8) | AF8: =AD8-AE8 | AG8: =IF(DRIP="Yes",AH7+Z8-AE8,0) | AH8: =IF(DRIP="Yes",0,AH7+Z8-AE8) | AI8: =SUM(R8:W8)+AH8 | AJ8: =IF($B8=0,AV7,(AV7+$D8*AV$1)*AJ$1) | AK8: =IF($B8=0,AW7,(AW7+$D8*AW$1)*AK$1) | AL8: =IF($B8=0,AX7,(AX7+$D8*AX$1)*AL$1) | AM8: =IF($B8=0,AY7,(AY7+$D8*AY$1)*AM$1) | AN8: =IF($B8=0,AZ7,(AZ7+$D8*AZ$1)*AN$1) | AO8: =IF($B8=0,BA7,(BA7+$D8*BA$1)*AO$1) | AP8: =IF($B8=0,0,(AV7+$D8*AV$1)*AP$1) | AQ8: =IF($B8=0,0,(AW7+$D8*AW$1)*AQ$1) | AR8: =IF($B8=0,0,(AX7+$D8*AX$1)*AR$1) | AS8: =IF($B8=0,0,(AY7+$D8*AY$1)*AS$1) | AT8: =IF($B8=0,0,(AZ7+$D8*AZ$1)*AT$1) | AU8: =IF($B8=0,0,(BA7+$D8*BA$1)*AU$1) | AV8: =IF(BC8=0,AJ8,AJ8*(1-(BJ8-BK8)/BC8)) | AW8: =IF(BC8=0,AK8,AK8*(1-(BJ8-BK8)/BC8)) | AX8: =IF(BC8=0,AL8,AL8*(1-(BJ8-BK8)/BC8)) | AY8: =IF(BC8=0,AM8,AM8*(1-(BJ8-BK8)/BC8)) | AZ8: =IF(BC8=0,AN8,AN8*(1-(BJ8-BK8)/BC8)) | BA8: =IF(BC8=0,AO8,AO8*(1-(BJ8-BK8)/BC8)) | BB8: =$D8*(AV$1+AW$1+AX$1+AY$1+AZ$1+BA$1) | BC8: =SUM(AJ8:AO8) | BD8: =SUM(AP8:AU8) | BE8: =BC8-SUM(AV7:BA7)-BB8 | BF8: =BL7+BD8+BC8 | BG8: =IF(RankNR<RankTF,AB8,0)+IF(RankRR<RankTF,CJ8,0) | BH8: =MAX(0,MIN(BF8,$E8-BG8)) | BI8: =MIN(BH8,BL7+BD8) | BJ8: =BH8-BI8 | BK8: =IF(DRIP="Yes",BL7+BD8-BI8,0) | BL8: =IF(DRIP="Yes",0,BL7+BD8-BI8) | BM8: =SUM(AV8:BA8)+BL8 | BN8: =IF($B8=0,BZ7,(BZ7+$D8*BZ$1)*BN$1) | BO8: =IF($B8=0,CA7,(CA7+$D8*CA$1)*BO$1) | BP8: =IF($B8=0,CB7,(CB7+$D8*CB$1)*BP$1) | BQ8: =IF($B8=0,CC7,(CC7+$D8*CC$1)*BQ$1) | BR8: =IF($B8=0,CD7,(CD7+$D8*CD$1)*BR$1) | BS8: =IF($B8=0,CE7,(CE7+$D8*CE$1)*BS$1) | BT8: =IF($B8=0,0,(BZ7+$D8*BZ$1)*BT$1) | BU8: =IF($B8=0,0,(CA7+$D8*CA$1)*BU$1) | BV8: =IF($B8=0,0,(CB7+$D8*CB$1)*BV$1) | BW8: =IF($B8=0,0,(CC7+$D8*CC$1)*BW$1) | BX8: =IF($B8=0,0,(CD7+$D8*CD$1)*BX$1) | BY8: =IF($B8=0,0,(CE7+$D8*CE$1)*BY$1) | BZ8: =IF(CG8=0,BN8,BN8*(1-(CN8-CO8)/CG8)) | CA8: =IF(CG8=0,BO8,BO8*(1-(CN8-CO8)/CG8)) | CB8: =IF(CG8=0,BP8,BP8*(1-(CN8-CO8)/CG8)) | CC8: =IF(CG8=0,BQ8,BQ8*(1-(CN8-CO8)/CG8)) | CD8: =IF(CG8=0,BR8,BR8*(1-(CN8-CO8)/CG8)) | CE8: =IF(CG8=0,BS8,BS8*(1-(CN8-CO8)/CG8)) | CF8: =$D8*(BZ$1+CA$1+CB$1+CC$1+CD$1+CE$1) | CG8: =SUM(BN8:BS8) | CH8: =SUM(BT8:BY8) | CI8: =CG8-SUM(BZ7:CE7)-CF8 | CJ8: =CP7+CH8+CG8 | CK8: =IF(RankNR<RankRR,AB8,0)+IF(RankTF<RankRR,BF8,0) | CL8: =MAX(0,MIN(CJ8,$E8-CK8)) | CM8: =MIN(CL8,CP7+CH8) | CN8: =CL8-CM8 | CO8: =IF(DRIP="Yes",CP7+CH8-CM8,0) | CP8: =IF(DRIP="Yes",0,CP7+CH8-CM8) | CQ8: =SUM(BZ8:CE8)+CP8 | CR8: =IF(S1Type="Eligible",L8,0)+IF(S2Type="Eligible",M8,0)+IF(S3Type="Eligible",N8,0)+IF(S4Type="Eligible",O8,0)+IF(S5Type="Eligible",P8,0)+IF(S6Type="Eligible",Q8,0) | CS8: =IF(S1Type="Non-eligible",L8,0)+IF(S2Type="Non-eligible",M8,0)+IF(S3Type="Non-eligible",N8,0)+IF(S4Type="Non-eligible",O8,0)+IF(S5Type="Non-eligible",P8,0)+IF(S6Type="Non-eligible",Q8,0) | CT8: =IF(S1Type="Foreign / interest",L8,0)+IF(S2Type="Foreign / interest",M8,0)+IF(S3Type="Foreign / interest",N8,0)+IF(S4Type="Foreign / interest",O8,0)+IF(S5Type="Foreign / interest",P8,0)+IF(S6Type="Foreign / interest",Q8,0) | CU8: =CW7+X8 | CV8: =IF(Y8=0,0,AF8*(1-CU8/Y8)) | CW8: =IF(Y8=0,CU8,CU8*(1-AF8/Y8))+AG8 | CX8: =AI8+BM8+CQ8 | CY8: =AD8+BH8+CL8 | CZ8: =AE8+BI8+CM8 | DA8: =AF8+BJ8+CN8 | DB8: =IF(AND($B8=1,$E8-CY8>0.01),1,0)
A9: =A8+1 | B9: =IF($A9<=HorizonM,1,0) | C9: =INT(($A9-1)/12)+1 | D9: =IF($B9=0,0,IF(AND($A9>=CStartEff,$A9<=CEndEff),ContribMonthly*POWER(1+N(ContribEsc),INT(($A9-CStartEff)/12)),0)) | E9: =IF($B9=0,0,IF(AND($A9>=WdStartEff,$A9<=WdEndEff),IF(WdFreq="Annual",IF(MOD($A9-WdStartEff,12)=0,N(WdAmt),0),WdMonthlyBase)*IF(WdIndexed="Yes",POWER(1+N(Inflation),INT(($A9-WdStartEff)/12)),1),0)) | F9: =IF($B9=0,R8,(R8+$D9*R$1)*F$1) | G9: =IF($B9=0,S8,(S8+$D9*S$1)*G$1) | H9: =IF($B9=0,T8,(T8+$D9*T$1)*H$1) | I9: =IF($B9=0,U8,(U8+$D9*U$1)*I$1) | J9: =IF($B9=0,V8,(V8+$D9*V$1)*J$1) | K9: =IF($B9=0,W8,(W8+$D9*W$1)*K$1) | L9: =IF($B9=0,0,(R8+$D9*R$1)*L$1) | M9: =IF($B9=0,0,(S8+$D9*S$1)*M$1) | N9: =IF($B9=0,0,(T8+$D9*T$1)*N$1) | O9: =IF($B9=0,0,(U8+$D9*U$1)*O$1) | P9: =IF($B9=0,0,(V8+$D9*V$1)*P$1) | Q9: =IF($B9=0,0,(W8+$D9*W$1)*Q$1) | R9: =IF(Y9=0,F9,F9*(1-(AF9-AG9)/Y9)) | S9: =IF(Y9=0,G9,G9*(1-(AF9-AG9)/Y9)) | T9: =IF(Y9=0,H9,H9*(1-(AF9-AG9)/Y9)) | U9: =IF(Y9=0,I9,I9*(1-(AF9-AG9)/Y9)) | V9: =IF(Y9=0,J9,J9*(1-(AF9-AG9)/Y9)) | W9: =IF(Y9=0,K9,K9*(1-(AF9-AG9)/Y9)) | X9: =$D9*(R$1+S$1+T$1+U$1+V$1+W$1) | Y9: =SUM(F9:K9) | Z9: =SUM(L9:Q9) | AA9: =Y9-SUM(R8:W8)-X9 | AB9: =AH8+Z9+Y9 | AC9: =IF(RankTF<RankNR,BF9,0)+IF(RankRR<RankNR,CJ9,0) | AD9: =MAX(0,MIN(AB9,$E9-AC9)) | AE9: =MIN(AD9,AH8+Z9) | AF9: =AD9-AE9 | AG9: =IF(DRIP="Yes",AH8+Z9-AE9,0) | AH9: =IF(DRIP="Yes",0,AH8+Z9-AE9) | AI9: =SUM(R9:W9)+AH9 | AJ9: =IF($B9=0,AV8,(AV8+$D9*AV$1)*AJ$1) | AK9: =IF($B9=0,AW8,(AW8+$D9*AW$1)*AK$1) | AL9: =IF($B9=0,AX8,(AX8+$D9*AX$1)*AL$1) | AM9: =IF($B9=0,AY8,(AY8+$D9*AY$1)*AM$1) | AN9: =IF($B9=0,AZ8,(AZ8+$D9*AZ$1)*AN$1) | AO9: =IF($B9=0,BA8,(BA8+$D9*BA$1)*AO$1) | AP9: =IF($B9=0,0,(AV8+$D9*AV$1)*AP$1) | AQ9: =IF($B9=0,0,(AW8+$D9*AW$1)*AQ$1) | AR9: =IF($B9=0,0,(AX8+$D9*AX$1)*AR$1) | AS9: =IF($B9=0,0,(AY8+$D9*AY$1)*AS$1) | AT9: =IF($B9=0,0,(AZ8+$D9*AZ$1)*AT$1) | AU9: =IF($B9=0,0,(BA8+$D9*BA$1)*AU$1) | AV9: =IF(BC9=0,AJ9,AJ9*(1-(BJ9-BK9)/BC9)) | AW9: =IF(BC9=0,AK9,AK9*(1-(BJ9-BK9)/BC9)) | AX9: =IF(BC9=0,AL9,AL9*(1-(BJ9-BK9)/BC9)) | AY9: =IF(BC9=0,AM9,AM9*(1-(BJ9-BK9)/BC9)) | AZ9: =IF(BC9=0,AN9,AN9*(1-(BJ9-BK9)/BC9)) | BA9: =IF(BC9=0,AO9,AO9*(1-(BJ9-BK9)/BC9)) | BB9: =$D9*(AV$1+AW$1+AX$1+AY$1+AZ$1+BA$1) | BC9: =SUM(AJ9:AO9) | BD9: =SUM(AP9:AU9) | BE9: =BC9-SUM(AV8:BA8)-BB9 | BF9: =BL8+BD9+BC9 | BG9: =IF(RankNR<RankTF,AB9,0)+IF(RankRR<RankTF,CJ9,0) | BH9: =MAX(0,MIN(BF9,$E9-BG9)) | BI9: =MIN(BH9,BL8+BD9) | BJ9: =BH9-BI9 | BK9: =IF(DRIP="Yes",BL8+BD9-BI9,0) | BL9: =IF(DRIP="Yes",0,BL8+BD9-BI9) | BM9: =SUM(AV9:BA9)+BL9 | BN9: =IF($B9=0,BZ8,(BZ8+$D9*BZ$1)*BN$1) | BO9: =IF($B9=0,CA8,(CA8+$D9*CA$1)*BO$1) | BP9: =IF($B9=0,CB8,(CB8+$D9*CB$1)*BP$1) | BQ9: =IF($B9=0,CC8,(CC8+$D9*CC$1)*BQ$1) | BR9: =IF($B9=0,CD8,(CD8+$D9*CD$1)*BR$1) | BS9: =IF($B9=0,CE8,(CE8+$D9*CE$1)*BS$1) | BT9: =IF($B9=0,0,(BZ8+$D9*BZ$1)*BT$1) | BU9: =IF($B9=0,0,(CA8+$D9*CA$1)*BU$1) | BV9: =IF($B9=0,0,(CB8+$D9*CB$1)*BV$1) | BW9: =IF($B9=0,0,(CC8+$D9*CC$1)*BW$1) | BX9: =IF($B9=0,0,(CD8+$D9*CD$1)*BX$1) | BY9: =IF($B9=0,0,(CE8+$D9*CE$1)*BY$1) | BZ9: =IF(CG9=0,BN9,BN9*(1-(CN9-CO9)/CG9)) | CA9: =IF(CG9=0,BO9,BO9*(1-(CN9-CO9)/CG9)) | CB9: =IF(CG9=0,BP9,BP9*(1-(CN9-CO9)/CG9)) | CC9: =IF(CG9=0,BQ9,BQ9*(1-(CN9-CO9)/CG9)) | CD9: =IF(CG9=0,BR9,BR9*(1-(CN9-CO9)/CG9)) | CE9: =IF(CG9=0,BS9,BS9*(1-(CN9-CO9)/CG9)) | CF9: =$D9*(BZ$1+CA$1+CB$1+CC$1+CD$1+CE$1) | CG9: =SUM(BN9:BS9) | CH9: =SUM(BT9:BY9) | CI9: =CG9-SUM(BZ8:CE8)-CF9 | CJ9: =CP8+CH9+CG9 | CK9: =IF(RankNR<RankRR,AB9,0)+IF(RankTF<RankRR,BF9,0) | CL9: =MAX(0,MIN(CJ9,$E9-CK9)) | CM9: =MIN(CL9,CP8+CH9) | CN9: =CL9-CM9 | CO9: =IF(DRIP="Yes",CP8+CH9-CM9,0) | CP9: =IF(DRIP="Yes",0,CP8+CH9-CM9) | CQ9: =SUM(BZ9:CE9)+CP9 | CR9: =IF(S1Type="Eligible",L9,0)+IF(S2Type="Eligible",M9,0)+IF(S3Type="Eligible",N9,0)+IF(S4Type="Eligible",O9,0)+IF(S5Type="Eligible",P9,0)+IF(S6Type="Eligible",Q9,0) | CS9: =IF(S1Type="Non-eligible",L9,0)+IF(S2Type="Non-eligible",M9,0)+IF(S3Type="Non-eligible",N9,0)+IF(S4Type="Non-eligible",O9,0)+IF(S5Type="Non-eligible",P9,0)+IF(S6Type="Non-eligible",Q9,0) | CT9: =IF(S1Type="Foreign / interest",L9,0)+IF(S2Type="Foreign / interest",M9,0)+IF(S3Type="Foreign / interest",N9,0)+IF(S4Type="Foreign / interest",O9,0)+IF(S5Type="Foreign / interest",P9,0)+IF(S6Type="Foreign / interest",Q9,0) | CU9: =CW8+X9 | CV9: =IF(Y9=0,0,AF9*(1-CU9/Y9)) | CW9: =IF(Y9=0,CU9,CU9*(1-AF9/Y9))+AG9 | CX9: =AI9+BM9+CQ9 | CY9: =AD9+BH9+CL9 | CZ9: =AE9+BI9+CM9 | DA9: =AF9+BJ9+CN9 | DB9: =IF(AND($B9=1,$E9-CY9>0.01),1,0)
A10: =A9+1 | B10: =IF($A10<=HorizonM,1,0) | C10: =INT(($A10-1)/12)+1 | D10: =IF($B10=0,0,IF(AND($A10>=CStartEff,$A10<=CEndEff),ContribMonthly*POWER(1+N(ContribEsc),INT(($A10-CStartEff)/12)),0)) | E10: =IF($B10=0,0,IF(AND($A10>=WdStartEff,$A10<=WdEndEff),IF(WdFreq="Annual",IF(MOD($A10-WdStartEff,12)=0,N(WdAmt),0),WdMonthlyBase)*IF(WdIndexed="Yes",POWER(1+N(Inflation),INT(($A10-WdStartEff)/12)),1),0)) | F10: =IF($B10=0,R9,(R9+$D10*R$1)*F$1) | G10: =IF($B10=0,S9,(S9+$D10*S$1)*G$1) | H10: =IF($B10=0,T9,(T9+$D10*T$1)*H$1) | I10: =IF($B10=0,U9,(U9+$D10*U$1)*I$1) | J10: =IF($B10=0,V9,(V9+$D10*V$1)*J$1) | K10: =IF($B10=0,W9,(W9+$D10*W$1)*K$1) | L10: =IF($B10=0,0,(R9+$D10*R$1)*L$1) | M10: =IF($B10=0,0,(S9+$D10*S$1)*M$1) | N10: =IF($B10=0,0,(T9+$D10*T$1)*N$1) | O10: =IF($B10=0,0,(U9+$D10*U$1)*O$1) | P10: =IF($B10=0,0,(V9+$D10*V$1)*P$1) | Q10: =IF($B10=0,0,(W9+$D10*W$1)*Q$1) | R10: =IF(Y10=0,F10,F10*(1-(AF10-AG10)/Y10)) | S10: =IF(Y10=0,G10,G10*(1-(AF10-AG10)/Y10)) | T10: =IF(Y10=0,H10,H10*(1-(AF10-AG10)/Y10)) | U10: =IF(Y10=0,I10,I10*(1-(AF10-AG10)/Y10)) | V10: =IF(Y10=0,J10,J10*(1-(AF10-AG10)/Y10)) | W10: =IF(Y10=0,K10,K10*(1-(AF10-AG10)/Y10)) | X10: =$D10*(R$1+S$1+T$1+U$1+V$1+W$1) | Y10: =SUM(F10:K10) | Z10: =SUM(L10:Q10) | AA10: =Y10-SUM(R9:W9)-X10 | AB10: =AH9+Z10+Y10 | AC10: =IF(RankTF<RankNR,BF10,0)+IF(RankRR<RankNR,CJ10,0) | AD10: =MAX(0,MIN(AB10,$E10-AC10)) | AE10: =MIN(AD10,AH9+Z10) | AF10: =AD10-AE10 | AG10: =IF(DRIP="Yes",AH9+Z10-AE10,0) | AH10: =IF(DRIP="Yes",0,AH9+Z10-AE10) | AI10: =SUM(R10:W10)+AH10 | AJ10: =IF($B10=0,AV9,(AV9+$D10*AV$1)*AJ$1) | AK10: =IF($B10=0,AW9,(AW9+$D10*AW$1)*AK$1) | AL10: =IF($B10=0,AX9,(AX9+$D10*AX$1)*AL$1) | AM10: =IF($B10=0,AY9,(AY9+$D10*AY$1)*AM$1) | AN10: =IF($B10=0,AZ9,(AZ9+$D10*AZ$1)*AN$1) | AO10: =IF($B10=0,BA9,(BA9+$D10*BA$1)*AO$1) | AP10: =IF($B10=0,0,(AV9+$D10*AV$1)*AP$1) | AQ10: =IF($B10=0,0,(AW9+$D10*AW$1)*AQ$1) | AR10: =IF($B10=0,0,(AX9+$D10*AX$1)*AR$1) | AS10: =IF($B10=0,0,(AY9+$D10*AY$1)*AS$1) | AT10: =IF($B10=0,0,(AZ9+$D10*AZ$1)*AT$1) | AU10: =IF($B10=0,0,(BA9+$D10*BA$1)*AU$1) | AV10: =IF(BC10=0,AJ10,AJ10*(1-(BJ10-BK10)/BC10)) | AW10: =IF(BC10=0,AK10,AK10*(1-(BJ10-BK10)/BC10)) | AX10: =IF(BC10=0,AL10,AL10*(1-(BJ10-BK10)/BC10)) | AY10: =IF(BC10=0,AM10,AM10*(1-(BJ10-BK10)/BC10)) | AZ10: =IF(BC10=0,AN10,AN10*(1-(BJ10-BK10)/BC10)) | BA10: =IF(BC10=0,AO10,AO10*(1-(BJ10-BK10)/BC10)) | BB10: =$D10*(AV$1+AW$1+AX$1+AY$1+AZ$1+BA$1) | BC10: =SUM(AJ10:AO10) | BD10: =SUM(AP10:AU10) | BE10: =BC10-SUM(AV9:BA9)-BB10 | BF10: =BL9+BD10+BC10 | BG10: =IF(RankNR<RankTF,AB10,0)+IF(RankRR<RankTF,CJ10,0) | BH10: =MAX(0,MIN(BF10,$E10-BG10)) | BI10: =MIN(BH10,BL9+BD10) | BJ10: =BH10-BI10 | BK10: =IF(DRIP="Yes",BL9+BD10-BI10,0) | BL10: =IF(DRIP="Yes",0,BL9+BD10-BI10) | BM10: =SUM(AV10:BA10)+BL10 | BN10: =IF($B10=0,BZ9,(BZ9+$D10*BZ$1)*BN$1) | BO10: =IF($B10=0,CA9,(CA9+$D10*CA$1)*BO$1) | BP10: =IF($B10=0,CB9,(CB9+$D10*CB$1)*BP$1) | BQ10: =IF($B10=0,CC9,(CC9+$D10*CC$1)*BQ$1) | BR10: =IF($B10=0,CD9,(CD9+$D10*CD$1)*BR$1) | BS10: =IF($B10=0,CE9,(CE9+$D10*CE$1)*BS$1) | BT10: =IF($B10=0,0,(BZ9+$D10*BZ$1)*BT$1) | BU10: =IF($B10=0,0,(CA9+$D10*CA$1)*BU$1) | BV10: =IF($B10=0,0,(CB9+$D10*CB$1)*BV$1) | BW10: =IF($B10=0,0,(CC9+$D10*CC$1)*BW$1) | BX10: =IF($B10=0,0,(CD9+$D10*CD$1)*BX$1) | BY10: =IF($B10=0,0,(CE9+$D10*CE$1)*BY$1) | BZ10: =IF(CG10=0,BN10,BN10*(1-(CN10-CO10)/CG10)) | CA10: =IF(CG10=0,BO10,BO10*(1-(CN10-CO10)/CG10)) | CB10: =IF(CG10=0,BP10,BP10*(1-(CN10-CO10)/CG10)) | CC10: =IF(CG10=0,BQ10,BQ10*(1-(CN10-CO10)/CG10)) | CD10: =IF(CG10=0,BR10,BR10*(1-(CN10-CO10)/CG10)) | CE10: =IF(CG10=0,BS10,BS10*(1-(CN10-CO10)/CG10)) | CF10: =$D10*(BZ$1+CA$1+CB$1+CC$1+CD$1+CE$1) | CG10: =SUM(BN10:BS10) | CH10: =SUM(BT10:BY10) | CI10: =CG10-SUM(BZ9:CE9)-CF10 | CJ10: =CP9+CH10+CG10 | CK10: =IF(RankNR<RankRR,AB10,0)+IF(RankTF<RankRR,BF10,0) | CL10: =MAX(0,MIN(CJ10,$E10-CK10)) | CM10: =MIN(CL10,CP9+CH10) | CN10: =CL10-CM10 | CO10: =IF(DRIP="Yes",CP9+CH10-CM10,0) | CP10: =IF(DRIP="Yes",0,CP9+CH10-CM10) | CQ10: =SUM(BZ10:CE10)+CP10 | CR10: =IF(S1Type="Eligible",L10,0)+IF(S2Type="Eligible",M10,0)+IF(S3Type="Eligible",N10,0)+IF(S4Type="Eligible",O10,0)+IF(S5Type="Eligible",P10,0)+IF(S6Type="Eligible",Q10,0) | CS10: =IF(S1Type="Non-eligible",L10,0)+IF(S2Type="Non-eligible",M10,0)+IF(S3Type="Non-eligible",N10,0)+IF(S4Type="Non-eligible",O10,0)+IF(S5Type="Non-eligible",P10,0)+IF(S6Type="Non-eligible",Q10,0) | CT10: =IF(S1Type="Foreign / interest",L10,0)+IF(S2Type="Foreign / interest",M10,0)+IF(S3Type="Foreign / interest",N10,0)+IF(S4Type="Foreign / interest",O10,0)+IF(S5Type="Foreign / interest",P10,0)+IF(S6Type="Foreign / interest",Q10,0) | CU10: =CW9+X10 | CV10: =IF(Y10=0,0,AF10*(1-CU10/Y10)) | CW10: =IF(Y10=0,CU10,CU10*(1-AF10/Y10))+AG10 | CX10: =AI10+BM10+CQ10 | CY10: =AD10+BH10+CL10 | CZ10: =AE10+BI10+CM10 | DA10: =AF10+BJ10+CN10 | DB10: =IF(AND($B10=1,$E10-CY10>0.01),1,0)
A11: =A10+1 | B11: =IF($A11<=HorizonM,1,0) | C11: =INT(($A11-1)/12)+1 | D11: =IF($B11=0,0,IF(AND($A11>=CStartEff,$A11<=CEndEff),ContribMonthly*POWER(1+N(ContribEsc),INT(($A11-CStartEff)/12)),0)) | E11: =IF($B11=0,0,IF(AND($A11>=WdStartEff,$A11<=WdEndEff),IF(WdFreq="Annual",IF(MOD($A11-WdStartEff,12)=0,N(WdAmt),0),WdMonthlyBase)*IF(WdIndexed="Yes",POWER(1+N(Inflation),INT(($A11-WdStartEff)/12)),1),0)) | F11: =IF($B11=0,R10,(R10+$D11*R$1)*F$1) | G11: =IF($B11=0,S10,(S10+$D11*S$1)*G$1) | H11: =IF($B11=0,T10,(T10+$D11*T$1)*H$1) | I11: =IF($B11=0,U10,(U10+$D11*U$1)*I$1) | J11: =IF($B11=0,V10,(V10+$D11*V$1)*J$1) | K11: =IF($B11=0,W10,(W10+$D11*W$1)*K$1) | L11: =IF($B11=0,0,(R10+$D11*R$1)*L$1) | M11: =IF($B11=0,0,(S10+$D11*S$1)*M$1) | N11: =IF($B11=0,0,(T10+$D11*T$1)*N$1) | O11: =IF($B11=0,0,(U10+$D11*U$1)*O$1) | P11: =IF($B11=0,0,(V10+$D11*V$1)*P$1) | Q11: =IF($B11=0,0,(W10+$D11*W$1)*Q$1) | R11: =IF(Y11=0,F11,F11*(1-(AF11-AG11)/Y11)) | S11: =IF(Y11=0,G11,G11*(1-(AF11-AG11)/Y11)) | T11: =IF(Y11=0,H11,H11*(1-(AF11-AG11)/Y11)) | U11: =IF(Y11=0,I11,I11*(1-(AF11-AG11)/Y11)) | V11: =IF(Y11=0,J11,J11*(1-(AF11-AG11)/Y11)) | W11: =IF(Y11=0,K11,K11*(1-(AF11-AG11)/Y11)) | X11: =$D11*(R$1+S$1+T$1+U$1+V$1+W$1) | Y11: =SUM(F11:K11) | Z11: =SUM(L11:Q11) | AA11: =Y11-SUM(R10:W10)-X11 | AB11: =AH10+Z11+Y11 | AC11: =IF(RankTF<RankNR,BF11,0)+IF(RankRR<RankNR,CJ11,0) | AD11: =MAX(0,MIN(AB11,$E11-AC11)) | AE11: =MIN(AD11,AH10+Z11) | AF11: =AD11-AE11 | AG11: =IF(DRIP="Yes",AH10+Z11-AE11,0) | AH11: =IF(DRIP="Yes",0,AH10+Z11-AE11) | AI11: =SUM(R11:W11)+AH11 | AJ11: =IF($B11=0,AV10,(AV10+$D11*AV$1)*AJ$1) | AK11: =IF($B11=0,AW10,(AW10+$D11*AW$1)*AK$1) | AL11: =IF($B11=0,AX10,(AX10+$D11*AX$1)*AL$1) | AM11: =IF($B11=0,AY10,(AY10+$D11*AY$1)*AM$1) | AN11: =IF($B11=0,AZ10,(AZ10+$D11*AZ$1)*AN$1) | AO11: =IF($B11=0,BA10,(BA10+$D11*BA$1)*AO$1) | AP11: =IF($B11=0,0,(AV10+$D11*AV$1)*AP$1) | AQ11: =IF($B11=0,0,(AW10+$D11*AW$1)*AQ$1) | AR11: =IF($B11=0,0,(AX10+$D11*AX$1)*AR$1) | AS11: =IF($B11=0,0,(AY10+$D11*AY$1)*AS$1) | AT11: =IF($B11=0,0,(AZ10+$D11*AZ$1)*AT$1) | AU11: =IF($B11=0,0,(BA10+$D11*BA$1)*AU$1) | AV11: =IF(BC11=0,AJ11,AJ11*(1-(BJ11-BK11)/BC11)) | AW11: =IF(BC11=0,AK11,AK11*(1-(BJ11-BK11)/BC11)) | AX11: =IF(BC11=0,AL11,AL11*(1-(BJ11-BK11)/BC11)) | AY11: =IF(BC11=0,AM11,AM11*(1-(BJ11-BK11)/BC11)) | AZ11: =IF(BC11=0,AN11,AN11*(1-(BJ11-BK11)/BC11)) | BA11: =IF(BC11=0,AO11,AO11*(1-(BJ11-BK11)/BC11)) | BB11: =$D11*(AV$1+AW$1+AX$1+AY$1+AZ$1+BA$1) | BC11: =SUM(AJ11:AO11) | BD11: =SUM(AP11:AU11) | BE11: =BC11-SUM(AV10:BA10)-BB11 | BF11: =BL10+BD11+BC11 | BG11: =IF(RankNR<RankTF,AB11,0)+IF(RankRR<RankTF,CJ11,0) | BH11: =MAX(0,MIN(BF11,$E11-BG11)) | BI11: =MIN(BH11,BL10+BD11) | BJ11: =BH11-BI11 | BK11: =IF(DRIP="Yes",BL10+BD11-BI11,0) | BL11: =IF(DRIP="Yes",0,BL10+BD11-BI11) | BM11: =SUM(AV11:BA11)+BL11 | BN11: =IF($B11=0,BZ10,(BZ10+$D11*BZ$1)*BN$1) | BO11: =IF($B11=0,CA10,(CA10+$D11*CA$1)*BO$1) | BP11: =IF($B11=0,CB10,(CB10+$D11*CB$1)*BP$1) | BQ11: =IF($B11=0,CC10,(CC10+$D11*CC$1)*BQ$1) | BR11: =IF($B11=0,CD10,(CD10+$D11*CD$1)*BR$1) | BS11: =IF($B11=0,CE10,(CE10+$D11*CE$1)*BS$1) | BT11: =IF($B11=0,0,(BZ10+$D11*BZ$1)*BT$1) | BU11: =IF($B11=0,0,(CA10+$D11*CA$1)*BU$1) | BV11: =IF($B11=0,0,(CB10+$D11*CB$1)*BV$1) | BW11: =IF($B11=0,0,(CC10+$D11*CC$1)*BW$1) | BX11: =IF($B11=0,0,(CD10+$D11*CD$1)*BX$1) | BY11: =IF($B11=0,0,(CE10+$D11*CE$1)*BY$1) | BZ11: =IF(CG11=0,BN11,BN11*(1-(CN11-CO11)/CG11)) | CA11: =IF(CG11=0,BO11,BO11*(1-(CN11-CO11)/CG11)) | CB11: =IF(CG11=0,BP11,BP11*(1-(CN11-CO11)/CG11)) | CC11: =IF(CG11=0,BQ11,BQ11*(1-(CN11-CO11)/CG11)) | CD11: =IF(CG11=0,BR11,BR11*(1-(CN11-CO11)/CG11)) | CE11: =IF(CG11=0,BS11,BS11*(1-(CN11-CO11)/CG11)) | CF11: =$D11*(BZ$1+CA$1+CB$1+CC$1+CD$1+CE$1) | CG11: =SUM(BN11:BS11) | CH11: =SUM(BT11:BY11) | CI11: =CG11-SUM(BZ10:CE10)-CF11 | CJ11: =CP10+CH11+CG11 | CK11: =IF(RankNR<RankRR,AB11,0)+IF(RankTF<RankRR,BF11,0) | CL11: =MAX(0,MIN(CJ11,$E11-CK11)) | CM11: =MIN(CL11,CP10+CH11) | CN11: =CL11-CM11 | CO11: =IF(DRIP="Yes",CP10+CH11-CM11,0) | CP11: =IF(DRIP="Yes",0,CP10+CH11-CM11) | CQ11: =SUM(BZ11:CE11)+CP11 | CR11: =IF(S1Type="Eligible",L11,0)+IF(S2Type="Eligible",M11,0)+IF(S3Type="Eligible",N11,0)+IF(S4Type="Eligible",O11,0)+IF(S5Type="Eligible",P11,0)+IF(S6Type="Eligible",Q11,0) | CS11: =IF(S1Type="Non-eligible",L11,0)+IF(S2Type="Non-eligible",M11,0)+IF(S3Type="Non-eligible",N11,0)+IF(S4Type="Non-eligible",O11,0)+IF(S5Type="Non-eligible",P11,0)+IF(S6Type="Non-eligible",Q11,0) | CT11: =IF(S1Type="Foreign / interest",L11,0)+IF(S2Type="Foreign / interest",M11,0)+IF(S3Type="Foreign / interest",N11,0)+IF(S4Type="Foreign / interest",O11,0)+IF(S5Type="Foreign / interest",P11,0)+IF(S6Type="Foreign / interest",Q11,0) | CU11: =CW10+X11 | CV11: =IF(Y11=0,0,AF11*(1-CU11/Y11)) | CW11: =IF(Y11=0,CU11,CU11*(1-AF11/Y11))+AG11 | CX11: =AI11+BM11+CQ11 | CY11: =AD11+BH11+CL11 | CZ11: =AE11+BI11+CM11 | DA11: =AF11+BJ11+CN11 | DB11: =IF(AND($B11=1,$E11-CY11>0.01),1,0)
A12: =A11+1 | B12: =IF($A12<=HorizonM,1,0) | C12: =INT(($A12-1)/12)+1 | D12: =IF($B12=0,0,IF(AND($A12>=CStartEff,$A12<=CEndEff),ContribMonthly*POWER(1+N(ContribEsc),INT(($A12-CStartEff)/12)),0)) | E12: =IF($B12=0,0,IF(AND($A12>=WdStartEff,$A12<=WdEndEff),IF(WdFreq="Annual",IF(MOD($A12-WdStartEff,12)=0,N(WdAmt),0),WdMonthlyBase)*IF(WdIndexed="Yes",POWER(1+N(Inflation),INT(($A12-WdStartEff)/12)),1),0)) | F12: =IF($B12=0,R11,(R11+$D12*R$1)*F$1) | G12: =IF($B12=0,S11,(S11+$D12*S$1)*G$1) | H12: =IF($B12=0,T11,(T11+$D12*T$1)*H$1) | I12: =IF($B12=0,U11,(U11+$D12*U$1)*I$1) | J12: =IF($B12=0,V11,(V11+$D12*V$1)*J$1) | K12: =IF($B12=0,W11,(W11+$D12*W$1)*K$1) | L12: =IF($B12=0,0,(R11+$D12*R$1)*L$1) | M12: =IF($B12=0,0,(S11+$D12*S$1)*M$1) | N12: =IF($B12=0,0,(T11+$D12*T$1)*N$1) | O12: =IF($B12=0,0,(U11+$D12*U$1)*O$1) | P12: =IF($B12=0,0,(V11+$D12*V$1)*P$1) | Q12: =IF($B12=0,0,(W11+$D12*W$1)*Q$1) | R12: =IF(Y12=0,F12,F12*(1-(AF12-AG12)/Y12)) | S12: =IF(Y12=0,G12,G12*(1-(AF12-AG12)/Y12)) | T12: =IF(Y12=0,H12,H12*(1-(AF12-AG12)/Y12)) | U12: =IF(Y12=0,I12,I12*(1-(AF12-AG12)/Y12)) | V12: =IF(Y12=0,J12,J12*(1-(AF12-AG12)/Y12)) | W12: =IF(Y12=0,K12,K12*(1-(AF12-AG12)/Y12)) | X12: =$D12*(R$1+S$1+T$1+U$1+V$1+W$1) | Y12: =SUM(F12:K12) | Z12: =SUM(L12:Q12) | AA12: =Y12-SUM(R11:W11)-X12 | AB12: =AH11+Z12+Y12 | AC12: =IF(RankTF<RankNR,BF12,0)+IF(RankRR<RankNR,CJ12,0) | AD12: =MAX(0,MIN(AB12,$E12-AC12)) | AE12: =MIN(AD12,AH11+Z12) | AF12: =AD12-AE12 | AG12: =IF(DRIP="Yes",AH11+Z12-AE12,0) | AH12: =IF(DRIP="Yes",0,AH11+Z12-AE12) | AI12: =SUM(R12:W12)+AH12 | AJ12: =IF($B12=0,AV11,(AV11+$D12*AV$1)*AJ$1) | AK12: =IF($B12=0,AW11,(AW11+$D12*AW$1)*AK$1) | AL12: =IF($B12=0,AX11,(AX11+$D12*AX$1)*AL$1) | AM12: =IF($B12=0,AY11,(AY11+$D12*AY$1)*AM$1) | AN12: =IF($B12=0,AZ11,(AZ11+$D12*AZ$1)*AN$1) | AO12: =IF($B12=0,BA11,(BA11+$D12*BA$1)*AO$1) | AP12: =IF($B12=0,0,(AV11+$D12*AV$1)*AP$1) | AQ12: =IF($B12=0,0,(AW11+$D12*AW$1)*AQ$1) | AR12: =IF($B12=0,0,(AX11+$D12*AX$1)*AR$1) | AS12: =IF($B12=0,0,(AY11+$D12*AY$1)*AS$1) | AT12: =IF($B12=0,0,(AZ11+$D12*AZ$1)*AT$1) | AU12: =IF($B12=0,0,(BA11+$D12*BA$1)*AU$1) | AV12: =IF(BC12=0,AJ12,AJ12*(1-(BJ12-BK12)/BC12)) | AW12: =IF(BC12=0,AK12,AK12*(1-(BJ12-BK12)/BC12)) | AX12: =IF(BC12=0,AL12,AL12*(1-(BJ12-BK12)/BC12)) | AY12: =IF(BC12=0,AM12,AM12*(1-(BJ12-BK12)/BC12)) | AZ12: =IF(BC12=0,AN12,AN12*(1-(BJ12-BK12)/BC12)) | BA12: =IF(BC12=0,AO12,AO12*(1-(BJ12-BK12)/BC12)) | BB12: =$D12*(AV$1+AW$1+AX$1+AY$1+AZ$1+BA$1) | BC12: =SUM(AJ12:AO12) | BD12: =SUM(AP12:AU12) | BE12: =BC12-SUM(AV11:BA11)-BB12 | BF12: =BL11+BD12+BC12 | BG12: =IF(RankNR<RankTF,AB12,0)+IF(RankRR<RankTF,CJ12,0) | BH12: =MAX(0,MIN(BF12,$E12-BG12)) | BI12: =MIN(BH12,BL11+BD12) | BJ12: =BH12-BI12 | BK12: =IF(DRIP="Yes",BL11+BD12-BI12,0) | BL12: =IF(DRIP="Yes",0,BL11+BD12-BI12) | BM12: =SUM(AV12:BA12)+BL12 | BN12: =IF($B12=0,BZ11,(BZ11+$D12*BZ$1)*BN$1) | BO12: =IF($B12=0,CA11,(CA11+$D12*CA$1)*BO$1) | BP12: =IF($B12=0,CB11,(CB11+$D12*CB$1)*BP$1) | BQ12: =IF($B12=0,CC11,(CC11+$D12*CC$1)*BQ$1) | BR12: =IF($B12=0,CD11,(CD11+$D12*CD$1)*BR$1) | BS12: =IF($B12=0,CE11,(CE11+$D12*CE$1)*BS$1) | BT12: =IF($B12=0,0,(BZ11+$D12*BZ$1)*BT$1) | BU12: =IF($B12=0,0,(CA11+$D12*CA$1)*BU$1) | BV12: =IF($B12=0,0,(CB11+$D12*CB$1)*BV$1) | BW12: =IF($B12=0,0,(CC11+$D12*CC$1)*BW$1) | BX12: =IF($B12=0,0,(CD11+$D12*CD$1)*BX$1) | BY12: =IF($B12=0,0,(CE11+$D12*CE$1)*BY$1) | BZ12: =IF(CG12=0,BN12,BN12*(1-(CN12-CO12)/CG12)) | CA12: =IF(CG12=0,BO12,BO12*(1-(CN12-CO12)/CG12)) | CB12: =IF(CG12=0,BP12,BP12*(1-(CN12-CO12)/CG12)) | CC12: =IF(CG12=0,BQ12,BQ12*(1-(CN12-CO12)/CG12)) | CD12: =IF(CG12=0,BR12,BR12*(1-(CN12-CO12)/CG12)) | CE12: =IF(CG12=0,BS12,BS12*(1-(CN12-CO12)/CG12)) | CF12: =$D12*(BZ$1+CA$1+CB$1+CC$1+CD$1+CE$1) | CG12: =SUM(BN12:BS12) | CH12: =SUM(BT12:BY12) | CI12: =CG12-SUM(BZ11:CE11)-CF12 | CJ12: =CP11+CH12+CG12 | CK12: =IF(RankNR<RankRR,AB12,0)+IF(RankTF<RankRR,BF12,0) | CL12: =MAX(0,MIN(CJ12,$E12-CK12)) | CM12: =MIN(CL12,CP11+CH12) | CN12: =CL12-CM12 | CO12: =IF(DRIP="Yes",CP11+CH12-CM12,0) | CP12: =IF(DRIP="Yes",0,CP11+CH12-CM12) | CQ12: =SUM(BZ12:CE12)+CP12 | CR12: =IF(S1Type="Eligible",L12,0)+IF(S2Type="Eligible",M12,0)+IF(S3Type="Eligible",N12,0)+IF(S4Type="Eligible",O12,0)+IF(S5Type="Eligible",P12,0)+IF(S6Type="Eligible",Q12,0) | CS12: =IF(S1Type="Non-eligible",L12,0)+IF(S2Type="Non-eligible",M12,0)+IF(S3Type="Non-eligible",N12,0)+IF(S4Type="Non-eligible",O12,0)+IF(S5Type="Non-eligible",P12,0)+IF(S6Type="Non-eligible",Q12,0) | CT12: =IF(S1Type="Foreign / interest",L12,0)+IF(S2Type="Foreign / interest",M12,0)+IF(S3Type="Foreign / interest",N12,0)+IF(S4Type="Foreign / interest",O12,0)+IF(S5Type="Foreign / interest",P12,0)+IF(S6Type="Foreign / interest",Q12,0) | CU12: =CW11+X12 | CV12: =IF(Y12=0,0,AF12*(1-CU12/Y12)) | CW12: =IF(Y12=0,CU12,CU12*(1-AF12/Y12))+AG12 | CX12: =AI12+BM12+CQ12 | CY12: =AD12+BH12+CL12 | CZ12: =AE12+BI12+CM12 | DA12: =AF12+BJ12+CN12 | DB12: =IF(AND($B12=1,$E12-CY12>0.01),1,0)
A13: =A12+1 | B13: =IF($A13<=HorizonM,1,0) | C13: =INT(($A13-1)/12)+1 | D13: =IF($B13=0,0,IF(AND($A13>=CStartEff,$A13<=CEndEff),ContribMonthly*POWER(1+N(ContribEsc),INT(($A13-CStartEff)/12)),0)) | E13: =IF($B13=0,0,IF(AND($A13>=WdStartEff,$A13<=WdEndEff),IF(WdFreq="Annual",IF(MOD($A13-WdStartEff,12)=0,N(WdAmt),0),WdMonthlyBase)*IF(WdIndexed="Yes",POWER(1+N(Inflation),INT(($A13-WdStartEff)/12)),1),0)) | F13: =IF($B13=0,R12,(R12+$D13*R$1)*F$1) | G13: =IF($B13=0,S12,(S12+$D13*S$1)*G$1) | H13: =IF($B13=0,T12,(T12+$D13*T$1)*H$1) | I13: =IF($B13=0,U12,(U12+$D13*U$1)*I$1) | J13: =IF($B13=0,V12,(V12+$D13*V$1)*J$1) | K13: =IF($B13=0,W12,(W12+$D13*W$1)*K$1) | L13: =IF($B13=0,0,(R12+$D13*R$1)*L$1) | M13: =IF($B13=0,0,(S12+$D13*S$1)*M$1) | N13: =IF($B13=0,0,(T12+$D13*T$1)*N$1) | O13: =IF($B13=0,0,(U12+$D13*U$1)*O$1) | P13: =IF($B13=0,0,(V12+$D13*V$1)*P$1) | Q13: =IF($B13=0,0,(W12+$D13*W$1)*Q$1) | R13: =IF(Y13=0,F13,F13*(1-(AF13-AG13)/Y13)) | S13: =IF(Y13=0,G13,G13*(1-(AF13-AG13)/Y13)) | T13: =IF(Y13=0,H13,H13*(1-(AF13-AG13)/Y13)) | U13: =IF(Y13=0,I13,I13*(1-(AF13-AG13)/Y13)) | V13: =IF(Y13=0,J13,J13*(1-(AF13-AG13)/Y13)) | W13: =IF(Y13=0,K13,K13*(1-(AF13-AG13)/Y13)) | X13: =$D13*(R$1+S$1+T$1+U$1+V$1+W$1) | Y13: =SUM(F13:K13) | Z13: =SUM(L13:Q13) | AA13: =Y13-SUM(R12:W12)-X13 | AB13: =AH12+Z13+Y13 | AC13: =IF(RankTF<RankNR,BF13,0)+IF(RankRR<RankNR,CJ13,0) | AD13: =MAX(0,MIN(AB13,$E13-AC13)) | AE13: =MIN(AD13,AH12+Z13) | AF13: =AD13-AE13 | AG13: =IF(DRIP="Yes",AH12+Z13-AE13,0) | AH13: =IF(DRIP="Yes",0,AH12+Z13-AE13) | AI13: =SUM(R13:W13)+AH13 | AJ13: =IF($B13=0,AV12,(AV12+$D13*AV$1)*AJ$1) | AK13: =IF($B13=0,AW12,(AW12+$D13*AW$1)*AK$1) | AL13: =IF($B13=0,AX12,(AX12+$D13*AX$1)*AL$1) | AM13: =IF($B13=0,AY12,(AY12+$D13*AY$1)*AM$1) | AN13: =IF($B13=0,AZ12,(AZ12+$D13*AZ$1)*AN$1) | AO13: =IF($B13=0,BA12,(BA12+$D13*BA$1)*AO$1) | AP13: =IF($B13=0,0,(AV12+$D13*AV$1)*AP$1) | AQ13: =IF($B13=0,0,(AW12+$D13*AW$1)*AQ$1) | AR13: =IF($B13=0,0,(AX12+$D13*AX$1)*AR$1) | AS13: =IF($B13=0,0,(AY12+$D13*AY$1)*AS$1) | AT13: =IF($B13=0,0,(AZ12+$D13*AZ$1)*AT$1) | AU13: =IF($B13=0,0,(BA12+$D13*BA$1)*AU$1) | AV13: =IF(BC13=0,AJ13,AJ13*(1-(BJ13-BK13)/BC13)) | AW13: =IF(BC13=0,AK13,AK13*(1-(BJ13-BK13)/BC13)) | AX13: =IF(BC13=0,AL13,AL13*(1-(BJ13-BK13)/BC13)) | AY13: =IF(BC13=0,AM13,AM13*(1-(BJ13-BK13)/BC13)) | AZ13: =IF(BC13=0,AN13,AN13*(1-(BJ13-BK13)/BC13)) | BA13: =IF(BC13=0,AO13,AO13*(1-(BJ13-BK13)/BC13)) | BB13: =$D13*(AV$1+AW$1+AX$1+AY$1+AZ$1+BA$1) | BC13: =SUM(AJ13:AO13) | BD13: =SUM(AP13:AU13) | BE13: =BC13-SUM(AV12:BA12)-BB13 | BF13: =BL12+BD13+BC13 | BG13: =IF(RankNR<RankTF,AB13,0)+IF(RankRR<RankTF,CJ13,0) | BH13: =MAX(0,MIN(BF13,$E13-BG13)) | BI13: =MIN(BH13,BL12+BD13) | BJ13: =BH13-BI13 | BK13: =IF(DRIP="Yes",BL12+BD13-BI13,0) | BL13: =IF(DRIP="Yes",0,BL12+BD13-BI13) | BM13: =SUM(AV13:BA13)+BL13 | BN13: =IF($B13=0,BZ12,(BZ12+$D13*BZ$1)*BN$1) | BO13: =IF($B13=0,CA12,(CA12+$D13*CA$1)*BO$1) | BP13: =IF($B13=0,CB12,(CB12+$D13*CB$1)*BP$1) | BQ13: =IF($B13=0,CC12,(CC12+$D13*CC$1)*BQ$1) | BR13: =IF($B13=0,CD12,(CD12+$D13*CD$1)*BR$1) | BS13: =IF($B13=0,CE12,(CE12+$D13*CE$1)*BS$1) | BT13: =IF($B13=0,0,(BZ12+$D13*BZ$1)*BT$1) | BU13: =IF($B13=0,0,(CA12+$D13*CA$1)*BU$1) | BV13: =IF($B13=0,0,(CB12+$D13*CB$1)*BV$1) | BW13: =IF($B13=0,0,(CC12+$D13*CC$1)*BW$1) | BX13: =IF($B13=0,0,(CD12+$D13*CD$1)*BX$1) | BY13: =IF($B13=0,0,(CE12+$D13*CE$1)*BY$1) | BZ13: =IF(CG13=0,BN13,BN13*(1-(CN13-CO13)/CG13)) | CA13: =IF(CG13=0,BO13,BO13*(1-(CN13-CO13)/CG13)) | CB13: =IF(CG13=0,BP13,BP13*(1-(CN13-CO13)/CG13)) | CC13: =IF(CG13=0,BQ13,BQ13*(1-(CN13-CO13)/CG13)) | CD13: =IF(CG13=0,BR13,BR13*(1-(CN13-CO13)/CG13)) | CE13: =IF(CG13=0,BS13,BS13*(1-(CN13-CO13)/CG13)) | CF13: =$D13*(BZ$1+CA$1+CB$1+CC$1+CD$1+CE$1) | CG13: =SUM(BN13:BS13) | CH13: =SUM(BT13:BY13) | CI13: =CG13-SUM(BZ12:CE12)-CF13 | CJ13: =CP12+CH13+CG13 | CK13: =IF(RankNR<RankRR,AB13,0)+IF(RankTF<RankRR,BF13,0) | CL13: =MAX(0,MIN(CJ13,$E13-CK13)) | CM13: =MIN(CL13,CP12+CH13) | CN13: =CL13-CM13 | CO13: =IF(DRIP="Yes",CP12+CH13-CM13,0) | CP13: =IF(DRIP="Yes",0,CP12+CH13-CM13) | CQ13: =SUM(BZ13:CE13)+CP13 | CR13: =IF(S1Type="Eligible",L13,0)+IF(S2Type="Eligible",M13,0)+IF(S3Type="Eligible",N13,0)+IF(S4Type="Eligible",O13,0)+IF(S5Type="Eligible",P13,0)+IF(S6Type="Eligible",Q13,0) | CS13: =IF(S1Type="Non-eligible",L13,0)+IF(S2Type="Non-eligible",M13,0)+IF(S3Type="Non-eligible",N13,0)+IF(S4Type="Non-eligible",O13,0)+IF(S5Type="Non-eligible",P13,0)+IF(S6Type="Non-eligible",Q13,0) | CT13: =IF(S1Type="Foreign / interest",L13,0)+IF(S2Type="Foreign / interest",M13,0)+IF(S3Type="Foreign / interest",N13,0)+IF(S4Type="Foreign / interest",O13,0)+IF(S5Type="Foreign / interest",P13,0)+IF(S6Type="Foreign / interest",Q13,0) | CU13: =CW12+X13 | CV13: =IF(Y13=0,0,AF13*(1-CU13/Y13)) | CW13: =IF(Y13=0,CU13,CU13*(1-AF13/Y13))+AG13 | CX13: =AI13+BM13+CQ13 | CY13: =AD13+BH13+CL13 | CZ13: =AE13+BI13+CM13 | DA13: =AF13+BJ13+CN13 | DB13: =IF(AND($B13=1,$E13-CY13>0.01),1,0)
A14: =A13+1 | B14: =IF($A14<=HorizonM,1,0) | C14: =INT(($A14-1)/12)+1 | D14: =IF($B14=0,0,IF(AND($A14>=CStartEff,$A14<=CEndEff),ContribMonthly*POWER(1+N(ContribEsc),INT(($A14-CStartEff)/12)),0)) | E14: =IF($B14=0,0,IF(AND($A14>=WdStartEff,$A14<=WdEndEff),IF(WdFreq="Annual",IF(MOD($A14-WdStartEff,12)=0,N(WdAmt),0),WdMonthlyBase)*IF(WdIndexed="Yes",POWER(1+N(Inflation),INT(($A14-WdStartEff)/12)),1),0)) | F14: =IF($B14=0,R13,(R13+$D14*R$1)*F$1) | G14: =IF($B14=0,S13,(S13+$D14*S$1)*G$1) | H14: =IF($B14=0,T13,(T13+$D14*T$1)*H$1) | I14: =IF($B14=0,U13,(U13+$D14*U$1)*I$1) | J14: =IF($B14=0,V13,(V13+$D14*V$1)*J$1) | K14: =IF($B14=0,W13,(W13+$D14*W$1)*K$1) | L14: =IF($B14=0,0,(R13+$D14*R$1)*L$1) | M14: =IF($B14=0,0,(S13+$D14*S$1)*M$1) | N14: =IF($B14=0,0,(T13+$D14*T$1)*N$1) | O14: =IF($B14=0,0,(U13+$D14*U$1)*O$1) | P14: =IF($B14=0,0,(V13+$D14*V$1)*P$1) | Q14: =IF($B14=0,0,(W13+$D14*W$1)*Q$1) | R14: =IF(Y14=0,F14,F14*(1-(AF14-AG14)/Y14)) | S14: =IF(Y14=0,G14,G14*(1-(AF14-AG14)/Y14)) | T14: =IF(Y14=0,H14,H14*(1-(AF14-AG14)/Y14)) | U14: =IF(Y14=0,I14,I14*(1-(AF14-AG14)/Y14)) | V14: =IF(Y14=0,J14,J14*(1-(AF14-AG14)/Y14)) | W14: =IF(Y14=0,K14,K14*(1-(AF14-AG14)/Y14)) | X14: =$D14*(R$1+S$1+T$1+U$1+V$1+W$1) | Y14: =SUM(F14:K14) | Z14: =SUM(L14:Q14) | AA14: =Y14-SUM(R13:W13)-X14 | AB14: =AH13+Z14+Y14 | AC14: =IF(RankTF<RankNR,BF14,0)+IF(RankRR<RankNR,CJ14,0) | AD14: =MAX(0,MIN(AB14,$E14-AC14)) | AE14: =MIN(AD14,AH13+Z14) | AF14: =AD14-AE14 | AG14: =IF(DRIP="Yes",AH13+Z14-AE14,0) | AH14: =IF(DRIP="Yes",0,AH13+Z14-AE14) | AI14: =SUM(R14:W14)+AH14 | AJ14: =IF($B14=0,AV13,(AV13+$D14*AV$1)*AJ$1) | AK14: =IF($B14=0,AW13,(AW13+$D14*AW$1)*AK$1) | AL14: =IF($B14=0,AX13,(AX13+$D14*AX$1)*AL$1) | AM14: =IF($B14=0,AY13,(AY13+$D14*AY$1)*AM$1) | AN14: =IF($B14=0,AZ13,(AZ13+$D14*AZ$1)*AN$1) | AO14: =IF($B14=0,BA13,(BA13+$D14*BA$1)*AO$1) | AP14: =IF($B14=0,0,(AV13+$D14*AV$1)*AP$1) | AQ14: =IF($B14=0,0,(AW13+$D14*AW$1)*AQ$1) | AR14: =IF($B14=0,0,(AX13+$D14*AX$1)*AR$1) | AS14: =IF($B14=0,0,(AY13+$D14*AY$1)*AS$1) | AT14: =IF($B14=0,0,(AZ13+$D14*AZ$1)*AT$1) | AU14: =IF($B14=0,0,(BA13+$D14*BA$1)*AU$1) | AV14: =IF(BC14=0,AJ14,AJ14*(1-(BJ14-BK14)/BC14)) | AW14: =IF(BC14=0,AK14,AK14*(1-(BJ14-BK14)/BC14)) | AX14: =IF(BC14=0,AL14,AL14*(1-(BJ14-BK14)/BC14)) | AY14: =IF(BC14=0,AM14,AM14*(1-(BJ14-BK14)/BC14)) | AZ14: =IF(BC14=0,AN14,AN14*(1-(BJ14-BK14)/BC14)) | BA14: =IF(BC14=0,AO14,AO14*(1-(BJ14-BK14)/BC14)) | BB14: =$D14*(AV$1+AW$1+AX$1+AY$1+AZ$1+BA$1) | BC14: =SUM(AJ14:AO14) | BD14: =SUM(AP14:AU14) | BE14: =BC14-SUM(AV13:BA13)-BB14 | BF14: =BL13+BD14+BC14 | BG14: =IF(RankNR<RankTF,AB14,0)+IF(RankRR<RankTF,CJ14,0) | BH14: =MAX(0,MIN(BF14,$E14-BG14)) | BI14: =MIN(BH14,BL13+BD14) | BJ14: =BH14-BI14 | BK14: =IF(DRIP="Yes",BL13+BD14-BI14,0) | BL14: =IF(DRIP="Yes",0,BL13+BD14-BI14) | BM14: =SUM(AV14:BA14)+BL14 | BN14: =IF($B14=0,BZ13,(BZ13+$D14*BZ$1)*BN$1) | BO14: =IF($B14=0,CA13,(CA13+$D14*CA$1)*BO$1) | BP14: =IF($B14=0,CB13,(CB13+$D14*CB$1)*BP$1) | BQ14: =IF($B14=0,CC13,(CC13+$D14*CC$1)*BQ$1) | BR14: =IF($B14=0,CD13,(CD13+$D14*CD$1)*BR$1) | BS14: =IF($B14=0,CE13,(CE13+$D14*CE$1)*BS$1) | BT14: =IF($B14=0,0,(BZ13+$D14*BZ$1)*BT$1) | BU14: =IF($B14=0,0,(CA13+$D14*CA$1)*BU$1) | BV14: =IF($B14=0,0,(CB13+$D14*CB$1)*BV$1) | BW14: =IF($B14=0,0,(CC13+$D14*CC$1)*BW$1) | BX14: =IF($B14=0,0,(CD13+$D14*CD$1)*BX$1) | BY14: =IF($B14=0,0,(CE13+$D14*CE$1)*BY$1) | BZ14: =IF(CG14=0,BN14,BN14*(1-(CN14-CO14)/CG14)) | CA14: =IF(CG14=0,BO14,BO14*(1-(CN14-CO14)/CG14)) | CB14: =IF(CG14=0,BP14,BP14*(1-(CN14-CO14)/CG14)) | CC14: =IF(CG14=0,BQ14,BQ14*(1-(CN14-CO14)/CG14)) | CD14: =IF(CG14=0,BR14,BR14*(1-(CN14-CO14)/CG14)) | CE14: =IF(CG14=0,BS14,BS14*(1-(CN14-CO14)/CG14)) | CF14: =$D14*(BZ$1+CA$1+CB$1+CC$1+CD$1+CE$1) | CG14: =SUM(BN14:BS14) | CH14: =SUM(BT14:BY14) | CI14: =CG14-SUM(BZ13:CE13)-CF14 | CJ14: =CP13+CH14+CG14 | CK14: =IF(RankNR<RankRR,AB14,0)+IF(RankTF<RankRR,BF14,0) | CL14: =MAX(0,MIN(CJ14,$E14-CK14)) | CM14: =MIN(CL14,CP13+CH14) | CN14: =CL14-CM14 | CO14: =IF(DRIP="Yes",CP13+CH14-CM14,0) | CP14: =IF(DRIP="Yes",0,CP13+CH14-CM14) | CQ14: =SUM(BZ14:CE14)+CP14 | CR14: =IF(S1Type="Eligible",L14,0)+IF(S2Type="Eligible",M14,0)+IF(S3Type="Eligible",N14,0)+IF(S4Type="Eligible",O14,0)+IF(S5Type="Eligible",P14,0)+IF(S6Type="Eligible",Q14,0) | CS14: =IF(S1Type="Non-eligible",L14,0)+IF(S2Type="Non-eligible",M14,0)+IF(S3Type="Non-eligible",N14,0)+IF(S4Type="Non-eligible",O14,0)+IF(S5Type="Non-eligible",P14,0)+IF(S6Type="Non-eligible",Q14,0) | CT14: =IF(S1Type="Foreign / interest",L14,0)+IF(S2Type="Foreign / interest",M14,0)+IF(S3Type="Foreign / interest",N14,0)+IF(S4Type="Foreign / interest",O14,0)+IF(S5Type="Foreign / interest",P14,0)+IF(S6Type="Foreign / interest",Q14,0) | CU14: =CW13+X14 | CV14: =IF(Y14=0,0,AF14*(1-CU14/Y14)) | CW14: =IF(Y14=0,CU14,CU14*(1-AF14/Y14))+AG14 | CX14: =AI14+BM14+CQ14 | CY14: =AD14+BH14+CL14 | CZ14: =AE14+BI14+CM14 | DA14: =AF14+BJ14+CN14 | DB14: =IF(AND($B14=1,$E14-CY14>0.01),1,0)
A15: =A14+1 | B15: =IF($A15<=HorizonM,1,0) | C15: =INT(($A15-1)/12)+1 | D15: =IF($B15=0,0,IF(AND($A15>=CStartEff,$A15<=CEndEff),ContribMonthly*POWER(1+N(ContribEsc),INT(($A15-CStartEff)/12)),0)) | E15: =IF($B15=0,0,IF(AND($A15>=WdStartEff,$A15<=WdEndEff),IF(WdFreq="Annual",IF(MOD($A15-WdStartEff,12)=0,N(WdAmt),0),WdMonthlyBase)*IF(WdIndexed="Yes",POWER(1+N(Inflation),INT(($A15-WdStartEff)/12)),1),0)) | F15: =IF($B15=0,R14,(R14+$D15*R$1)*F$1) | G15: =IF($B15=0,S14,(S14+$D15*S$1)*G$1) | H15: =IF($B15=0,T14,(T14+$D15*T$1)*H$1) | I15: =IF($B15=0,U14,(U14+$D15*U$1)*I$1) | J15: =IF($B15=0,V14,(V14+$D15*V$1)*J$1) | K15: =IF($B15=0,W14,(W14+$D15*W$1)*K$1) | L15: =IF($B15=0,0,(R14+$D15*R$1)*L$1) | M15: =IF($B15=0,0,(S14+$D15*S$1)*M$1) | N15: =IF($B15=0,0,(T14+$D15*T$1)*N$1) | O15: =IF($B15=0,0,(U14+$D15*U$1)*O$1) | P15: =IF($B15=0,0,(V14+$D15*V$1)*P$1) | Q15: =IF($B15=0,0,(W14+$D15*W$1)*Q$1) | R15: =IF(Y15=0,F15,F15*(1-(AF15-AG15)/Y15)) | S15: =IF(Y15=0,G15,G15*(1-(AF15-AG15)/Y15)) | T15: =IF(Y15=0,H15,H15*(1-(AF15-AG15)/Y15)) | U15: =IF(Y15=0,I15,I15*(1-(AF15-AG15)/Y15)) | V15: =IF(Y15=0,J15,J15*(1-(AF15-AG15)/Y15)) | W15: =IF(Y15=0,K15,K15*(1-(AF15-AG15)/Y15)) | X15: =$D15*(R$1+S$1+T$1+U$1+V$1+W$1) | Y15: =SUM(F15:K15) | Z15: =SUM(L15:Q15) | AA15: =Y15-SUM(R14:W14)-X15 | AB15: =AH14+Z15+Y15 | AC15: =IF(RankTF<RankNR,BF15,0)+IF(RankRR<RankNR,CJ15,0) | AD15: =MAX(0,MIN(AB15,$E15-AC15)) | AE15: =MIN(AD15,AH14+Z15) | AF15: =AD15-AE15 | AG15: =IF(DRIP="Yes",AH14+Z15-AE15,0) | AH15: =IF(DRIP="Yes",0,AH14+Z15-AE15) | AI15: =SUM(R15:W15)+AH15 | AJ15: =IF($B15=0,AV14,(AV14+$D15*AV$1)*AJ$1) | AK15: =IF($B15=0,AW14,(AW14+$D15*AW$1)*AK$1) | AL15: =IF($B15=0,AX14,(AX14+$D15*AX$1)*AL$1) | AM15: =IF($B15=0,AY14,(AY14+$D15*AY$1)*AM$1) | AN15: =IF($B15=0,AZ14,(AZ14+$D15*AZ$1)*AN$1) | AO15: =IF($B15=0,BA14,(BA14+$D15*BA$1)*AO$1) | AP15: =IF($B15=0,0,(AV14+$D15*AV$1)*AP$1) | AQ15: =IF($B15=0,0,(AW14+$D15*AW$1)*AQ$1) | AR15: =IF($B15=0,0,(AX14+$D15*AX$1)*AR$1) | AS15: =IF($B15=0,0,(AY14+$D15*AY$1)*AS$1) | AT15: =IF($B15=0,0,(AZ14+$D15*AZ$1)*AT$1) | AU15: =IF($B15=0,0,(BA14+$D15*BA$1)*AU$1) | AV15: =IF(BC15=0,AJ15,AJ15*(1-(BJ15-BK15)/BC15)) | AW15: =IF(BC15=0,AK15,AK15*(1-(BJ15-BK15)/BC15)) | AX15: =IF(BC15=0,AL15,AL15*(1-(BJ15-BK15)/BC15)) | AY15: =IF(BC15=0,AM15,AM15*(1-(BJ15-BK15)/BC15)) | AZ15: =IF(BC15=0,AN15,AN15*(1-(BJ15-BK15)/BC15)) | BA15: =IF(BC15=0,AO15,AO15*(1-(BJ15-BK15)/BC15)) | BB15: =$D15*(AV$1+AW$1+AX$1+AY$1+AZ$1+BA$1) | BC15: =SUM(AJ15:AO15) | BD15: =SUM(AP15:AU15) | BE15: =BC15-SUM(AV14:BA14)-BB15 | BF15: =BL14+BD15+BC15 | BG15: =IF(RankNR<RankTF,AB15,0)+IF(RankRR<RankTF,CJ15,0) | BH15: =MAX(0,MIN(BF15,$E15-BG15)) | BI15: =MIN(BH15,BL14+BD15) | BJ15: =BH15-BI15 | BK15: =IF(DRIP="Yes",BL14+BD15-BI15,0) | BL15: =IF(DRIP="Yes",0,BL14+BD15-BI15) | BM15: =SUM(AV15:BA15)+BL15 | BN15: =IF($B15=0,BZ14,(BZ14+$D15*BZ$1)*BN$1) | BO15: =IF($B15=0,CA14,(CA14+$D15*CA$1)*BO$1) | BP15: =IF($B15=0,CB14,(CB14+$D15*CB$1)*BP$1) | BQ15: =IF($B15=0,CC14,(CC14+$D15*CC$1)*BQ$1) | BR15: =IF($B15=0,CD14,(CD14+$D15*CD$1)*BR$1) | BS15: =IF($B15=0,CE14,(CE14+$D15*CE$1)*BS$1) | BT15: =IF($B15=0,0,(BZ14+$D15*BZ$1)*BT$1) | BU15: =IF($B15=0,0,(CA14+$D15*CA$1)*BU$1) | BV15: =IF($B15=0,0,(CB14+$D15*CB$1)*BV$1) | BW15: =IF($B15=0,0,(CC14+$D15*CC$1)*BW$1) | BX15: =IF($B15=0,0,(CD14+$D15*CD$1)*BX$1) | BY15: =IF($B15=0,0,(CE14+$D15*CE$1)*BY$1) | BZ15: =IF(CG15=0,BN15,BN15*(1-(CN15-CO15)/CG15)) | CA15: =IF(CG15=0,BO15,BO15*(1-(CN15-CO15)/CG15)) | CB15: =IF(CG15=0,BP15,BP15*(1-(CN15-CO15)/CG15)) | CC15: =IF(CG15=0,BQ15,BQ15*(1-(CN15-CO15)/CG15)) | CD15: =IF(CG15=0,BR15,BR15*(1-(CN15-CO15)/CG15)) | CE15: =IF(CG15=0,BS15,BS15*(1-(CN15-CO15)/CG15)) | CF15: =$D15*(BZ$1+CA$1+CB$1+CC$1+CD$1+CE$1) | CG15: =SUM(BN15:BS15) | CH15: =SUM(BT15:BY15) | CI15: =CG15-SUM(BZ14:CE14)-CF15 | CJ15: =CP14+CH15+CG15 | CK15: =IF(RankNR<RankRR,AB15,0)+IF(RankTF<RankRR,BF15,0) | CL15: =MAX(0,MIN(CJ15,$E15-CK15)) | CM15: =MIN(CL15,CP14+CH15) | CN15: =CL15-CM15 | CO15: =IF(DRIP="Yes",CP14+CH15-CM15,0) | CP15: =IF(DRIP="Yes",0,CP14+CH15-CM15) | CQ15: =SUM(BZ15:CE15)+CP15 | CR15: =IF(S1Type="Eligible",L15,0)+IF(S2Type="Eligible",M15,0)+IF(S3Type="Eligible",N15,0)+IF(S4Type="Eligible",O15,0)+IF(S5Type="Eligible",P15,0)+IF(S6Type="Eligible",Q15,0) | CS15: =IF(S1Type="Non-eligible",L15,0)+IF(S2Type="Non-eligible",M15,0)+IF(S3Type="Non-eligible",N15,0)+IF(S4Type="Non-eligible",O15,0)+IF(S5Type="Non-eligible",P15,0)+IF(S6Type="Non-eligible",Q15,0) | CT15: =IF(S1Type="Foreign / interest",L15,0)+IF(S2Type="Foreign / interest",M15,0)+IF(S3Type="Foreign / interest",N15,0)+IF(S4Type="Foreign / interest",O15,0)+IF(S5Type="Foreign / interest",P15,0)+IF(S6Type="Foreign / interest",Q15,0) | CU15: =CW14+X15 | CV15: =IF(Y15=0,0,AF15*(1-CU15/Y15)) | CW15: =IF(Y15=0,CU15,CU15*(1-AF15/Y15))+AG15 | CX15: =AI15+BM15+CQ15 | CY15: =AD15+BH15+CL15 | CZ15: =AE15+BI15+CM15 | DA15: =AF15+BJ15+CN15 | DB15: =IF(AND($B15=1,$E15-CY15>0.01),1,0)
... A603: =A602+1 | B603: =IF($A603<=HorizonM,1,0) | C603: =INT(($A603-1)/12)+1 | D603: =IF($B603=0,0,IF(AND($A603>=CStartEff,$A603<=CEndEff),ContribMonthly*POWER(1+N(ContribEsc),INT(($A603-CStartEff)/12)),0)) | E603: =IF($B603=0,0,IF(AND($A603>=WdStartEff,$A603<=WdEndEff),IF(WdFreq="Annual",IF(MOD($A603-WdStartEff,12)=0,N(WdAmt),0),WdMonthlyBase)*IF(WdIndexed="Yes",POWER(1+N(Inflation),INT(($A603-WdStartEff)/12)),1),0)) | F603: =IF($B603=0,R602,(R602+$D603*R$1)*F$1) | G603: =IF($B603=0,S602,(S602+$D603*S$1)*G$1) | H603: =IF($B603=0,T602,(T602+$D603*T$1)*H$1) | I603: =IF($B603=0,U602,(U602+$D603*U$1)*I$1) | J603: =IF($B603=0,V602,(V602+$D603*V$1)*J$1) | K603: =IF($B603=0,W602,(W602+$D603*W$1)*K$1) | L603: =IF($B603=0,0,(R602+$D603*R$1)*L$1) | M603: =IF($B603=0,0,(S602+$D603*S$1)*M$1) | N603: =IF($B603=0,0,(T602+$D603*T$1)*N$1) | O603: =IF($B603=0,0,(U602+$D603*U$1)*O$1) | P603: =IF($B603=0,0,(V602+$D603*V$1)*P$1) | Q603: =IF($B603=0,0,(W602+$D603*W$1)*Q$1) | R603: =IF(Y603=0,F603,F603*(1-(AF603-AG603)/Y603)) | S603: =IF(Y603=0,G603,G603*(1-(AF603-AG603)/Y603)) | T603: =IF(Y603=0,H603,H603*(1-(AF603-AG603)/Y603)) | U603: =IF(Y603=0,I603,I603*(1-(AF603-AG603)/Y603)) | V603: =IF(Y603=0,J603,J603*(1-(AF603-AG603)/Y603)) | W603: =IF(Y603=0,K603,K603*(1-(AF603-AG603)/Y603)) | X603: =$D603*(R$1+S$1+T$1+U$1+V$1+W$1) | Y603: =SUM(F603:K603) | Z603: =SUM(L603:Q603) | AA603: =Y603-SUM(R602:W602)-X603 | AB603: =AH602+Z603+Y603 | AC603: =IF(RankTF<RankNR,BF603,0)+IF(RankRR<RankNR,CJ603,0) | AD603: =MAX(0,MIN(AB603,$E603-AC603)) | AE603: =MIN(AD603,AH602+Z603) | AF603: =AD603-AE603 | AG603: =IF(DRIP="Yes",AH602+Z603-AE603,0) | AH603: =IF(DRIP="Yes",0,AH602+Z603-AE603) | AI603: =SUM(R603:W603)+AH603 | AJ603: =IF($B603=0,AV602,(AV602+$D603*AV$1)*AJ$1) | AK603: =IF($B603=0,AW602,(AW602+$D603*AW$1)*AK$1) | AL603: =IF($B603=0,AX602,(AX602+$D603*AX$1)*AL$1) | AM603: =IF($B603=0,AY602,(AY602+$D603*AY$1)*AM$1) | AN603: =IF($B603=0,AZ602,(AZ602+$D603*AZ$1)*AN$1) | AO603: =IF($B603=0,BA602,(BA602+$D603*BA$1)*AO$1) | AP603: =IF($B603=0,0,(AV602+$D603*AV$1)*AP$1) | AQ603: =IF($B603=0,0,(AW602+$D603*AW$1)*AQ$1) | AR603: =IF($B603=0,0,(AX602+$D603*AX$1)*AR$1) | AS603: =IF($B603=0,0,(AY602+$D603*AY$1)*AS$1) | AT603: =IF($B603=0,0,(AZ602+$D603*AZ$1)*AT$1) | AU603: =IF($B603=0,0,(BA602+$D603*BA$1)*AU$1) | AV603: =IF(BC603=0,AJ603,AJ603*(1-(BJ603-BK603)/BC603)) | AW603: =IF(BC603=0,AK603,AK603*(1-(BJ603-BK603)/BC603)) | AX603: =IF(BC603=0,AL603,AL603*(1-(BJ603-BK603)/BC603)) | AY603: =IF(BC603=0,AM603,AM603*(1-(BJ603-BK603)/BC603)) | AZ603: =IF(BC603=0,AN603,AN603*(1-(BJ603-BK603)/BC603)) | BA603: =IF(BC603=0,AO603,AO603*(1-(BJ603-BK603)/BC603)) | BB603: =$D603*(AV$1+AW$1+AX$1+AY$1+AZ$1+BA$1) | BC603: =SUM(AJ603:AO603) | BD603: =SUM(AP603:AU603) | BE603: =BC603-SUM(AV602:BA602)-BB603 | BF603: =BL602+BD603+BC603 | BG603: =IF(RankNR<RankTF,AB603,0)+IF(RankRR<RankTF,CJ603,0) | BH603: =MAX(0,MIN(BF603,$E603-BG603)) | BI603: =MIN(BH603,BL602+BD603) | BJ603: =BH603-BI603 | BK603: =IF(DRIP="Yes",BL602+BD603-BI603,0) | BL603: =IF(DRIP="Yes",0,BL602+BD603-BI603) | BM603: =SUM(AV603:BA603)+BL603 | BN603: =IF($B603=0,BZ602,(BZ602+$D603*BZ$1)*BN$1) | BO603: =IF($B603=0,CA602,(CA602+$D603*CA$1)*BO$1) | BP603: =IF($B603=0,CB602,(CB602+$D603*CB$1)*BP$1) | BQ603: =IF($B603=0,CC602,(CC602+$D603*CC$1)*BQ$1) | BR603: =IF($B603=0,CD602,(CD602+$D603*CD$1)*BR$1) | BS603: =IF($B603=0,CE602,(CE602+$D603*CE$1)*BS$1) | BT603: =IF($B603=0,0,(BZ602+$D603*BZ$1)*BT$1) | BU603: =IF($B603=0,0,(CA602+$D603*CA$1)*BU$1) | BV603: =IF($B603=0,0,(CB602+$D603*CB$1)*BV$1) | BW603: =IF($B603=0,0,(CC602+$D603*CC$1)*BW$1) | BX603: =IF($B603=0,0,(CD602+$D603*CD$1)*BX$1) | BY603: =IF($B603=0,0,(CE602+$D603*CE$1)*BY$1) | BZ603: =IF(CG603=0,BN603,BN603*(1-(CN603-CO603)/CG603)) | CA603: =IF(CG603=0,BO603,BO603*(1-(CN603-CO603)/CG603)) | CB603: =IF(CG603=0,BP603,BP603*(1-(CN603-CO603)/CG603)) | CC603: =IF(CG603=0,BQ603,BQ603*(1-(CN603-CO603)/CG603)) | CD603: =IF(CG603=0,BR603,BR603*(1-(CN603-CO603)/CG603)) | CE603: =IF(CG603=0,BS603,BS603*(1-(CN603-CO603)/CG603)) | CF603: =$D603*(BZ$1+CA$1+CB$1+CC$1+CD$1+CE$1) | CG603: =SUM(BN603:BS603) | CH603: =SUM(BT603:BY603) | CI603: =CG603-SUM(BZ602:CE602)-CF603 | CJ603: =CP602+CH603+CG603 | CK603: =IF(RankNR<RankRR,AB603,0)+IF(RankTF<RankRR,BF603,0) | CL603: =MAX(0,MIN(CJ603,$E603-CK603)) | CM603: =MIN(CL603,CP602+CH603) | CN603: =CL603-CM603 | CO603: =IF(DRIP="Yes",CP602+CH603-CM603,0) | CP603: =IF(DRIP="Yes",0,CP602+CH603-CM603) | CQ603: =SUM(BZ603:CE603)+CP603 | CR603: =IF(S1Type="Eligible",L603,0)+IF(S2Type="Eligible",M603,0)+IF(S3Type="Eligible",N603,0)+IF(S4Type="Eligible",O603,0)+IF(S5Type="Eligible",P603,0)+IF(S6Type="Eligible",Q603,0) | CS603: =IF(S1Type="Non-eligible",L603,0)+IF(S2Type="Non-eligible",M603,0)+IF(S3Type="Non-eligible",N603,0)+IF(S4Type="Non-eligible",O603,0)+IF(S5Type="Non-eligible",P603,0)+IF(S6Type="Non-eligible",Q603,0) | CT603: =IF(S1Type="Foreign / interest",L603,0)+IF(S2Type="Foreign / interest",M603,0)+IF(S3Type="Foreign / interest",N603,0)+IF(S4Type="Foreign / interest",O603,0)+IF(S5Type="Foreign / interest",P603,0)+IF(S6Type="Foreign / interest",Q603,0) | CU603: =CW602+X603 | CV603: =IF(Y603=0,0,AF603*(1-CU603/Y603)) | CW603: =IF(Y603=0,CU603,CU603*(1-AF603/Y603))+AG603 | CX603: =AI603+BM603+CQ603 | CY603: =AD603+BH603+CL603 | CZ603: =AE603+BI603+CM603 | DA603: =AF603+BJ603+CN603 | DB603: =IF(AND($B603=1,$E603-CY603>0.01),1,0)

Sheet Assumptions & Notes
A1: Assumptions, tax tables & conventions
A2: Tax year 2026 parameters, verified 2026-07-10. The engine references these named cells — update here when CRA publishes new figures.
A4: Federal brackets (2026) | B4: Lower bound | C4: Rate | D4: Rate step
B5: 0 | C5: 0.14 | D5: 0.14
B6: 58523 | C6: 0.205 | D6: 0.065
B7: 117045 | C7: 0.26 | D7: 0.055
B8: 181440 | C8: 0.29 | D8: 0.03
B9: 258482 | C9: 0.33 | D9: 0.04
A11: Ontario brackets (2026)
B12: 0 | C12: 0.0505 | D12: 0.0505
B13: 53891 | C13: 0.0915 | D13: 0.041
B14: 107785 | C14: 0.1116 | D14: 0.0201
B15: 150000 | C15: 0.1216 | D15: 0.01
B16: 220000 | C16: 0.1316 | D16: 0.01
A18: Federal lowest rate | B18: 0.14
A19: Federal BPA (max) | B19: 16452
A20: Federal BPA (min) | B20: 14829
A21: Federal BPA phase-out floor | B21: 181440
A22: Federal BPA phase-out ceiling | B22: 258482
A23: Ontario lowest rate | B23: 0.0505
A24: Ontario BPA | B24: 12989
A25: Ontario surtax threshold 1 (20%) | B25: 5818
A26: Ontario surtax threshold 2 (36%) | B26: 7446
A27: Ontario surtax rate 1 | B27: 0.2
A28: Ontario surtax rate 2 | B28: 0.36
A29: Eligible dividend gross-up | B29: 0.38
... A35: Capital gains inclusion rate | B35: 0.5
A36: Scenario delta — base | B36: =N(RetOverride)
A37: Scenario delta — minus 1% | B37: =N(RetOverride)-0.01
A38: Scenario delta — plus 1% | B38: =N(RetOverride)+0.01
A41: SOURCES (verified 2026-07-10)
A42: • Federal brackets & 14% lowest rate: CRA 2026 tax-year page (canada.ca) + Bill C-4, Royal Assent 2026-03-12; thresholds = 2025 × 1.020 indexation.
A43: • Federal BPA $16,452 / $14,829 with phase-out $181,440→$258,482: CRA indexation release; KPMG personal tax credits table (Dec 31, 2025).
A44: • Ontario brackets, BPA $12,989, surtax $5,818 / $7,446 (indexation 1.019): taxtips.ca/on.htm; EY Ontario 2026 table (2026-01-15).
A45: • Dividend gross-ups & credits (38% / 15.0198% / 10%; 15% / 9.0301% / 2.9863%): CRA line 40425; ontario.ca dividend tax credit page.
A46: • Capital gains inclusion 50%: proposed 2/3 rate increase cancelled 2025-03-21 (Dept. of Finance), never enacted.
A48: ENGINE CONVENTIONS
A49: • Monthly engine. Annual rates converted to effective monthly: (1+annual)^(1/12)−1. Weekly amounts ×52/12, bi-weekly ×26/12.
A50: • Order of operations each month: contributions in → price growth on (opening+contribution) → dividends on (opening+contribution) → withdrawal funded (dividends/cash first, then pro-rata asset sale per funding order) → leftover dividends reinvested (or held as 0%-cash if DRIP = No).
A51: • Escalations/indexing step once every 12 months from their own start month.
A52: • 'Annual' withdrawal frequency = full amount taken every 12th month starting at the start month.
A53: • ACB tracking (non-registered): opening ACB = ACB% × opening non-reg value; contributions & reinvested dividends add at full value; sales remove ACB in proportion to market value sold. Realized gain = proceeds × (1 − ACB/market value). A negative result is a capital loss; annual taxable gains are floored at zero (losses are not carried between years).
... A66: • A large single-year sale may trigger Alternative Minimum Tax — confirm with an accountant before acting on any single-year figure.

Sheet Engine (No Withdrawals)
A1: Row 1 = calculation helpers (monthly rate multipliers & contribution shares). | F1: =POWER(1+N(S1Ret)+DeltaBase,1/12) | G1: =POWER(1+N(S2Ret)+DeltaBase,1/12) | H1: =POWER(1+N(S3Ret)+DeltaBase,1/12) | I1: =POWER(1+N(S4Ret)+DeltaBase,1/12) | J1: =POWER(1+N(S5Ret)+DeltaBase,1/12) | K1: =POWER(1+N(S6Ret)+DeltaBase,1/12) | L1: =POWER(1+N(S1Yld),1/12)-1 | M1: =POWER(1+N(S2Yld),1/12)-1 | N1: =POWER(1+N(S3Yld),1/12)-1 | O1: =POWER(1+N(S4Yld),1/12)-1 | P1: =POWER(1+N(S5Yld),1/12)-1 | Q1: =POWER(1+N(S6Yld),1/12)-1 | R1: =N(DS1)*N(S1NR) | S1: =N(DS2)*N(S2NR) | T1: =N(DS3)*N(S3NR) | U1: =N(DS4)*N(S4NR) | V1: =N(DS5)*N(S5NR) | W1: =N(DS6)*N(S6NR) | AJ1: =POWER(1+N(S1Ret)+DeltaBase,1/12) | AK1: =POWER(1+N(S2Ret)+DeltaBase,1/12) | AL1: =POWER(1+N(S3Ret)+DeltaBase,1/12) | AM1: =POWER(1+N(S4Ret)+DeltaBase,1/12) | AN1: =POWER(1+N(S5Ret)+DeltaBase,1/12) | AO1: =POWER(1+N(S6Ret)+DeltaBase,1/12) | AP1: =POWER(1+N(S1Yld),1/12)-1 | AQ1: =POWER(1+N(S2Yld),1/12)-1 | AR1: =POWER(1+N(S3Yld),1/12)-1 | AS1: =POWER(1+N(S4Yld),1/12)-1 | AT1: =POWER(1+N(S5Yld),1/12)-1 | AU1: =POWER(1+N(S6Yld),1/12)-1 | AV1: =N(DS1)*N(S1TF) | AW1: =N(DS2)*N(S2TF) | AX1: =N(DS3)*N(S3TF) | AY1: =N(DS4)*N(S4TF) | AZ1: =N(DS5)*N(S5TF) | BA1: =N(DS6)*N(S6TF) | BN1: =POWER(1+N(S1Ret)+DeltaBase,1/12) | BO1: =POWER(1+N(S2Ret)+DeltaBase,1/12) | BP1: =POWER(1+N(S3Ret)+DeltaBase,1/12) | BQ1: =POWER(1+N(S4Ret)+DeltaBase,1/12) | BR1: =POWER(1+N(S5Ret)+DeltaBase,1/12) | BS1: =POWER(1+N(S6Ret)+DeltaBase,1/12) | BT1: =POWER(1+N(S1Yld),1/12)-1 | BU1: =POWER(1+N(S2Yld),1/12)-1 | BV1: =POWER(1+N(S3Yld),1/12)-1 | BW1: =POWER(1+N(S4Yld),1/12)-1 | BX1: =POWER(1+N(S5Yld),1/12)-1 | BY1: =POWER(1+N(S6Yld),1/12)-1 | BZ1: =N(DS1)*N(S1RR) | CA1: =N(DS2)*N(S2RR) | CB1: =N(DS3)*N(S3RR) | CC1: =N(DS4)*N(S4RR) | CD1: =N(DS5)*N(S5RR) | CE1: =N(DS6)*N(S6RR)
A2: Month | B2: Active | C2: Year | D2: Contribution $ | E2: Withdrawal target $ | F2: NR S1 post-growth | G2: NR S2 post-growth | H2: NR S3 post-growth | I2: NR S4 post-growth | J2: NR S5 post-growth | K2: NR S6 post-growth | L2: NR S1 dividends | M2: NR S2 dividends | N2: NR S3 dividends | O2: NR S4 dividends | P2: NR S5 dividends | Q2: NR S6 dividends | R2: NR S1 closing | S2: NR S2 closing | T2: NR S3 closing | U2: NR S4 closing | V2: NR S5 closing | W2: NR S6 closing | X2: NR contribution | Y2: NR balance post-growth | Z2: NR dividends | AA2: NR growth | AB2: NR capacity | AC2: NR capacity ahead | AD2: NR withdrawn | AE2: NR from divs/cash | AF2: NR sold | AG2: NR reinvested | AH2: NR cash bucket | AI2: NR balance | AJ2: TF S1 post-growth | AK2: TF S2 post-growth | AL2: TF S3 post-growth | AM2: TF S4 post-growth | AN2: TF S5 post-growth | AO2: TF S6 post-growth | AP2: TF S1 dividends | AQ2: TF S2 dividends | AR2: TF S3 dividends | AS2: TF S4 dividends | AT2: TF S5 dividends | AU2: TF S6 dividends | AV2: TF S1 closing | AW2: TF S2 closing | AX2: TF S3 closing | AY2: TF S4 closing | AZ2: TF S5 closing | BA2: TF S6 closing | BB2: TF contribution | BC2: TF balance post-growth | BD2: TF dividends | BE2: TF growth | BF2: TF capacity | BG2: TF capacity ahead | BH2: TF withdrawn | BI2: TF from divs/cash | BJ2: TF sold | BK2: TF reinvested | BL2: TF cash bucket | BM2: TF balance | BN2: RR S1 post-growth | BO2: RR S2 post-growth | BP2: RR S3 post-growth | BQ2: RR S4 post-growth | BR2: RR S5 post-growth | BS2: RR S6 post-growth | BT2: RR S1 dividends | BU2: RR S2 dividends | BV2: RR S3 dividends | BW2: RR S4 dividends | BX2: RR S5 dividends | BY2: RR S6 dividends | BZ2: RR S1 closing | CA2: RR S2 closing | CB2: RR S3 closing | CC2: RR S4 closing | CD2: RR S5 closing | CE2: RR S6 closing | CF2: RR contribution | CG2: RR balance post-growth | CH2: RR dividends | CI2: RR growth | CJ2: RR capacity | CK2: RR capacity ahead | CL2: RR withdrawn | CM2: RR from divs/cash | CN2: RR sold | CO2: RR reinvested | CP2: RR cash bucket | CQ2: RR balance | CR2: NR divs — eligible | CS2: NR divs — non-eligible | CT2: NR divs — foreign/interest | CU2: ACB base (pre-sale) | CV2: Realized gain (NR) | CW2: ACB (closing) | CX2: Total balance | CY2: Total withdrawn | CZ2: Funded by divs/cash | DA2: Funded by sales | DB2: Shortfall flag
A3: 0 | B3: 1 | C3: 0 | D3: 0 | E3: 0 | F3: 0 | G3: 0 | H3: 0 | I3: 0 | J3: 0 | K3: 0 | L3: 0 | M3: 0 | N3: 0 | O3: 0 | P3: 0 | Q3: 0 | R3: =StartValue*N(S1Alloc)*N(S1NR) | S3: =StartValue*N(S2Alloc)*N(S2NR) | T3: =StartValue*N(S3Alloc)*N(S3NR) | U3: =StartValue*N(S4Alloc)*N(S4NR) | V3: =StartValue*N(S5Alloc)*N(S5NR) | W3: =StartValue*N(S6Alloc)*N(S6NR) | X3: 0 | Y3: 0 | Z3: 0 | AA3: 0 | AB3: 0 | AC3: 0 | AD3: 0 | AE3: 0 | AF3: 0 | AG3: 0 | AH3: 0 | AI3: =SUM(R3:W3) | AJ3: 0 | AK3: 0 | AL3: 0 | AM3: 0 | AN3: 0 | AO3: 0 | AP3: 0 | AQ3: 0 | AR3: 0 | AS3: 0 | AT3: 0 | AU3: 0 | AV3: =StartValue*N(S1Alloc)*N(S1TF) | AW3: =StartValue*N(S2Alloc)*N(S2TF) | AX3: =StartValue*N(S3Alloc)*N(S3TF) | AY3: =StartValue*N(S4Alloc)*N(S4TF) | AZ3: =StartValue*N(S5Alloc)*N(S5TF) | BA3: =StartValue*N(S6Alloc)*N(S6TF) | BB3: 0 | BC3: 0 | BD3: 0 | BE3: 0 | BF3: 0 | BG3: 0 | BH3: 0 | BI3: 0 | BJ3: 0 | BK3: 0 | BL3: 0 | BM3: =SUM(AV3:BA3) | BN3: 0 | BO3: 0 | BP3: 0 | BQ3: 0 | BR3: 0 | BS3: 0 | BT3: 0 | BU3: 0 | BV3: 0 | BW3: 0 | BX3: 0 | BY3: 0 | BZ3: =StartValue*N(S1Alloc)*N(S1RR) | CA3: =StartValue*N(S2Alloc)*N(S2RR) | CB3: =StartValue*N(S3Alloc)*N(S3RR) | CC3: =StartValue*N(S4Alloc)*N(S4RR) | CD3: =StartValue*N(S5Alloc)*N(S5RR) | CE3: =StartValue*N(S6Alloc)*N(S6RR) | CF3: 0 | CG3: 0 | CH3: 0 | CI3: 0 | CJ3: 0 | CK3: 0 | CL3: 0 | CM3: 0 | CN3: 0 | CO3: 0 | CP3: 0 | CQ3: =SUM(BZ3:CE3) | CR3: 0 | CS3: 0 | CT3: 0 | CU3: =N(ACBPct)*SUM(R3:W3) | CV3: 0 | CW3: =N(ACBPct)*SUM(R3:W3) | CX3: =AI3+BM3+CQ3 | CY3: 0 | CZ3: 0 | DA3: 0 | DB3: 0
A4: =A3+1 | B4: =IF($A4<=HorizonM,1,0) | C4: =INT(($A4-1)/12)+1 | D4: =IF($B4=0,0,IF(AND($A4>=CStartEff,$A4<=CEndEff),ContribMonthly*POWER(1+N(ContribEsc),INT(($A4-CStartEff)/12)),0)) | E4: 0 | F4: =IF($B4=0,R3,(R3+$D4*R$1)*F$1) | G4: =IF($B4=0,S3,(S3+$D4*S$1)*G$1) | H4: =IF($B4=0,T3,(T3+$D4*T$1)*H$1) | I4: =IF($B4=0,U3,(U3+$D4*U$1)*I$1) | J4: =IF($B4=0,V3,(V3+$D4*V$1)*J$1) | K4: =IF($B4=0,W3,(W3+$D4*W$1)*K$1) | L4: =IF($B4=0,0,(R3+$D4*R$1)*L$1) | M4: =IF($B4=0,0,(S3+$D4*S$1)*M$1) | N4: =IF($B4=0,0,(T3+$D4*T$1)*N$1) | O4: =IF($B4=0,0,(U3+$D4*U$1)*O$1) | P4: =IF($B4=0,0,(V3+$D4*V$1)*P$1) | Q4: =IF($B4=0,0,(W3+$D4*W$1)*Q$1) | R4: =IF(Y4=0,F4,F4*(1-(AF4-AG4)/Y4)) | S4: =IF(Y4=0,G4,G4*(1-(AF4-AG4)/Y4)) | T4: =IF(Y4=0,H4,H4*(1-(AF4-AG4)/Y4)) | U4: =IF(Y4=0,I4,I4*(1-(AF4-AG4)/Y4)) | V4: =IF(Y4=0,J4,J4*(1-(AF4-AG4)/Y4)) | W4: =IF(Y4=0,K4,K4*(1-(AF4-AG4)/Y4)) | X4: =$D4*(R$1+S$1+T$1+U$1+V$1+W$1) | Y4: =SUM(F4:K4) | Z4: =SUM(L4:Q4) | AA4: =Y4-SUM(R3:W3)-X4 | AB4: =AH3+Z4+Y4 | AC4: =IF(RankTF<RankNR,BF4,0)+IF(RankRR<RankNR,CJ4,0) | AD4: =MAX(0,MIN(AB4,$E4-AC4)) | AE4: =MIN(AD4,AH3+Z4) | AF4: =AD4-AE4 | AG4: =IF(DRIP="Yes",AH3+Z4-AE4,0) | AH4: =IF(DRIP="Yes",0,AH3+Z4-AE4) | AI4: =SUM(R4:W4)+AH4 | AJ4: =IF($B4=0,AV3,(AV3+$D4*AV$1)*AJ$1) | AK4: =IF($B4=0,AW3,(AW3+$D4*AW$1)*AK$1) | AL4: =IF($B4=0,AX3,(AX3+$D4*AX$1)*AL$1) | AM4: =IF($B4=0,AY3,(AY3+$D4*AY$1)*AM$1) | AN4: =IF($B4=0,AZ3,(AZ3+$D4*AZ$1)*AN$1) | AO4: =IF($B4=0,BA3,(BA3+$D4*BA$1)*AO$1) | AP4: =IF($B4=0,0,(AV3+$D4*AV$1)*AP$1) | AQ4: =IF($B4=0,0,(AW3+$D4*AW$1)*AQ$1) | AR4: =IF($B4=0,0,(AX3+$D4*AX$1)*AR$1) | AS4: =IF($B4=0,0,(AY3+$D4*AY$1)*AS$1) | AT4: =IF($B4=0,0,(AZ3+$D4*AZ$1)*AT$1) | AU4: =IF($B4=0,0,(BA3+$D4*BA$1)*AU$1) | AV4: =IF(BC4=0,AJ4,AJ4*(1-(BJ4-BK4)/BC4)) | AW4: =IF(BC4=0,AK4,AK4*(1-(BJ4-BK4)/BC4)) | AX4: =IF(BC4=0,AL4,AL4*(1-(BJ4-BK4)/BC4)) | AY4: =IF(BC4=0,AM4,AM4*(1-(BJ4-BK4)/BC4)) | AZ4: =IF(BC4=0,AN4,AN4*(1-(BJ4-BK4)/BC4)) | BA4: =IF(BC4=0,AO4,AO4*(1-(BJ4-BK4)/BC4)) | BB4: =$D4*(AV$1+AW$1+AX$1+AY$1+AZ$1+BA$1) | BC4: =SUM(AJ4:AO4) | BD4: =SUM(AP4:AU4) | BE4: =BC4-SUM(AV3:BA3)-BB4 | BF4: =BL3+BD4+BC4 | BG4: =IF(RankNR<RankTF,AB4,0)+IF(RankRR<RankTF,CJ4,0) | BH4: =MAX(0,MIN(BF4,$E4-BG4)) | BI4: =MIN(BH4,BL3+BD4) | BJ4: =BH4-BI4 | BK4: =IF(DRIP="Yes",BL3+BD4-BI4,0) | BL4: =IF(DRIP="Yes",0,BL3+BD4-BI4) | BM4: =SUM(AV4:BA4)+BL4 | BN4: =IF($B4=0,BZ3,(BZ3+$D4*BZ$1)*BN$1) | BO4: =IF($B4=0,CA3,(CA3+$D4*CA$1)*BO$1) | BP4: =IF($B4=0,CB3,(CB3+$D4*CB$1)*BP$1) | BQ4: =IF($B4=0,CC3,(CC3+$D4*CC$1)*BQ$1) | BR4: =IF($B4=0,CD3,(CD3+$D4*CD$1)*BR$1) | BS4: =IF($B4=0,CE3,(CE3+$D4*CE$1)*BS$1) | BT4: =IF($B4=0,0,(BZ3+$D4*BZ$1)*BT$1) | BU4: =IF($B4=0,0,(CA3+$D4*CA$1)*BU$1) | BV4: =IF($B4=0,0,(CB3+$D4*CB$1)*BV$1) | BW4: =IF($B4=0,0,(CC3+$D4*CC$1)*BW$1) | BX4: =IF($B4=0,0,(CD3+$D4*CD$1)*BX$1) | BY4: =IF($B4=0,0,(CE3+$D4*CE$1)*BY$1) | BZ4: =IF(CG4=0,BN4,BN4*(1-(CN4-CO4)/CG4)) | CA4: =IF(CG4=0,BO4,BO4*(1-(CN4-CO4)/CG4)) | CB4: =IF(CG4=0,BP4,BP4*(1-(CN4-CO4)/CG4)) | CC4: =IF(CG4=0,BQ4,BQ4*(1-(CN4-CO4)/CG4)) | CD4: =IF(CG4=0,BR4,BR4*(1-(CN4-CO4)/CG4)) | CE4: =IF(CG4=0,BS4,BS4*(1-(CN4-CO4)/CG4)) | CF4: =$D4*(BZ$1+CA$1+CB$1+CC$1+CD$1+CE$1) | CG4: =SUM(BN4:BS4) | CH4: =SUM(BT4:BY4) | CI4: =CG4-SUM(BZ3:CE3)-CF4 | CJ4: =CP3+CH4+CG4 | CK4: =IF(RankNR<RankRR,AB4,0)+IF(RankTF<RankRR,BF4,0) | CL4: =MAX(0,MIN(CJ4,$E4-CK4)) | CM4: =MIN(CL4,CP3+CH4) | CN4: =CL4-CM4 | CO4: =IF(DRIP="Yes",CP3+CH4-CM4,0) | CP4: =IF(DRIP="Yes",0,CP3+CH4-CM4) | CQ4: =SUM(BZ4:CE4)+CP4 | CR4: =IF(S1Type="Eligible",L4,0)+IF(S2Type="Eligible",M4,0)+IF(S3Type="Eligible",N4,0)+IF(S4Type="Eligible",O4,0)+IF(S5Type="Eligible",P4,0)+IF(S6Type="Eligible",Q4,0) | CS4: =IF(S1Type="Non-eligible",L4,0)+IF(S2Type="Non-eligible",M4,0)+IF(S3Type="Non-eligible",N4,0)+IF(S4Type="Non-eligible",O4,0)+IF(S5Type="Non-eligible",P4,0)+IF(S6Type="Non-eligible",Q4,0) | CT4: =IF(S1Type="Foreign / interest",L4,0)+IF(S2Type="Foreign / interest",M4,0)+IF(S3Type="Foreign / interest",N4,0)+IF(S4Type="Foreign / interest",O4,0)+IF(S5Type="Foreign / interest",P4,0)+IF(S6Type="Foreign / interest",Q4,0) | CU4: =CW3+X4 | CV4: =IF(Y4=0,0,AF4*(1-CU4/Y4)) | CW4: =IF(Y4=0,CU4,CU4*(1-AF4/Y4))+AG4 | CX4: =AI4+BM4+CQ4 | CY4: =AD4+BH4+CL4 | CZ4: =AE4+BI4+CM4 | DA4: =AF4+BJ4+CN4 | DB4: =IF(AND($B4=1,$E4-CY4>0.01),1,0)
A5: =A4+1 | B5: =IF($A5<=HorizonM,1,0) | C5: =INT(($A5-1)/12)+1 | D5: =IF($B5=0,0,IF(AND($A5>=CStartEff,$A5<=CEndEff),ContribMonthly*POWER(1+N(ContribEsc),INT(($A5-CStartEff)/12)),0)) | E5: 0 | F5: =IF($B5=0,R4,(R4+$D5*R$1)*F$1) | G5: =IF($B5=0,S4,(S4+$D5*S$1)*G$1) | H5: =IF($B5=0,T4,(T4+$D5*T$1)*H$1) | I5: =IF($B5=0,U4,(U4+$D5*U$1)*I$1) | J5: =IF($B5=0,V4,(V4+$D5*V$1)*J$1) | K5: =IF($B5=0,W4,(W4+$D5*W$1)*K$1) | L5: =IF($B5=0,0,(R4+$D5*R$1)*L$1) | M5: =IF($B5=0,0,(S4+$D5*S$1)*M$1) | N5: =IF($B5=0,0,(T4+$D5*T$1)*N$1) | O5: =IF($B5=0,0,(U4+$D5*U$1)*O$1) | P5: =IF($B5=0,0,(V4+$D5*V$1)*P$1) | Q5: =IF($B5=0,0,(W4+$D5*W$1)*Q$1) | R5: =IF(Y5=0,F5,F5*(1-(AF5-AG5)/Y5)) | S5: =IF(Y5=0,G5,G5*(1-(AF5-AG5)/Y5)) | T5: =IF(Y5=0,H5,H5*(1-(AF5-AG5)/Y5)) | U5: =IF(Y5=0,I5,I5*(1-(AF5-AG5)/Y5)) | V5: =IF(Y5=0,J5,J5*(1-(AF5-AG5)/Y5)) | W5: =IF(Y5=0,K5,K5*(1-(AF5-AG5)/Y5)) | X5: =$D5*(R$1+S$1+T$1+U$1+V$1+W$1) | Y5: =SUM(F5:K5) | Z5: =SUM(L5:Q5) | AA5: =Y5-SUM(R4:W4)-X5 | AB5: =AH4+Z5+Y5 | AC5: =IF(RankTF<RankNR,BF5,0)+IF(RankRR<RankNR,CJ5,0) | AD5: =MAX(0,MIN(AB5,$E5-AC5)) | AE5: =MIN(AD5,AH4+Z5) | AF5: =AD5-AE5 | AG5: =IF(DRIP="Yes",AH4+Z5-AE5,0) | AH5: =IF(DRIP="Yes",0,AH4+Z5-AE5) | AI5: =SUM(R5:W5)+AH5 | AJ5: =IF($B5=0,AV4,(AV4+$D5*AV$1)*AJ$1) | AK5: =IF($B5=0,AW4,(AW4+$D5*AW$1)*AK$1) | AL5: =IF($B5=0,AX4,(AX4+$D5*AX$1)*AL$1) | AM5: =IF($B5=0,AY4,(AY4+$D5*AY$1)*AM$1) | AN5: =IF($B5=0,AZ4,(AZ4+$D5*AZ$1)*AN$1) | AO5: =IF($B5=0,BA4,(BA4+$D5*BA$1)*AO$1) | AP5: =IF($B5=0,0,(AV4+$D5*AV$1)*AP$1) | AQ5: =IF($B5=0,0,(AW4+$D5*AW$1)*AQ$1) | AR5: =IF($B5=0,0,(AX4+$D5*AX$1)*AR$1) | AS5: =IF($B5=0,0,(AY4+$D5*AY$1)*AS$1) | AT5: =IF($B5=0,0,(AZ4+$D5*AZ$1)*AT$1) | AU5: =IF($B5=0,0,(BA4+$D5*BA$1)*AU$1) | AV5: =IF(BC5=0,AJ5,AJ5*(1-(BJ5-BK5)/BC5)) | AW5: =IF(BC5=0,AK5,AK5*(1-(BJ5-BK5)/BC5)) | AX5: =IF(BC5=0,AL5,AL5*(1-(BJ5-BK5)/BC5)) | AY5: =IF(BC5=0,AM5,AM5*(1-(BJ5-BK5)/BC5)) | AZ5: =IF(BC5=0,AN5,AN5*(1-(BJ5-BK5)/BC5)) | BA5: =IF(BC5=0,AO5,AO5*(1-(BJ5-BK5)/BC5)) | BB5: =$D5*(AV$1+AW$1+AX$1+AY$1+AZ$1+BA$1) | BC5: =SUM(AJ5:AO5) | BD5: =SUM(AP5:AU5) | BE5: =BC5-SUM(AV4:BA4)-BB5 | BF5: =BL4+BD5+BC5 | BG5: =IF(RankNR<RankTF,AB5,0)+IF(RankRR<RankTF,CJ5,0) | BH5: =MAX(0,MIN(BF5,$E5-BG5)) | BI5: =MIN(BH5,BL4+BD5) | BJ5: =BH5-BI5 | BK5: =IF(DRIP="Yes",BL4+BD5-BI5,0) | BL5: =IF(DRIP="Yes",0,BL4+BD5-BI5) | BM5: =SUM(AV5:BA5)+BL5 | BN5: =IF($B5=0,BZ4,(BZ4+$D5*BZ$1)*BN$1) | BO5: =IF($B5=0,CA4,(CA4+$D5*CA$1)*BO$1) | BP5: =IF($B5=0,CB4,(CB4+$D5*CB$1)*BP$1) | BQ5: =IF($B5=0,CC4,(CC4+$D5*CC$1)*BQ$1) | BR5: =IF($B5=0,CD4,(CD4+$D5*CD$1)*BR$1) | BS5: =IF($B5=0,CE4,(CE4+$D5*CE$1)*BS$1) | BT5: =IF($B5=0,0,(BZ4+$D5*BZ$1)*BT$1) | BU5: =IF($B5=0,0,(CA4+$D5*CA$1)*BU$1) | BV5: =IF($B5=0,0,(CB4+$D5*CB$1)*BV$1) | BW5: =IF($B5=0,0,(CC4+$D5*CC$1)*BW$1) | BX5: =IF($B5=0,0,(CD4+$D5*CD$1)*BX$1) | BY5: =IF($B5=0,0,(CE4+$D5*CE$1)*BY$1) | BZ5: =IF(CG5=0,BN5,BN5*(1-(CN5-CO5)/CG5)) | CA5: =IF(CG5=0,BO5,BO5*(1-(CN5-CO5)/CG5)) | CB5: =IF(CG5=0,BP5,BP5*(1-(CN5-CO5)/CG5)) | CC5: =IF(CG5=0,BQ5,BQ5*(1-(CN5-CO5)/CG5)) | CD5: =IF(CG5=0,BR5,BR5*(1-(CN5-CO5)/CG5)) | CE5: =IF(CG5=0,BS5,BS5*(1-(CN5-CO5)/CG5)) | CF5: =$D5*(BZ$1+CA$1+CB$1+CC$1+CD$1+CE$1) | CG5: =SUM(BN5:BS5) | CH5: =SUM(BT5:BY5) | CI5: =CG5-SUM(BZ4:CE4)-CF5 | CJ5: =CP4+CH5+CG5 | CK5: =IF(RankNR<RankRR,AB5,0)+IF(RankTF<RankRR,BF5,0) | CL5: =MAX(0,MIN(CJ5,$E5-CK5)) | CM5: =MIN(CL5,CP4+CH5) | CN5: =CL5-CM5 | CO5: =IF(DRIP="Yes",CP4+CH5-CM5,0) | CP5: =IF(DRIP="Yes",0,CP4+CH5-CM5) | CQ5: =SUM(BZ5:CE5)+CP5 | CR5: =IF(S1Type="Eligible",L5,0)+IF(S2Type="Eligible",M5,0)+IF(S3Type="Eligible",N5,0)+IF(S4Type="Eligible",O5,0)+IF(S5Type="Eligible",P5,0)+IF(S6Type="Eligible",Q5,0) | CS5: =IF(S1Type="Non-eligible",L5,0)+IF(S2Type="Non-eligible",M5,0)+IF(S3Type="Non-eligible",N5,0)+IF(S4Type="Non-eligible",O5,0)+IF(S5Type="Non-eligible",P5,0)+IF(S6Type="Non-eligible",Q5,0) | CT5: =IF(S1Type="Foreign / interest",L5,0)+IF(S2Type="Foreign / interest",M5,0)+IF(S3Type="Foreign / interest",N5,0)+IF(S4Type="Foreign / interest",O5,0)+IF(S5Type="Foreign / interest",P5,0)+IF(S6Type="Foreign / interest",Q5,0) | CU5: =CW4+X5 | CV5: =IF(Y5=0,0,AF5*(1-CU5/Y5)) | CW5: =IF(Y5=0,CU5,CU5*(1-AF5/Y5))+AG5 | CX5: =AI5+BM5+CQ5 | CY5: =AD5+BH5+CL5 | CZ5: =AE5+BI5+CM5 | DA5: =AF5+BJ5+CN5 | DB5: =IF(AND($B5=1,$E5-CY5>0.01),1,0)
A6: =A5+1 | B6: =IF($A6<=HorizonM,1,0) | C6: =INT(($A6-1)/12)+1 | D6: =IF($B6=0,0,IF(AND($A6>=CStartEff,$A6<=CEndEff),ContribMonthly*POWER(1+N(ContribEsc),INT(($A6-CStartEff)/12)),0)) | E6: 0 | F6: =IF($B6=0,R5,(R5+$D6*R$1)*F$1) | G6: =IF($B6=0,S5,(S5+$D6*S$1)*G$1) | H6: =IF($B6=0,T5,(T5+$D6*T$1)*H$1) | I6: =IF($B6=0,U5,(U5+$D6*U$1)*I$1) | J6: =IF($B6=0,V5,(V5+$D6*V$1)*J$1) | K6: =IF($B6=0,W5,(W5+$D6*W$1)*K$1) | L6: =IF($B6=0,0,(R5+$D6*R$1)*L$1) | M6: =IF($B6=0,0,(S5+$D6*S$1)*M$1) | N6: =IF($B6=0,0,(T5+$D6*T$1)*N$1) | O6: =IF($B6=0,0,(U5+$D6*U$1)*O$1) | P6: =IF($B6=0,0,(V5+$D6*V$1)*P$1) | Q6: =IF($B6=0,0,(W5+$D6*W$1)*Q$1) | R6: =IF(Y6=0,F6,F6*(1-(AF6-AG6)/Y6)) | S6: =IF(Y6=0,G6,G6*(1-(AF6-AG6)/Y6)) | T6: =IF(Y6=0,H6,H6*(1-(AF6-AG6)/Y6)) | U6: =IF(Y6=0,I6,I6*(1-(AF6-AG6)/Y6)) | V6: =IF(Y6=0,J6,J6*(1-(AF6-AG6)/Y6)) | W6: =IF(Y6=0,K6,K6*(1-(AF6-AG6)/Y6)) | X6: =$D6*(R$1+S$1+T$1+U$1+V$1+W$1) | Y6: =SUM(F6:K6) | Z6: =SUM(L6:Q6) | AA6: =Y6-SUM(R5:W5)-X6 | AB6: =AH5+Z6+Y6 | AC6: =IF(RankTF<RankNR,BF6,0)+IF(RankRR<RankNR,CJ6,0) | AD6: =MAX(0,MIN(AB6,$E6-AC6)) | AE6: =MIN(AD6,AH5+Z6) | AF6: =AD6-AE6 | AG6: =IF(DRIP="Yes",AH5+Z6-AE6,0) | AH6: =IF(DRIP="Yes",0,AH5+Z6-AE6) | AI6: =SUM(R6:W6)+AH6 | AJ6: =IF($B6=0,AV5,(AV5+$D6*AV$1)*AJ$1) | AK6: =IF($B6=0,AW5,(AW5+$D6*AW$1)*AK$1) | AL6: =IF($B6=0,AX5,(AX5+$D6*AX$1)*AL$1) | AM6: =IF($B6=0,AY5,(AY5+$D6*AY$1)*AM$1) | AN6: =IF($B6=0,AZ5,(AZ5+$D6*AZ$1)*AN$1) | AO6: =IF($B6=0,BA5,(BA5+$D6*BA$1)*AO$1) | AP6: =IF($B6=0,0,(AV5+$D6*AV$1)*AP$1) | AQ6: =IF($B6=0,0,(AW5+$D6*AW$1)*AQ$1) | AR6: =IF($B6=0,0,(AX5+$D6*AX$1)*AR$1) | AS6: =IF($B6=0,0,(AY5+$D6*AY$1)*AS$1) | AT6: =IF($B6=0,0,(AZ5+$D6*AZ$1)*AT$1) | AU6: =IF($B6=0,0,(BA5+$D6*BA$1)*AU$1) | AV6: =IF(BC6=0,AJ6,AJ6*(1-(BJ6-BK6)/BC6)) | AW6: =IF(BC6=0,AK6,AK6*(1-(BJ6-BK6)/BC6)) | AX6: =IF(BC6=0,AL6,AL6*(1-(BJ6-BK6)/BC6)) | AY6: =IF(BC6=0,AM6,AM6*(1-(BJ6-BK6)/BC6)) | AZ6: =IF(BC6=0,AN6,AN6*(1-(BJ6-BK6)/BC6)) | BA6: =IF(BC6=0,AO6,AO6*(1-(BJ6-BK6)/BC6)) | BB6: =$D6*(AV$1+AW$1+AX$1+AY$1+AZ$1+BA$1) | BC6: =SUM(AJ6:AO6) | BD6: =SUM(AP6:AU6) | BE6: =BC6-SUM(AV5:BA5)-BB6 | BF6: =BL5+BD6+BC6 | BG6: =IF(RankNR<RankTF,AB6,0)+IF(RankRR<RankTF,CJ6,0) | BH6: =MAX(0,MIN(BF6,$E6-BG6)) | BI6: =MIN(BH6,BL5+BD6) | BJ6: =BH6-BI6 | BK6: =IF(DRIP="Yes",BL5+BD6-BI6,0) | BL6: =IF(DRIP="Yes",0,BL5+BD6-BI6) | BM6: =SUM(AV6:BA6)+BL6 | BN6: =IF($B6=0,BZ5,(BZ5+$D6*BZ$1)*BN$1) | BO6: =IF($B6=0,CA5,(CA5+$D6*CA$1)*BO$1) | BP6: =IF($B6=0,CB5,(CB5+$D6*CB$1)*BP$1) | BQ6: =IF($B6=0,CC5,(CC5+$D6*CC$1)*BQ$1) | BR6: =IF($B6=0,CD5,(CD5+$D6*CD$1)*BR$1) | BS6: =IF($B6=0,CE5,(CE5+$D6*CE$1)*BS$1) | BT6: =IF($B6=0,0,(BZ5+$D6*BZ$1)*BT$1) | BU6: =IF($B6=0,0,(CA5+$D6*CA$1)*BU$1) | BV6: =IF($B6=0,0,(CB5+$D6*CB$1)*BV$1) | BW6: =IF($B6=0,0,(CC5+$D6*CC$1)*BW$1) | BX6: =IF($B6=0,0,(CD5+$D6*CD$1)*BX$1) | BY6: =IF($B6=0,0,(CE5+$D6*CE$1)*BY$1) | BZ6: =IF(CG6=0,BN6,BN6*(1-(CN6-CO6)/CG6)) | CA6: =IF(CG6=0,BO6,BO6*(1-(CN6-CO6)/CG6)) | CB6: =IF(CG6=0,BP6,BP6*(1-(CN6-CO6)/CG6)) | CC6: =IF(CG6=0,BQ6,BQ6*(1-(CN6-CO6)/CG6)) | CD6: =IF(CG6=0,BR6,BR6*(1-(CN6-CO6)/CG6)) | CE6: =IF(CG6=0,BS6,BS6*(1-(CN6-CO6)/CG6)) | CF6: =$D6*(BZ$1+CA$1+CB$1+CC$1+CD$1+CE$1) | CG6: =SUM(BN6:BS6) | CH6: =SUM(BT6:BY6) | CI6: =CG6-SUM(BZ5:CE5)-CF6 | CJ6: =CP5+CH6+CG6 | CK6: =IF(RankNR<RankRR,AB6,0)+IF(RankTF<RankRR,BF6,0) | CL6: =MAX(0,MIN(CJ6,$E6-CK6)) | CM6: =MIN(CL6,CP5+CH6) | CN6: =CL6-CM6 | CO6: =IF(DRIP="Yes",CP5+CH6-CM6,0) | CP6: =IF(DRIP="Yes",0,CP5+CH6-CM6) | CQ6: =SUM(BZ6:CE6)+CP6 | CR6: =IF(S1Type="Eligible",L6,0)+IF(S2Type="Eligible",M6,0)+IF(S3Type="Eligible",N6,0)+IF(S4Type="Eligible",O6,0)+IF(S5Type="Eligible",P6,0)+IF(S6Type="Eligible",Q6,0) | CS6: =IF(S1Type="Non-eligible",L6,0)+IF(S2Type="Non-eligible",M6,0)+IF(S3Type="Non-eligible",N6,0)+IF(S4Type="Non-eligible",O6,0)+IF(S5Type="Non-eligible",P6,0)+IF(S6Type="Non-eligible",Q6,0) | CT6: =IF(S1Type="Foreign / interest",L6,0)+IF(S2Type="Foreign / interest",M6,0)+IF(S3Type="Foreign / interest",N6,0)+IF(S4Type="Foreign / interest",O6,0)+IF(S5Type="Foreign / interest",P6,0)+IF(S6Type="Foreign / interest",Q6,0) | CU6: =CW5+X6 | CV6: =IF(Y6=0,0,AF6*(1-CU6/Y6)) | CW6: =IF(Y6=0,CU6,CU6*(1-AF6/Y6))+AG6 | CX6: =AI6+BM6+CQ6 | CY6: =AD6+BH6+CL6 | CZ6: =AE6+BI6+CM6 | DA6: =AF6+BJ6+CN6 | DB6: =IF(AND($B6=1,$E6-CY6>0.01),1,0)
A7: =A6+1 | B7: =IF($A7<=HorizonM,1,0) | C7: =INT(($A7-1)/12)+1 | D7: =IF($B7=0,0,IF(AND($A7>=CStartEff,$A7<=CEndEff),ContribMonthly*POWER(1+N(ContribEsc),INT(($A7-CStartEff)/12)),0)) | E7: 0 | F7: =IF($B7=0,R6,(R6+$D7*R$1)*F$1) | G7: =IF($B7=0,S6,(S6+$D7*S$1)*G$1) | H7: =IF($B7=0,T6,(T6+$D7*T$1)*H$1) | I7: =IF($B7=0,U6,(U6+$D7*U$1)*I$1) | J7: =IF($B7=0,V6,(V6+$D7*V$1)*J$1) | K7: =IF($B7=0,W6,(W6+$D7*W$1)*K$1) | L7: =IF($B7=0,0,(R6+$D7*R$1)*L$1) | M7: =IF($B7=0,0,(S6+$D7*S$1)*M$1) | N7: =IF($B7=0,0,(T6+$D7*T$1)*N$1) | O7: =IF($B7=0,0,(U6+$D7*U$1)*O$1) | P7: =IF($B7=0,0,(V6+$D7*V$1)*P$1) | Q7: =IF($B7=0,0,(W6+$D7*W$1)*Q$1) | R7: =IF(Y7=0,F7,F7*(1-(AF7-AG7)/Y7)) | S7: =IF(Y7=0,G7,G7*(1-(AF7-AG7)/Y7)) | T7: =IF(Y7=0,H7,H7*(1-(AF7-AG7)/Y7)) | U7: =IF(Y7=0,I7,I7*(1-(AF7-AG7)/Y7)) | V7: =IF(Y7=0,J7,J7*(1-(AF7-AG7)/Y7)) | W7: =IF(Y7=0,K7,K7*(1-(AF7-AG7)/Y7)) | X7: =$D7*(R$1+S$1+T$1+U$1+V$1+W$1) | Y7: =SUM(F7:K7) | Z7: =SUM(L7:Q7) | AA7: =Y7-SUM(R6:W6)-X7 | AB7: =AH6+Z7+Y7 | AC7: =IF(RankTF<RankNR,BF7,0)+IF(RankRR<RankNR,CJ7,0) | AD7: =MAX(0,MIN(AB7,$E7-AC7)) | AE7: =MIN(AD7,AH6+Z7) | AF7: =AD7-AE7 | AG7: =IF(DRIP="Yes",AH6+Z7-AE7,0) | AH7: =IF(DRIP="Yes",0,AH6+Z7-AE7) | AI7: =SUM(R7:W7)+AH7 | AJ7: =IF($B7=0,AV6,(AV6+$D7*AV$1)*AJ$1) | AK7: =IF($B7=0,AW6,(AW6+$D7*AW$1)*AK$1) | AL7: =IF($B7=0,AX6,(AX6+$D7*AX$1)*AL$1) | AM7: =IF($B7=0,AY6,(AY6+$D7*AY$1)*AM$1) | AN7: =IF($B7=0,AZ6,(AZ6+$D7*AZ$1)*AN$1) | AO7: =IF($B7=0,BA6,(BA6+$D7*BA$1)*AO$1) | AP7: =IF($B7=0,0,(AV6+$D7*AV$1)*AP$1) | AQ7: =IF($B7=0,0,(AW6+$D7*AW$1)*AQ$1) | AR7: =IF($B7=0,0,(AX6+$D7*AX$1)*AR$1) | AS7: =IF($B7=0,0,(AY6+$D7*AY$1)*AS$1) | AT7: =IF($B7=0,0,(AZ6+$D7*AZ$1)*AT$1) | AU7: =IF($B7=0,0,(BA6+$D7*BA$1)*AU$1) | AV7: =IF(BC7=0,AJ7,AJ7*(1-(BJ7-BK7)/BC7)) | AW7: =IF(BC7=0,AK7,AK7*(1-(BJ7-BK7)/BC7)) | AX7: =IF(BC7=0,AL7,AL7*(1-(BJ7-BK7)/BC7)) | AY7: =IF(BC7=0,AM7,AM7*(1-(BJ7-BK7)/BC7)) | AZ7: =IF(BC7=0,AN7,AN7*(1-(BJ7-BK7)/BC7)) | BA7: =IF(BC7=0,AO7,AO7*(1-(BJ7-BK7)/BC7)) | BB7: =$D7*(AV$1+AW$1+AX$1+AY$1+AZ$1+BA$1) | BC7: =SUM(AJ7:AO7) | BD7: =SUM(AP7:AU7) | BE7: =BC7-SUM(AV6:BA6)-BB7 | BF7: =BL6+BD7+BC7 | BG7: =IF(RankNR<RankTF,AB7,0)+IF(RankRR<RankTF,CJ7,0) | BH7: =MAX(0,MIN(BF7,$E7-BG7)) | BI7: =MIN(BH7,BL6+BD7) | BJ7: =BH7-BI7 | BK7: =IF(DRIP="Yes",BL6+BD7-BI7,0) | BL7: =IF(DRIP="Yes",0,BL6+BD7-BI7) | BM7: =SUM(AV7:BA7)+BL7 | BN7: =IF($B7=0,BZ6,(BZ6+$D7*BZ$1)*BN$1) | BO7: =IF($B7=0,CA6,(CA6+$D7*CA$1)*BO$1) | BP7: =IF($B7=0,CB6,(CB6+$D7*CB$1)*BP$1) | BQ7: =IF($B7=0,CC6,(CC6+$D7*CC$1)*BQ$1) | BR7: =IF($B7=0,CD6,(CD6+$D7*CD$1)*BR$1) | BS7: =IF($B7=0,CE6,(CE6+$D7*CE$1)*BS$1) | BT7: =IF($B7=0,0,(BZ6+$D7*BZ$1)*BT$1) | BU7: =IF($B7=0,0,(CA6+$D7*CA$1)*BU$1) | BV7: =IF($B7=0,0,(CB6+$D7*CB$1)*BV$1) | BW7: =IF($B7=0,0,(CC6+$D7*CC$1)*BW$1) | BX7: =IF($B7=0,0,(CD6+$D7*CD$1)*BX$1) | BY7: =IF($B7=0,0,(CE6+$D7*CE$1)*BY$1) | BZ7: =IF(CG7=0,BN7,BN7*(1-(CN7-CO7)/CG7)) | CA7: =IF(CG7=0,BO7,BO7*(1-(CN7-CO7)/CG7)) | CB7: =IF(CG7=0,BP7,BP7*(1-(CN7-CO7)/CG7)) | CC7: =IF(CG7=0,BQ7,BQ7*(1-(CN7-CO7)/CG7)) | CD7: =IF(CG7=0,BR7,BR7*(1-(CN7-CO7)/CG7)) | CE7: =IF(CG7=0,BS7,BS7*(1-(CN7-CO7)/CG7)) | CF7: =$D7*(BZ$1+CA$1+CB$1+CC$1+CD$1+CE$1) | CG7: =SUM(BN7:BS7) | CH7: =SUM(BT7:BY7) | CI7: =CG7-SUM(BZ6:CE6)-CF7 | CJ7: =CP6+CH7+CG7 | CK7: =IF(RankNR<RankRR,AB7,0)+IF(RankTF<RankRR,BF7,0) | CL7: =MAX(0,MIN(CJ7,$E7-CK7)) | CM7: =MIN(CL7,CP6+CH7) | CN7: =CL7-CM7 | CO7: =IF(DRIP="Yes",CP6+CH7-CM7,0) | CP7: =IF(DRIP="Yes",0,CP6+CH7-CM7) | CQ7: =SUM(BZ7:CE7)+CP7 | CR7: =IF(S1Type="Eligible",L7,0)+IF(S2Type="Eligible",M7,0)+IF(S3Type="Eligible",N7,0)+IF(S4Type="Eligible",O7,0)+IF(S5Type="Eligible",P7,0)+IF(S6Type="Eligible",Q7,0) | CS7: =IF(S1Type="Non-eligible",L7,0)+IF(S2Type="Non-eligible",M7,0)+IF(S3Type="Non-eligible",N7,0)+IF(S4Type="Non-eligible",O7,0)+IF(S5Type="Non-eligible",P7,0)+IF(S6Type="Non-eligible",Q7,0) | CT7: =IF(S1Type="Foreign / interest",L7,0)+IF(S2Type="Foreign / interest",M7,0)+IF(S3Type="Foreign / interest",N7,0)+IF(S4Type="Foreign / interest",O7,0)+IF(S5Type="Foreign / interest",P7,0)+IF(S6Type="Foreign / interest",Q7,0) | CU7: =CW6+X7 | CV7: =IF(Y7=0,0,AF7*(1-CU7/Y7)) | CW7: =IF(Y7=0,CU7,CU7*(1-AF7/Y7))+AG7 | CX7: =AI7+BM7+CQ7 | CY7: =AD7+BH7+CL7 | CZ7: =AE7+BI7+CM7 | DA7: =AF7+BJ7+CN7 | DB7: =IF(AND($B7=1,$E7-CY7>0.01),1,0)
A8: =A7+1 | B8: =IF($A8<=HorizonM,1,0) | C8: =INT(($A8-1)/12)+1 | D8: =IF($B8=0,0,IF(AND($A8>=CStartEff,$A8<=CEndEff),ContribMonthly*POWER(1+N(ContribEsc),INT(($A8-CStartEff)/12)),0)) | E8: 0 | F8: =IF($B8=0,R7,(R7+$D8*R$1)*F$1) | G8: =IF($B8=0,S7,(S7+$D8*S$1)*G$1) | H8: =IF($B8=0,T7,(T7+$D8*T$1)*H$1) | I8: =IF($B8=0,U7,(U7+$D8*U$1)*I$1) | J8: =IF($B8=0,V7,(V7+$D8*V$1)*J$1) | K8: =IF($B8=0,W7,(W7+$D8*W$1)*K$1) | L8: =IF($B8=0,0,(R7+$D8*R$1)*L$1) | M8: =IF($B8=0,0,(S7+$D8*S$1)*M$1) | N8: =IF($B8=0,0,(T7+$D8*T$1)*N$1) | O8: =IF($B8=0,0,(U7+$D8*U$1)*O$1) | P8: =IF($B8=0,0,(V7+$D8*V$1)*P$1) | Q8: =IF($B8=0,0,(W7+$D8*W$1)*Q$1) | R8: =IF(Y8=0,F8,F8*(1-(AF8-AG8)/Y8)) | S8: =IF(Y8=0,G8,G8*(1-(AF8-AG8)/Y8)) | T8: =IF(Y8=0,H8,H8*(1-(AF8-AG8)/Y8)) | U8: =IF(Y8=0,I8,I8*(1-(AF8-AG8)/Y8)) | V8: =IF(Y8=0,J8,J8*(1-(AF8-AG8)/Y8)) | W8: =IF(Y8=0,K8,K8*(1-(AF8-AG8)/Y8)) | X8: =$D8*(R$1+S$1+T$1+U$1+V$1+W$1) | Y8: =SUM(F8:K8) | Z8: =SUM(L8:Q8) | AA8: =Y8-SUM(R7:W7)-X8 | AB8: =AH7+Z8+Y8 | AC8: =IF(RankTF<RankNR,BF8,0)+IF(RankRR<RankNR,CJ8,0) | AD8: =MAX(0,MIN(AB8,$E8-AC8)) | AE8: =MIN(AD8,AH7+Z8) | AF8: =AD8-AE8 | AG8: =IF(DRIP="Yes",AH7+Z8-AE8,0) | AH8: =IF(DRIP="Yes",0,AH7+Z8-AE8) | AI8: =SUM(R8:W8)+AH8 | AJ8: =IF($B8=0,AV7,(AV7+$D8*AV$1)*AJ$1) | AK8: =IF($B8=0,AW7,(AW7+$D8*AW$1)*AK$1) | AL8: =IF($B8=0,AX7,(AX7+$D8*AX$1)*AL$1) | AM8: =IF($B8=0,AY7,(AY7+$D8*AY$1)*AM$1) | AN8: =IF($B8=0,AZ7,(AZ7+$D8*AZ$1)*AN$1) | AO8: =IF($B8=0,BA7,(BA7+$D8*BA$1)*AO$1) | AP8: =IF($B8=0,0,(AV7+$D8*AV$1)*AP$1) | AQ8: =IF($B8=0,0,(AW7+$D8*AW$1)*AQ$1) | AR8: =IF($B8=0,0,(AX7+$D8*AX$1)*AR$1) | AS8: =IF($B8=0,0,(AY7+$D8*AY$1)*AS$1) | AT8: =IF($B8=0,0,(AZ7+$D8*AZ$1)*AT$1) | AU8: =IF($B8=0,0,(BA7+$D8*BA$1)*AU$1) | AV8: =IF(BC8=0,AJ8,AJ8*(1-(BJ8-BK8)/BC8)) | AW8: =IF(BC8=0,AK8,AK8*(1-(BJ8-BK8)/BC8)) | AX8: =IF(BC8=0,AL8,AL8*(1-(BJ8-BK8)/BC8)) | AY8: =IF(BC8=0,AM8,AM8*(1-(BJ8-BK8)/BC8)) | AZ8: =IF(BC8=0,AN8,AN8*(1-(BJ8-BK8)/BC8)) | BA8: =IF(BC8=0,AO8,AO8*(1-(BJ8-BK8)/BC8)) | BB8: =$D8*(AV$1+AW$1+AX$1+AY$1+AZ$1+BA$1) | BC8: =SUM(AJ8:AO8) | BD8: =SUM(AP8:AU8) | BE8: =BC8-SUM(AV7:BA7)-BB8 | BF8: =BL7+BD8+BC8 | BG8: =IF(RankNR<RankTF,AB8,0)+IF(RankRR<RankTF,CJ8,0) | BH8: =MAX(0,MIN(BF8,$E8-BG8)) | BI8: =MIN(BH8,BL7+BD8) | BJ8: =BH8-BI8 | BK8: =IF(DRIP="Yes",BL7+BD8-BI8,0) | BL8: =IF(DRIP="Yes",0,BL7+BD8-BI8) | BM8: =SUM(AV8:BA8)+BL8 | BN8: =IF($B8=0,BZ7,(BZ7+$D8*BZ$1)*BN$1) | BO8: =IF($B8=0,CA7,(CA7+$D8*CA$1)*BO$1) | BP8: =IF($B8=0,CB7,(CB7+$D8*CB$1)*BP$1) | BQ8: =IF($B8=0,CC7,(CC7+$D8*CC$1)*BQ$1) | BR8: =IF($B8=0,CD7,(CD7+$D8*CD$1)*BR$1) | BS8: =IF($B8=0,CE7,(CE7+$D8*CE$1)*BS$1) | BT8: =IF($B8=0,0,(BZ7+$D8*BZ$1)*BT$1) | BU8: =IF($B8=0,0,(CA7+$D8*CA$1)*BU$1) | BV8: =IF($B8=0,0,(CB7+$D8*CB$1)*BV$1) | BW8: =IF($B8=0,0,(CC7+$D8*CC$1)*BW$1) | BX8: =IF($B8=0,0,(CD7+$D8*CD$1)*BX$1) | BY8: =IF($B8=0,0,(CE7+$D8*CE$1)*BY$1) | BZ8: =IF(CG8=0,BN8,BN8*(1-(CN8-CO8)/CG8)) | CA8: =IF(CG8=0,BO8,BO8*(1-(CN8-CO8)/CG8)) | CB8: =IF(CG8=0,BP8,BP8*(1-(CN8-CO8)/CG8)) | CC8: =IF(CG8=0,BQ8,BQ8*(1-(CN8-CO8)/CG8)) | CD8: =IF(CG8=0,BR8,BR8*(1-(CN8-CO8)/CG8)) | CE8: =IF(CG8=0,BS8,BS8*(1-(CN8-CO8)/CG8)) | CF8: =$D8*(BZ$1+CA$1+CB$1+CC$1+CD$1+CE$1) | CG8: =SUM(BN8:BS8) | CH8: =SUM(BT8:BY8) | CI8: =CG8-SUM(BZ7:CE7)-CF8 | CJ8: =CP7+CH8+CG8 | CK8: =IF(RankNR<RankRR,AB8,0)+IF(RankTF<RankRR,BF8,0) | CL8: =MAX(0,MIN(CJ8,$E8-CK8)) | CM8: =MIN(CL8,CP7+CH8) | CN8: =CL8-CM8 | CO8: =IF(DRIP="Yes",CP7+CH8-CM8,0) | CP8: =IF(DRIP="Yes",0,CP7+CH8-CM8) | CQ8: =SUM(BZ8:CE8)+CP8 | CR8: =IF(S1Type="Eligible",L8,0)+IF(S2Type="Eligible",M8,0)+IF(S3Type="Eligible",N8,0)+IF(S4Type="Eligible",O8,0)+IF(S5Type="Eligible",P8,0)+IF(S6Type="Eligible",Q8,0) | CS8: =IF(S1Type="Non-eligible",L8,0)+IF(S2Type="Non-eligible",M8,0)+IF(S3Type="Non-eligible",N8,0)+IF(S4Type="Non-eligible",O8,0)+IF(S5Type="Non-eligible",P8,0)+IF(S6Type="Non-eligible",Q8,0) | CT8: =IF(S1Type="Foreign / interest",L8,0)+IF(S2Type="Foreign / interest",M8,0)+IF(S3Type="Foreign / interest",N8,0)+IF(S4Type="Foreign / interest",O8,0)+IF(S5Type="Foreign / interest",P8,0)+IF(S6Type="Foreign / interest",Q8,0) | CU8: =CW7+X8 | CV8: =IF(Y8=0,0,AF8*(1-CU8/Y8)) | CW8: =IF(Y8=0,CU8,CU8*(1-AF8/Y8))+AG8 | CX8: =AI8+BM8+CQ8 | CY8: =AD8+BH8+CL8 | CZ8: =AE8+BI8+CM8 | DA8: =AF8+BJ8+CN8 | DB8: =IF(AND($B8=1,$E8-CY8>0.01),1,0)
A9: =A8+1 | B9: =IF($A9<=HorizonM,1,0) | C9: =INT(($A9-1)/12)+1 | D9: =IF($B9=0,0,IF(AND($A9>=CStartEff,$A9<=CEndEff),ContribMonthly*POWER(1+N(ContribEsc),INT(($A9-CStartEff)/12)),0)) | E9: 0 | F9: =IF($B9=0,R8,(R8+$D9*R$1)*F$1) | G9: =IF($B9=0,S8,(S8+$D9*S$1)*G$1) | H9: =IF($B9=0,T8,(T8+$D9*T$1)*H$1) | I9: =IF($B9=0,U8,(U8+$D9*U$1)*I$1) | J9: =IF($B9=0,V8,(V8+$D9*V$1)*J$1) | K9: =IF($B9=0,W8,(W8+$D9*W$1)*K$1) | L9: =IF($B9=0,0,(R8+$D9*R$1)*L$1) | M9: =IF($B9=0,0,(S8+$D9*S$1)*M$1) | N9: =IF($B9=0,0,(T8+$D9*T$1)*N$1) | O9: =IF($B9=0,0,(U8+$D9*U$1)*O$1) | P9: =IF($B9=0,0,(V8+$D9*V$1)*P$1) | Q9: =IF($B9=0,0,(W8+$D9*W$1)*Q$1) | R9: =IF(Y9=0,F9,F9*(1-(AF9-AG9)/Y9)) | S9: =IF(Y9=0,G9,G9*(1-(AF9-AG9)/Y9)) | T9: =IF(Y9=0,H9,H9*(1-(AF9-AG9)/Y9)) | U9: =IF(Y9=0,I9,I9*(1-(AF9-AG9)/Y9)) | V9: =IF(Y9=0,J9,J9*(1-(AF9-AG9)/Y9)) | W9: =IF(Y9=0,K9,K9*(1-(AF9-AG9)/Y9)) | X9: =$D9*(R$1+S$1+T$1+U$1+V$1+W$1) | Y9: =SUM(F9:K9) | Z9: =SUM(L9:Q9) | AA9: =Y9-SUM(R8:W8)-X9 | AB9: =AH8+Z9+Y9 | AC9: =IF(RankTF<RankNR,BF9,0)+IF(RankRR<RankNR,CJ9,0) | AD9: =MAX(0,MIN(AB9,$E9-AC9)) | AE9: =MIN(AD9,AH8+Z9) | AF9: =AD9-AE9 | AG9: =IF(DRIP="Yes",AH8+Z9-AE9,0) | AH9: =IF(DRIP="Yes",0,AH8+Z9-AE9) | AI9: =SUM(R9:W9)+AH9 | AJ9: =IF($B9=0,AV8,(AV8+$D9*AV$1)*AJ$1) | AK9: =IF($B9=0,AW8,(AW8+$D9*AW$1)*AK$1) | AL9: =IF($B9=0,AX8,(AX8+$D9*AX$1)*AL$1) | AM9: =IF($B9=0,AY8,(AY8+$D9*AY$1)*AM$1) | AN9: =IF($B9=0,AZ8,(AZ8+$D9*AZ$1)*AN$1) | AO9: =IF($B9=0,BA8,(BA8+$D9*BA$1)*AO$1) | AP9: =IF($B9=0,0,(AV8+$D9*AV$1)*AP$1) | AQ9: =IF($B9=0,0,(AW8+$D9*AW$1)*AQ$1) | AR9: =IF($B9=0,0,(AX8+$D9*AX$1)*AR$1) | AS9: =IF($B9=0,0,(AY8+$D9*AY$1)*AS$1) | AT9: =IF($B9=0,0,(AZ8+$D9*AZ$1)*AT$1) | AU9: =IF($B9=0,0,(BA8+$D9*BA$1)*AU$1) | AV9: =IF(BC9=0,AJ9,AJ9*(1-(BJ9-BK9)/BC9)) | AW9: =IF(BC9=0,AK9,AK9*(1-(BJ9-BK9)/BC9)) | AX9: =IF(BC9=0,AL9,AL9*(1-(BJ9-BK9)/BC9)) | AY9: =IF(BC9=0,AM9,AM9*(1-(BJ9-BK9)/BC9)) | AZ9: =IF(BC9=0,AN9,AN9*(1-(BJ9-BK9)/BC9)) | BA9: =IF(BC9=0,AO9,AO9*(1-(BJ9-BK9)/BC9)) | BB9: =$D9*(AV$1+AW$1+AX$1+AY$1+AZ$1+BA$1) | BC9: =SUM(AJ9:AO9) | BD9: =SUM(AP9:AU9) | BE9: =BC9-SUM(AV8:BA8)-BB9 | BF9: =BL8+BD9+BC9 | BG9: =IF(RankNR<RankTF,AB9,0)+IF(RankRR<RankTF,CJ9,0) | BH9: =MAX(0,MIN(BF9,$E9-BG9)) | BI9: =MIN(BH9,BL8+BD9) | BJ9: =BH9-BI9 | BK9: =IF(DRIP="Yes",BL8+BD9-BI9,0) | BL9: =IF(DRIP="Yes",0,BL8+BD9-BI9) | BM9: =SUM(AV9:BA9)+BL9 | BN9: =IF($B9=0,BZ8,(BZ8+$D9*BZ$1)*BN$1) | BO9: =IF($B9=0,CA8,(CA8+$D9*CA$1)*BO$1) | BP9: =IF($B9=0,CB8,(CB8+$D9*CB$1)*BP$1) | BQ9: =IF($B9=0,CC8,(CC8+$D9*CC$1)*BQ$1) | BR9: =IF($B9=0,CD8,(CD8+$D9*CD$1)*BR$1) | BS9: =IF($B9=0,CE8,(CE8+$D9*CE$1)*BS$1) | BT9: =IF($B9=0,0,(BZ8+$D9*BZ$1)*BT$1) | BU9: =IF($B9=0,0,(CA8+$D9*CA$1)*BU$1) | BV9: =IF($B9=0,0,(CB8+$D9*CB$1)*BV$1) | BW9: =IF($B9=0,0,(CC8+$D9*CC$1)*BW$1) | BX9: =IF($B9=0,0,(CD8+$D9*CD$1)*BX$1) | BY9: =IF($B9=0,0,(CE8+$D9*CE$1)*BY$1) | BZ9: =IF(CG9=0,BN9,BN9*(1-(CN9-CO9)/CG9)) | CA9: =IF(CG9=0,BO9,BO9*(1-(CN9-CO9)/CG9)) | CB9: =IF(CG9=0,BP9,BP9*(1-(CN9-CO9)/CG9)) | CC9: =IF(CG9=0,BQ9,BQ9*(1-(CN9-CO9)/CG9)) | CD9: =IF(CG9=0,BR9,BR9*(1-(CN9-CO9)/CG9)) | CE9: =IF(CG9=0,BS9,BS9*(1-(CN9-CO9)/CG9)) | CF9: =$D9*(BZ$1+CA$1+CB$1+CC$1+CD$1+CE$1) | CG9: =SUM(BN9:BS9) | CH9: =SUM(BT9:BY9) | CI9: =CG9-SUM(BZ8:CE8)-CF9 | CJ9: =CP8+CH9+CG9 | CK9: =IF(RankNR<RankRR,AB9,0)+IF(RankTF<RankRR,BF9,0) | CL9: =MAX(0,MIN(CJ9,$E9-CK9)) | CM9: =MIN(CL9,CP8+CH9) | CN9: =CL9-CM9 | CO9: =IF(DRIP="Yes",CP8+CH9-CM9,0) | CP9: =IF(DRIP="Yes",0,CP8+CH9-CM9) | CQ9: =SUM(BZ9:CE9)+CP9 | CR9: =IF(S1Type="Eligible",L9,0)+IF(S2Type="Eligible",M9,0)+IF(S3Type="Eligible",N9,0)+IF(S4Type="Eligible",O9,0)+IF(S5Type="Eligible",P9,0)+IF(S6Type="Eligible",Q9,0) | CS9: =IF(S1Type="Non-eligible",L9,0)+IF(S2Type="Non-eligible",M9,0)+IF(S3Type="Non-eligible",N9,0)+IF(S4Type="Non-eligible",O9,0)+IF(S5Type="Non-eligible",P9,0)+IF(S6Type="Non-eligible",Q9,0) | CT9: =IF(S1Type="Foreign / interest",L9,0)+IF(S2Type="Foreign / interest",M9,0)+IF(S3Type="Foreign / interest",N9,0)+IF(S4Type="Foreign / interest",O9,0)+IF(S5Type="Foreign / interest",P9,0)+IF(S6Type="Foreign / interest",Q9,0) | CU9: =CW8+X9 | CV9: =IF(Y9=0,0,AF9*(1-CU9/Y9)) | CW9: =IF(Y9=0,CU9,CU9*(1-AF9/Y9))+AG9 | CX9: =AI9+BM9+CQ9 | CY9: =AD9+BH9+CL9 | CZ9: =AE9+BI9+CM9 | DA9: =AF9+BJ9+CN9 | DB9: =IF(AND($B9=1,$E9-CY9>0.01),1,0)
A10: =A9+1 | B10: =IF($A10<=HorizonM,1,0) | C10: =INT(($A10-1)/12)+1 | D10: =IF($B10=0,0,IF(AND($A10>=CStartEff,$A10<=CEndEff),ContribMonthly*POWER(1+N(ContribEsc),INT(($A10-CStartEff)/12)),0)) | E10: 0 | F10: =IF($B10=0,R9,(R9+$D10*R$1)*F$1) | G10: =IF($B10=0,S9,(S9+$D10*S$1)*G$1) | H10: =IF($B10=0,T9,(T9+$D10*T$1)*H$1) | I10: =IF($B10=0,U9,(U9+$D10*U$1)*I$1) | J10: =IF($B10=0,V9,(V9+$D10*V$1)*J$1) | K10: =IF($B10=0,W9,(W9+$D10*W$1)*K$1) | L10: =IF($B10=0,0,(R9+$D10*R$1)*L$1) | M10: =IF($B10=0,0,(S9+$D10*S$1)*M$1) | N10: =IF($B10=0,0,(T9+$D10*T$1)*N$1) | O10: =IF($B10=0,0,(U9+$D10*U$1)*O$1) | P10: =IF($B10=0,0,(V9+$D10*V$1)*P$1) | Q10: =IF($B10=0,0,(W9+$D10*W$1)*Q$1) | R10: =IF(Y10=0,F10,F10*(1-(AF10-AG10)/Y10)) | S10: =IF(Y10=0,G10,G10*(1-(AF10-AG10)/Y10)) | T10: =IF(Y10=0,H10,H10*(1-(AF10-AG10)/Y10)) | U10: =IF(Y10=0,I10,I10*(1-(AF10-AG10)/Y10)) | V10: =IF(Y10=0,J10,J10*(1-(AF10-AG10)/Y10)) | W10: =IF(Y10=0,K10,K10*(1-(AF10-AG10)/Y10)) | X10: =$D10*(R$1+S$1+T$1+U$1+V$1+W$1) | Y10: =SUM(F10:K10) | Z10: =SUM(L10:Q10) | AA10: =Y10-SUM(R9:W9)-X10 | AB10: =AH9+Z10+Y10 | AC10: =IF(RankTF<RankNR,BF10,0)+IF(RankRR<RankNR,CJ10,0) | AD10: =MAX(0,MIN(AB10,$E10-AC10)) | AE10: =MIN(AD10,AH9+Z10) | AF10: =AD10-AE10 | AG10: =IF(DRIP="Yes",AH9+Z10-AE10,0) | AH10: =IF(DRIP="Yes",0,AH9+Z10-AE10) | AI10: =SUM(R10:W10)+AH10 | AJ10: =IF($B10=0,AV9,(AV9+$D10*AV$1)*AJ$1) | AK10: =IF($B10=0,AW9,(AW9+$D10*AW$1)*AK$1) | AL10: =IF($B10=0,AX9,(AX9+$D10*AX$1)*AL$1) | AM10: =IF($B10=0,AY9,(AY9+$D10*AY$1)*AM$1) | AN10: =IF($B10=0,AZ9,(AZ9+$D10*AZ$1)*AN$1) | AO10: =IF($B10=0,BA9,(BA9+$D10*BA$1)*AO$1) | AP10: =IF($B10=0,0,(AV9+$D10*AV$1)*AP$1) | AQ10: =IF($B10=0,0,(AW9+$D10*AW$1)*AQ$1) | AR10: =IF($B10=0,0,(AX9+$D10*AX$1)*AR$1) | AS10: =IF($B10=0,0,(AY9+$D10*AY$1)*AS$1) | AT10: =IF($B10=0,0,(AZ9+$D10*AZ$1)*AT$1) | AU10: =IF($B10=0,0,(BA9+$D10*BA$1)*AU$1) | AV10: =IF(BC10=0,AJ10,AJ10*(1-(BJ10-BK10)/BC10)) | AW10: =IF(BC10=0,AK10,AK10*(1-(BJ10-BK10)/BC10)) | AX10: =IF(BC10=0,AL10,AL10*(1-(BJ10-BK10)/BC10)) | AY10: =IF(BC10=0,AM10,AM10*(1-(BJ10-BK10)/BC10)) | AZ10: =IF(BC10=0,AN10,AN10*(1-(BJ10-BK10)/BC10)) | BA10: =IF(BC10=0,AO10,AO10*(1-(BJ10-BK10)/BC10)) | BB10: =$D10*(AV$1+AW$1+AX$1+AY$1+AZ$1+BA$1) | BC10: =SUM(AJ10:AO10) | BD10: =SUM(AP10:AU10) | BE10: =BC10-SUM(AV9:BA9)-BB10 | BF10: =BL9+BD10+BC10 | BG10: =IF(RankNR<RankTF,AB10,0)+IF(RankRR<RankTF,CJ10,0) | BH10: =MAX(0,MIN(BF10,$E10-BG10)) | BI10: =MIN(BH10,BL9+BD10) | BJ10: =BH10-BI10 | BK10: =IF(DRIP="Yes",BL9+BD10-BI10,0) | BL10: =IF(DRIP="Yes",0,BL9+BD10-BI10) | BM10: =SUM(AV10:BA10)+BL10 | BN10: =IF($B10=0,BZ9,(BZ9+$D10*BZ$1)*BN$1) | BO10: =IF($B10=0,CA9,(CA9+$D10*CA$1)*BO$1) | BP10: =IF($B10=0,CB9,(CB9+$D10*CB$1)*BP$1) | BQ10: =IF($B10=0,CC9,(CC9+$D10*CC$1)*BQ$1) | BR10: =IF($B10=0,CD9,(CD9+$D10*CD$1)*BR$1) | BS10: =IF($B10=0,CE9,(CE9+$D10*CE$1)*BS$1) | BT10: =IF($B10=0,0,(BZ9+$D10*BZ$1)*BT$1) | BU10: =IF($B10=0,0,(CA9+$D10*CA$1)*BU$1) | BV10: =IF($B10=0,0,(CB9+$D10*CB$1)*BV$1) | BW10: =IF($B10=0,0,(CC9+$D10*CC$1)*BW$1) | BX10: =IF($B10=0,0,(CD9+$D10*CD$1)*BX$1) | BY10: =IF($B10=0,0,(CE9+$D10*CE$1)*BY$1) | BZ10: =IF(CG10=0,BN10,BN10*(1-(CN10-CO10)/CG10)) | CA10: =IF(CG10=0,BO10,BO10*(1-(CN10-CO10)/CG10)) | CB10: =IF(CG10=0,BP10,BP10*(1-(CN10-CO10)/CG10)) | CC10: =IF(CG10=0,BQ10,BQ10*(1-(CN10-CO10)/CG10)) | CD10: =IF(CG10=0,BR10,BR10*(1-(CN10-CO10)/CG10)) | CE10: =IF(CG10=0,BS10,BS10*(1-(CN10-CO10)/CG10)) | CF10: =$D10*(BZ$1+CA$1+CB$1+CC$1+CD$1+CE$1) | CG10: =SUM(BN10:BS10) | CH10: =SUM(BT10:BY10) | CI10: =CG10-SUM(BZ9:CE9)-CF10 | CJ10: =CP9+CH10+CG10 | CK10: =IF(RankNR<RankRR,AB10,0)+IF(RankTF<RankRR,BF10,0) | CL10: =MAX(0,MIN(CJ10,$E10-CK10)) | CM10: =MIN(CL10,CP9+CH10) | CN10: =CL10-CM10 | CO10: =IF(DRIP="Yes",CP9+CH10-CM10,0) | CP10: =IF(DRIP="Yes",0,CP9+CH10-CM10) | CQ10: =SUM(BZ10:CE10)+CP10 | CR10: =IF(S1Type="Eligible",L10,0)+IF(S2Type="Eligible",M10,0)+IF(S3Type="Eligible",N10,0)+IF(S4Type="Eligible",O10,0)+IF(S5Type="Eligible",P10,0)+IF(S6Type="Eligible",Q10,0) | CS10: =IF(S1Type="Non-eligible",L10,0)+IF(S2Type="Non-eligible",M10,0)+IF(S3Type="Non-eligible",N10,0)+IF(S4Type="Non-eligible",O10,0)+IF(S5Type="Non-eligible",P10,0)+IF(S6Type="Non-eligible",Q10,0) | CT10: =IF(S1Type="Foreign / interest",L10,0)+IF(S2Type="Foreign / interest",M10,0)+IF(S3Type="Foreign / interest",N10,0)+IF(S4Type="Foreign / interest",O10,0)+IF(S5Type="Foreign / interest",P10,0)+IF(S6Type="Foreign / interest",Q10,0) | CU10: =CW9+X10 | CV10: =IF(Y10=0,0,AF10*(1-CU10/Y10)) | CW10: =IF(Y10=0,CU10,CU10*(1-AF10/Y10))+AG10 | CX10: =AI10+BM10+CQ10 | CY10: =AD10+BH10+CL10 | CZ10: =AE10+BI10+CM10 | DA10: =AF10+BJ10+CN10 | DB10: =IF(AND($B10=1,$E10-CY10>0.01),1,0)
A11: =A10+1 | B11: =IF($A11<=HorizonM,1,0) | C11: =INT(($A11-1)/12)+1 | D11: =IF($B11=0,0,IF(AND($A11>=CStartEff,$A11<=CEndEff),ContribMonthly*POWER(1+N(ContribEsc),INT(($A11-CStartEff)/12)),0)) | E11: 0 | F11: =IF($B11=0,R10,(R10+$D11*R$1)*F$1) | G11: =IF($B11=0,S10,(S10+$D11*S$1)*G$1) | H11: =IF($B11=0,T10,(T10+$D11*T$1)*H$1) | I11: =IF($B11=0,U10,(U10+$D11*U$1)*I$1) | J11: =IF($B11=0,V10,(V10+$D11*V$1)*J$1) | K11: =IF($B11=0,W10,(W10+$D11*W$1)*K$1) | L11: =IF($B11=0,0,(R10+$D11*R$1)*L$1) | M11: =IF($B11=0,0,(S10+$D11*S$1)*M$1) | N11: =IF($B11=0,0,(T10+$D11*T$1)*N$1) | O11: =IF($B11=0,0,(U10+$D11*U$1)*O$1) | P11: =IF($B11=0,0,(V10+$D11*V$1)*P$1) | Q11: =IF($B11=0,0,(W10+$D11*W$1)*Q$1) | R11: =IF(Y11=0,F11,F11*(1-(AF11-AG11)/Y11)) | S11: =IF(Y11=0,G11,G11*(1-(AF11-AG11)/Y11)) | T11: =IF(Y11=0,H11,H11*(1-(AF11-AG11)/Y11)) | U11: =IF(Y11=0,I11,I11*(1-(AF11-AG11)/Y11)) | V11: =IF(Y11=0,J11,J11*(1-(AF11-AG11)/Y11)) | W11: =IF(Y11=0,K11,K11*(1-(AF11-AG11)/Y11)) | X11: =$D11*(R$1+S$1+T$1+U$1+V$1+W$1) | Y11: =SUM(F11:K11) | Z11: =SUM(L11:Q11) | AA11: =Y11-SUM(R10:W10)-X11 | AB11: =AH10+Z11+Y11 | AC11: =IF(RankTF<RankNR,BF11,0)+IF(RankRR<RankNR,CJ11,0) | AD11: =MAX(0,MIN(AB11,$E11-AC11)) | AE11: =MIN(AD11,AH10+Z11) | AF11: =AD11-AE11 | AG11: =IF(DRIP="Yes",AH10+Z11-AE11,0) | AH11: =IF(DRIP="Yes",0,AH10+Z11-AE11) | AI11: =SUM(R11:W11)+AH11 | AJ11: =IF($B11=0,AV10,(AV10+$D11*AV$1)*AJ$1) | AK11: =IF($B11=0,AW10,(AW10+$D11*AW$1)*AK$1) | AL11: =IF($B11=0,AX10,(AX10+$D11*AX$1)*AL$1) | AM11: =IF($B11=0,AY10,(AY10+$D11*AY$1)*AM$1) | AN11: =IF($B11=0,AZ10,(AZ10+$D11*AZ$1)*AN$1) | AO11: =IF($B11=0,BA10,(BA10+$D11*BA$1)*AO$1) | AP11: =IF($B11=0,0,(AV10+$D11*AV$1)*AP$1) | AQ11: =IF($B11=0,0,(AW10+$D11*AW$1)*AQ$1) | AR11: =IF($B11=0,0,(AX10+$D11*AX$1)*AR$1) | AS11: =IF($B11=0,0,(AY10+$D11*AY$1)*AS$1) | AT11: =IF($B11=0,0,(AZ10+$D11*AZ$1)*AT$1) | AU11: =IF($B11=0,0,(BA10+$D11*BA$1)*AU$1) | AV11: =IF(BC11=0,AJ11,AJ11*(1-(BJ11-BK11)/BC11)) | AW11: =IF(BC11=0,AK11,AK11*(1-(BJ11-BK11)/BC11)) | AX11: =IF(BC11=0,AL11,AL11*(1-(BJ11-BK11)/BC11)) | AY11: =IF(BC11=0,AM11,AM11*(1-(BJ11-BK11)/BC11)) | AZ11: =IF(BC11=0,AN11,AN11*(1-(BJ11-BK11)/BC11)) | BA11: =IF(BC11=0,AO11,AO11*(1-(BJ11-BK11)/BC11)) | BB11: =$D11*(AV$1+AW$1+AX$1+AY$1+AZ$1+BA$1) | BC11: =SUM(AJ11:AO11) | BD11: =SUM(AP11:AU11) | BE11: =BC11-SUM(AV10:BA10)-BB11 | BF11: =BL10+BD11+BC11 | BG11: =IF(RankNR<RankTF,AB11,0)+IF(RankRR<RankTF,CJ11,0) | BH11: =MAX(0,MIN(BF11,$E11-BG11)) | BI11: =MIN(BH11,BL10+BD11) | BJ11: =BH11-BI11 | BK11: =IF(DRIP="Yes",BL10+BD11-BI11,0) | BL11: =IF(DRIP="Yes",0,BL10+BD11-BI11) | BM11: =SUM(AV11:BA11)+BL11 | BN11: =IF($B11=0,BZ10,(BZ10+$D11*BZ$1)*BN$1) | BO11: =IF($B11=0,CA10,(CA10+$D11*CA$1)*BO$1) | BP11: =IF($B11=0,CB10,(CB10+$D11*CB$1)*BP$1) | BQ11: =IF($B11=0,CC10,(CC10+$D11*CC$1)*BQ$1) | BR11: =IF($B11=0,CD10,(CD10+$D11*CD$1)*BR$1) | BS11: =IF($B11=0,CE10,(CE10+$D11*CE$1)*BS$1) | BT11: =IF($B11=0,0,(BZ10+$D11*BZ$1)*BT$1) | BU11: =IF($B11=0,0,(CA10+$D11*CA$1)*BU$1) | BV11: =IF($B11=0,0,(CB10+$D11*CB$1)*BV$1) | BW11: =IF($B11=0,0,(CC10+$D11*CC$1)*BW$1) | BX11: =IF($B11=0,0,(CD10+$D11*CD$1)*BX$1) | BY11: =IF($B11=0,0,(CE10+$D11*CE$1)*BY$1) | BZ11: =IF(CG11=0,BN11,BN11*(1-(CN11-CO11)/CG11)) | CA11: =IF(CG11=0,BO11,BO11*(1-(CN11-CO11)/CG11)) | CB11: =IF(CG11=0,BP11,BP11*(1-(CN11-CO11)/CG11)) | CC11: =IF(CG11=0,BQ11,BQ11*(1-(CN11-CO11)/CG11)) | CD11: =IF(CG11=0,BR11,BR11*(1-(CN11-CO11)/CG11)) | CE11: =IF(CG11=0,BS11,BS11*(1-(CN11-CO11)/CG11)) | CF11: =$D11*(BZ$1+CA$1+CB$1+CC$1+CD$1+CE$1) | CG11: =SUM(BN11:BS11) | CH11: =SUM(BT11:BY11) | CI11: =CG11-SUM(BZ10:CE10)-CF11 | CJ11: =CP10+CH11+CG11 | CK11: =IF(RankNR<RankRR,AB11,0)+IF(RankTF<RankRR,BF11,0) | CL11: =MAX(0,MIN(CJ11,$E11-CK11)) | CM11: =MIN(CL11,CP10+CH11) | CN11: =CL11-CM11 | CO11: =IF(DRIP="Yes",CP10+CH11-CM11,0) | CP11: =IF(DRIP="Yes",0,CP10+CH11-CM11) | CQ11: =SUM(BZ11:CE11)+CP11 | CR11: =IF(S1Type="Eligible",L11,0)+IF(S2Type="Eligible",M11,0)+IF(S3Type="Eligible",N11,0)+IF(S4Type="Eligible",O11,0)+IF(S5Type="Eligible",P11,0)+IF(S6Type="Eligible",Q11,0) | CS11: =IF(S1Type="Non-eligible",L11,0)+IF(S2Type="Non-eligible",M11,0)+IF(S3Type="Non-eligible",N11,0)+IF(S4Type="Non-eligible",O11,0)+IF(S5Type="Non-eligible",P11,0)+IF(S6Type="Non-eligible",Q11,0) | CT11: =IF(S1Type="Foreign / interest",L11,0)+IF(S2Type="Foreign / interest",M11,0)+IF(S3Type="Foreign / interest",N11,0)+IF(S4Type="Foreign / interest",O11,0)+IF(S5Type="Foreign / interest",P11,0)+IF(S6Type="Foreign / interest",Q11,0) | CU11: =CW10+X11 | CV11: =IF(Y11=0,0,AF11*(1-CU11/Y11)) | CW11: =IF(Y11=0,CU11,CU11*(1-AF11/Y11))+AG11 | CX11: =AI11+BM11+CQ11 | CY11: =AD11+BH11+CL11 | CZ11: =AE11+BI11+CM11 | DA11: =AF11+BJ11+CN11 | DB11: =IF(AND($B11=1,$E11-CY11>0.01),1,0)
A12: =A11+1 | B12: =IF($A12<=HorizonM,1,0) | C12: =INT(($A12-1)/12)+1 | D12: =IF($B12=0,0,IF(AND($A12>=CStartEff,$A12<=CEndEff),ContribMonthly*POWER(1+N(ContribEsc),INT(($A12-CStartEff)/12)),0)) | E12: 0 | F12: =IF($B12=0,R11,(R11+$D12*R$1)*F$1) | G12: =IF($B12=0,S11,(S11+$D12*S$1)*G$1) | H12: =IF($B12=0,T11,(T11+$D12*T$1)*H$1) | I12: =IF($B12=0,U11,(U11+$D12*U$1)*I$1) | J12: =IF($B12=0,V11,(V11+$D12*V$1)*J$1) | K12: =IF($B12=0,W11,(W11+$D12*W$1)*K$1) | L12: =IF($B12=0,0,(R11+$D12*R$1)*L$1) | M12: =IF($B12=0,0,(S11+$D12*S$1)*M$1) | N12: =IF($B12=0,0,(T11+$D12*T$1)*N$1) | O12: =IF($B12=0,0,(U11+$D12*U$1)*O$1) | P12: =IF($B12=0,0,(V11+$D12*V$1)*P$1) | Q12: =IF($B12=0,0,(W11+$D12*W$1)*Q$1) | R12: =IF(Y12=0,F12,F12*(1-(AF12-AG12)/Y12)) | S12: =IF(Y12=0,G12,G12*(1-(AF12-AG12)/Y12)) | T12: =IF(Y12=0,H12,H12*(1-(AF12-AG12)/Y12)) | U12: =IF(Y12=0,I12,I12*(1-(AF12-AG12)/Y12)) | V12: =IF(Y12=0,J12,J12*(1-(AF12-AG12)/Y12)) | W12: =IF(Y12=0,K12,K12*(1-(AF12-AG12)/Y12)) | X12: =$D12*(R$1+S$1+T$1+U$1+V$1+W$1) | Y12: =SUM(F12:K12) | Z12: =SUM(L12:Q12) | AA12: =Y12-SUM(R11:W11)-X12 | AB12: =AH11+Z12+Y12 | AC12: =IF(RankTF<RankNR,BF12,0)+IF(RankRR<RankNR,CJ12,0) | AD12: =MAX(0,MIN(AB12,$E12-AC12)) | AE12: =MIN(AD12,AH11+Z12) | AF12: =AD12-AE12 | AG12: =IF(DRIP="Yes",AH11+Z12-AE12,0) | AH12: =IF(DRIP="Yes",0,AH11+Z12-AE12) | AI12: =SUM(R12:W12)+AH12 | AJ12: =IF($B12=0,AV11,(AV11+$D12*AV$1)*AJ$1) | AK12: =IF($B12=0,AW11,(AW11+$D12*AW$1)*AK$1) | AL12: =IF($B12=0,AX11,(AX11+$D12*AX$1)*AL$1) | AM12: =IF($B12=0,AY11,(AY11+$D12*AY$1)*AM$1) | AN12: =IF($B12=0,AZ11,(AZ11+$D12*AZ$1)*AN$1) | AO12: =IF($B12=0,BA11,(BA11+$D12*BA$1)*AO$1) | AP12: =IF($B12=0,0,(AV11+$D12*AV$1)*AP$1) | AQ12: =IF($B12=0,0,(AW11+$D12*AW$1)*AQ$1) | AR12: =IF($B12=0,0,(AX11+$D12*AX$1)*AR$1) | AS12: =IF($B12=0,0,(AY11+$D12*AY$1)*AS$1) | AT12: =IF($B12=0,0,(AZ11+$D12*AZ$1)*AT$1) | AU12: =IF($B12=0,0,(BA11+$D12*BA$1)*AU$1) | AV12: =IF(BC12=0,AJ12,AJ12*(1-(BJ12-BK12)/BC12)) | AW12: =IF(BC12=0,AK12,AK12*(1-(BJ12-BK12)/BC12)) | AX12: =IF(BC12=0,AL12,AL12*(1-(BJ12-BK12)/BC12)) | AY12: =IF(BC12=0,AM12,AM12*(1-(BJ12-BK12)/BC12)) | AZ12: =IF(BC12=0,AN12,AN12*(1-(BJ12-BK12)/BC12)) | BA12: =IF(BC12=0,AO12,AO12*(1-(BJ12-BK12)/BC12)) | BB12: =$D12*(AV$1+AW$1+AX$1+AY$1+AZ$1+BA$1) | BC12: =SUM(AJ12:AO12) | BD12: =SUM(AP12:AU12) | BE12: =BC12-SUM(AV11:BA11)-BB12 | BF12: =BL11+BD12+BC12 | BG12: =IF(RankNR<RankTF,AB12,0)+IF(RankRR<RankTF,CJ12,0) | BH12: =MAX(0,MIN(BF12,$E12-BG12)) | BI12: =MIN(BH12,BL11+BD12) | BJ12: =BH12-BI12 | BK12: =IF(DRIP="Yes",BL11+BD12-BI12,0) | BL12: =IF(DRIP="Yes",0,BL11+BD12-BI12) | BM12: =SUM(AV12:BA12)+BL12 | BN12: =IF($B12=0,BZ11,(BZ11+$D12*BZ$1)*BN$1) | BO12: =IF($B12=0,CA11,(CA11+$D12*CA$1)*BO$1) | BP12: =IF($B12=0,CB11,(CB11+$D12*CB$1)*BP$1) | BQ12: =IF($B12=0,CC11,(CC11+$D12*CC$1)*BQ$1) | BR12: =IF($B12=0,CD11,(CD11+$D12*CD$1)*BR$1) | BS12: =IF($B12=0,CE11,(CE11+$D12*CE$1)*BS$1) | BT12: =IF($B12=0,0,(BZ11+$D12*BZ$1)*BT$1) | BU12: =IF($B12=0,0,(CA11+$D12*CA$1)*BU$1) | BV12: =IF($B12=0,0,(CB11+$D12*CB$1)*BV$1) | BW12: =IF($B12=0,0,(CC11+$D12*CC$1)*BW$1) | BX12: =IF($B12=0,0,(CD11+$D12*CD$1)*BX$1) | BY12: =IF($B12=0,0,(CE11+$D12*CE$1)*BY$1) | BZ12: =IF(CG12=0,BN12,BN12*(1-(CN12-CO12)/CG12)) | CA12: =IF(CG12=0,BO12,BO12*(1-(CN12-CO12)/CG12)) | CB12: =IF(CG12=0,BP12,BP12*(1-(CN12-CO12)/CG12)) | CC12: =IF(CG12=0,BQ12,BQ12*(1-(CN12-CO12)/CG12)) | CD12: =IF(CG12=0,BR12,BR12*(1-(CN12-CO12)/CG12)) | CE12: =IF(CG12=0,BS12,BS12*(1-(CN12-CO12)/CG12)) | CF12: =$D12*(BZ$1+CA$1+CB$1+CC$1+CD$1+CE$1) | CG12: =SUM(BN12:BS12) | CH12: =SUM(BT12:BY12) | CI12: =CG12-SUM(BZ11:CE11)-CF12 | CJ12: =CP11+CH12+CG12 | CK12: =IF(RankNR<RankRR,AB12,0)+IF(RankTF<RankRR,BF12,0) | CL12: =MAX(0,MIN(CJ12,$E12-CK12)) | CM12: =MIN(CL12,CP11+CH12) | CN12: =CL12-CM12 | CO12: =IF(DRIP="Yes",CP11+CH12-CM12,0) | CP12: =IF(DRIP="Yes",0,CP11+CH12-CM12) | CQ12: =SUM(BZ12:CE12)+CP12 | CR12: =IF(S1Type="Eligible",L12,0)+IF(S2Type="Eligible",M12,0)+IF(S3Type="Eligible",N12,0)+IF(S4Type="Eligible",O12,0)+IF(S5Type="Eligible",P12,0)+IF(S6Type="Eligible",Q12,0) | CS12: =IF(S1Type="Non-eligible",L12,0)+IF(S2Type="Non-eligible",M12,0)+IF(S3Type="Non-eligible",N12,0)+IF(S4Type="Non-eligible",O12,0)+IF(S5Type="Non-eligible",P12,0)+IF(S6Type="Non-eligible",Q12,0) | CT12: =IF(S1Type="Foreign / interest",L12,0)+IF(S2Type="Foreign / interest",M12,0)+IF(S3Type="Foreign / interest",N12,0)+IF(S4Type="Foreign / interest",O12,0)+IF(S5Type="Foreign / interest",P12,0)+IF(S6Type="Foreign / interest",Q12,0) | CU12: =CW11+X12 | CV12: =IF(Y12=0,0,AF12*(1-CU12/Y12)) | CW12: =IF(Y12=0,CU12,CU12*(1-AF12/Y12))+AG12 | CX12: =AI12+BM12+CQ12 | CY12: =AD12+BH12+CL12 | CZ12: =AE12+BI12+CM12 | DA12: =AF12+BJ12+CN12 | DB12: =IF(AND($B12=1,$E12-CY12>0.01),1,0)
